Workbook
Name _: #REF!
Name _: #REF!
Name _: #REF!
Name _: #REF!
Name _: #REF!
Name ___GR2: #REF!
Name ___GR2: #REF!
Name ___GR2: #REF!
Name ___GR2: #REF!
Name ___GR2: #REF!
Name ___GR2: #REF!
Name ___GR2: #REF!
Name ___GR2: #REF!
Name ___GR2: #REF!
Name ___GR2: #REF!
Name ___GR2: #REF!
Name ___GR2: #REF!
Name __age1: #REF!
Name __age1: #REF!
Name __age1: #REF!
Name __age1: #REF!
Name __age1: #REF!
Name __age1: #REF!
Name __age1: #REF!
Name __age1: #REF!
Name __age10: #REF!
Name __age10: #REF!
Name __age10: #REF!
Name __age10: #REF!
Name __age10: #REF!
Name __age12: #REF!
Name __age12: #REF!
Name __age12: #REF!
Name __age12: #REF!
Name __age12: #REF!
Name __age15: #REF!
Name __age15: #REF!
Name __age15: #REF!
Name __age20: #REF!
Name __age20: #REF!
Name __age20: #REF!
Name __age25: #REF!
Name __age25: #REF!
Name __age25: #REF!
Name __age30: #REF!
Name __age30: #REF!
Name __age30: #REF!
Name __age35: #REF!
Name __age35: #REF!
Name __age35: #REF!
Name __age5: #REF!
Name __age5: #REF!
Name __age5: #REF!
Name __age7: #REF!
Name __age7: #REF!
Name __age7: #REF!
Name __CHF2001: #REF!
Name __CHF2001: #REF!
Name __CHF2001: #REF!
Name __DEP1: #REF!

Sheet WACC_SECTOR GREEN ENERGY (2)
B1: DATOS | C1: FUENTE | G1: VALORES | H1: OBSERVACIÓN
B2: BETA DESAPALANCADA DE LA IND. | C2: http://pages.stern.nyu.edu/~adamodar/New_Home_Page/datafile/Betas.html | G2: =+'Betas 2025'!I117 -> 0.9791328 | H2: 2023
B3: D/E = APALANCAMIENTO | C3: http://pages.stern.nyu.edu/~adamodar/New_Home_Page/datafile/Betas.html | G3: =+'Betas 2025'!D117 -> 0.1792 | H3: 2023
B4: TASA LIBRE DE RIESGO | C4: Tbon 10 años (últimos 20 años) | G4: #REF! | H4: 44951
B5: PREMIO POR RIESGO | C5: http://pages.stern.nyu.edu/~adamodar/New_Home_Page/datafile/ctryprem.html | G5: #REF! | H5: 2023
B6: RIESGO PAÍS | C6: https://estadisticas.bcrp.gob.pe/estadisticas/series/diarias/resultados/PD04713XD/html | G6: 0.0363 | H6: 44944
B8: BETA DESAPALANCADA DE LA IND. | C8: Bu | D8: =+G2 -> 0.9791328
B9: D/E = APALANCAMIENTO | C9: D/P | D9: =+G3 -> 0.1792
B10: TASA DE IMPUESTOS | C10: t | D10: 0.3
B11: BETA APALANCADA DE LA EMPRESA | C11: BL | D11: =+D8*(1+(1-D10)*D9) -> 1.1019552
B14: CÁLCULO DE TASA DE DESCUENTO (ke) | F14: CÁLCULO DE TASA DE DESCUENTO (WACC)
B16: fórmula a utilizar (1) | F16: fórmula a utilizar (2)
B17: Ke= Rf + (Rm-Rf)B + Rp + SCP
B19: Ke= | C19: =C22+(C24)*C23+C25+C26 -> #VALUE!
F21: Kd= | G21: 0.1141
B22: TASA LIBRE DE RIESGO (RF) | C22: =+G4 -> #REF! | F22: ke= | G22: =C19 -> #VALUE!
B23: BETA DE LA EMPRESA (B) | C23: =+D11 -> 1.1019552 | F23: T= | G23: 0.3
B24: PREMIO POR RIESGO ( RM - RF ) | C24: =+G5 -> #REF! | F24: D= | G24: =+H30/(H31+H30) -> #VALUE!
B25: RIESGO PAÍS (URUGUAY) (RP) | C25: =+G6 -> 0.0363 | F25: C= | G25: =+H31/(H30+H31) -> #VALUE!
B26: PRIMA TAMAÑO EMPRESA (SCP) | C26: 0.01 | F26: wacc= | G26: =((G25)*(G22)+((G24)*(1-G23)*(G21))) -> #VALUE!
F28: Wacc= | G28: =+G26 -> #VALUE!
G30: DLP | H30: #REF!
G31: C | H31: #REF!
G32: % DLP | H32: #REF!
G33: % C | H33: #REF!

Sheet RESUMEN
A1: Valoracion Negocio En Marcha Grupo OVANDO
A2: CONCEPTO | B2: Valor | C2: Comentario
A4: WACC | B4: =WACC!K26 -> 0.15953943 | C4: Considero adecuada la WACC, se deefinió un nivel de riesgo medio y se tomaron los datos de damodaran para modelar, se sensibilizó con la falta de deuda a largo plazo
A5: Valor Neto Contable | B5: ='VALOR NETO CONTABLE'!C23 -> 0 | C5: Tomado de cruce contable
A6: EBITDA 2025 | B6: ='1. Datos'!J30 -> 0 | C6: Tomado a cierre del 25
A7: Valor compañía por flujos | B7: ='4.Resumen-Escenario'!AP36 -> #DIV/0! | C7: No es muy alta porque la compañía venia presentamndo flujos bajos, hasta el 2025 el EBITDA es relativamente bueno, tuvo un crecimiento exponencial de más del 70% en comparación con los años anteriores
A8: Veces EBITDA | B8: =B7/B6 -> #DIV/0! | C8: Si se compara con la media estamos sobre la cota baja, pero dado el tamaño de la compañía y el comportamiento de valor considero adecuado el valor
A11: Multiplos de EBITDA para venta | B11: =(12.2+6.5)/2 -> 9.35 | C11: Media del rango definido por segmento de negocio en Atlas KPMG | D11: https://atlas.kpmg.com/de/en/deal-advisory-services/cost-of-capital-and-multiples/industry-specific-multiples?utm_source=chatgpt.com
A12: EBITDA ULTIMO AÑO | B12: =B6 -> 0
A13: Valor por EBITDA | B13: =B11*B6 -> 0 | C13: Se toma como techo
A14: PROYECCIONES
F27: https://atlas.kpmg.com/de/en/deal-advisory-services/cost-of-capital-and-multiples/industry-specific-multiples?utm_source=chatgpt.com

Sheet WACC
B1: DATOS | C1: FUENTE | G1: VALORES | H1: OBSERVACIÓN
B2: BETA DESAPALANCADA DE LA IND. | C2: http://pages.stern.nyu.edu/~adamodar/New_Home_Page/datafile/Betas.html | G2: ='Betas 2025'!I117 -> 0.9791328 | H2: 2025
B3: D/E = APALANCAMIENTO | C3: http://pages.stern.nyu.edu/~adamodar/New_Home_Page/datafile/Betas.html | G3: ='Betas 2025'!D117 -> 0.1792 | H3: 2025
B4: TASA LIBRE DE RIESGO | C4: Tbon 10 años (últimos 20 años) | G4: 0.0417 | H4: =TODAY() -> 46072
B5: PREMIO POR RIESGO | C5: http://pages.stern.nyu.edu/~adamodar/New_Home_Page/datafile/ctryprem.html | G5: 0.0687 | H5: 2025
B6: RIESGO PAÍS | C6: https://estadisticas.bcrp.gob.pe/estadisticas/series/diarias/resultados/PD04713XD/html | G6: 0.0257 | H6: =TODAY() -> 46072
B8: BETA DESAPALANCADA DE LA IND. | C8: Bu | D8: =+G2 -> 0.9791328 | I8: FUENTE | J8: PORCENTAJE
B9: D/E = APALANCAMIENTO | C9: D/P | D9: =G3 -> 0.1792 | I9: Barregio, 2025 | J9: 0.25
B10: TASA DE IMPUESTOS | C10: t | D10: 0.3 | I10: Banorte, 2025 | J10: 0.2115
B11: BETA APALANCADA DE LA EMPRESA | C11: BL | D11: =+D8*(1+(1-D10)*D9) -> 1.1019552 | I11: HSBC, 2025 | J11: 0.206
J13: =AVERAGE(J9:J12) -> 0.2225
B14: CÁLCULO DE TASA DE DESCUENTO (ke) | F14: CÁLCULO DE TASA DE DESCUENTO (WACC)
K15: SECTOR
B16: fórmula a utilizar (1) | F16: fórmula a utilizar (2) | J16: fórmula a utilizar (2)
B17: Ke= Rf + (Rm-Rf)B + Rp + SCP
B19: Ke= | C19: =C22+(C24)*C23+C25+C26 -> 0.16310432
F21: Kd= | G21: =J13 -> 0.2225 | J21: Kd= | K21: =+J13 -> 0.2225
B22: TASA LIBRE DE RIESGO (RF) | C22: =+G4 -> 0.0417 | F22: ke= | G22: =C19 -> 0.16310432 | J22: ke= | K22: =+C19 -> 0.16310432
B23: BETA DE LA EMPRESA (B) | C23: =+D11 -> 1.1019552 | F23: T= | G23: 0.3 | J23: T= | K23: 0.3
B24: PREMIO POR RIESGO ( RM - RF ) | C24: =+G5 -> 0.0687 | F24: D= | G24: =+I28 -> #DIV/0! | J24: D= | K24: =I30 -> 0.48473411
B25: RIESGO PAÍS ( (RP) | C25: =+G6 -> 0.0257 | F25: C= | G25: =+I29 -> #DIV/0! | J25: C= | K25: =I31 -> 0.51526589
B26: PRIMA TAMAÑO EMPRESA (SCP) | C26: 0.02 | F26: wacc= | G26: =((G25)*(G22)+((G24)*(1-G23)*(G21))) -> #DIV/0! | J26: wacc= | K26: =((K25)*(K22)+((K24)*(1-K23)*(K21))) -> 0.15953943
F28: Wacc= | G28: =+G26 -> #DIV/0! | I28: =+H30/H32 -> #DIV/0!
I29: =+H31/H32 -> #DIV/0!
G30: DLP | H30: =+'1. Datos'!J119 -> 0 | I30: =+'Estructura de deuda'!J49 -> 0.48473411
G31: C | H31: =+'1. Datos'!J125 -> 0 | I31: =+'Estructura de deuda'!E49 -> 0.51526589
F32: SECTOR | G32: TOTAL | H32: =SUM(H30+H31) -> 0

Sheet Betas 2025
A1: Date updated: | B1: 45662 | H1: YouTube Video explaining estimation choices and process. | I1: Notes
A2: Created by: | B2: Aswath Damodaran, adamodar@stern.nyu.edu | I2: if you are looking for a pure-play beta, i.e., a beta for a business, the unlevered beta corrected for cash is your best bet. Since even sector betas can move over time, I have also reported the average of the this sector beta across time in the last column. This number, for obvious reasons, is less likely to be volatile over time.
A3: What is this data? | B3: Beta, Unlevered beta and other risk measures | F3: US companies
A4: Home Page: | B4: http://www.damodaran.com
A5: Data website: | B5: https://pages.stern.nyu.edu/~adamodar/New_Home_Page/datafile/Betas.html
A6: Companies in each industry: | B6: https://pages.stern.nyu.edu/~adamodar/pc/datasets/indname.xls
A7: Variable definitions: | B7: https://pages.stern.nyu.edu/~adamodar/New_Home_Page/datafile/variable.htm
A8: Do you want to use marginal or effective tax rates in unlevering betas? | F8: Marginal
A9: If marginal tax rate, enter the marginal tax rate to use | F9: 0.25 | L9: Unlevered beta corrected for cash - Over time
A10: Industry name | B10: Number of firms | C10: Beta | D10: D/E Ratio | E10: Effective Tax rate | F10: Unlevered beta | G10: Cash/Firm value | H10: Unlevered beta corrected for cash | I10: HiLo Risk | J10: Standard deviation of equity | K10: Standard deviation in operating income (last 10 years) | L10: 2019 | M10: 2020 | N10: 2021 | O10: 2022 | P10: Average (2019-23)
A11: Advertising | B11: 54 | C11: 1.34 | D11: 0.262 | E11: 0.0767 | F11: 1.12 | G11: 0.0656 | H11: 1.2 | I11: 0.6098 | J11: 0.6719 | K11: 0.121 | L11: 0.93 | M11: 0.77 | N11: 1.1 | O11: 1.35 | P11: 1.07
A12: Aerospace/Defense | B12: 67 | C12: 0.9 | D12: 0.2279 | E12: 0.1102 | F12: 0.77 | G12: 0.0387 | H12: 0.8 | I12: 0.4341 | J12: 0.4274 | K12: 0.2392 | L12: 1.08 | M12: 0.91 | N12: 1.11 | O12: 1.23 | P12: 1.05
A13: Air Transport | B13: 24 | C13: 1.24 | D13: 1.0683 | E13: 0.1015 | F13: 0.69 | G13: 0.1028 | H13: 0.76 | I13: 0.5255 | J13: 0.6527 | K13: 2.0402 | L13: 0.84 | M13: 0.91 | N13: 0.91 | O13: 0.69 | P13: 0.8
A14: Apparel | B14: 37 | C14: 0.99 | D14: 0.4589 | E14: 0.0808 | F14: 0.74 | G14: 0.1086 | H14: 0.83 | I14: 0.4841 | J14: 0.5093 | K14: 0.2449 | L14: 0.83 | M14: 0.94 | N14: 1.1 | O14: 1.02 | P14: 0.96
A15: Auto & Truck | B15: 34 | C15: 1.62 | D15: 0.224 | E15: 0.0211 | F15: 1.39 | G15: 0.0351 | H15: 1.43 | I15: 0.6646 | J15: 0.7759 | K15: 0.4693 | L15: 0.53 | M15: 1.05 | N15: 1.02 | O15: 1.23 | P15: 1.03
A16: Auto Parts | B16: 33 | C16: 1.23 | D16: 0.4783 | E16: 0.1277 | F16: 0.91 | G16: 0.0861 | H16: 0.99 | I16: 0.3843 | J16: 0.5262 | K16: 0.2056 | L16: 0.95 | M16: 1.09 | N16: 1.21 | O16: 1.2 | P16: 1.11
A17: Bank (Money Center) | B17: 15 | C17: 0.88 | D17: 1.8319 | E17: 0.181 | F17: 0.37 | G17: 0.2977 | H17: 0.53 | I17: 0.2337 | J17: 0.3047 | K17: NA | L17: 0.56 | M17: 0.59 | N17: 1.03 | O17: 0.74 | P17: 0.71
A18: Banks (Regional) | B18: 591 | C18: 0.52 | D18: 0.6032 | E18: 0.1684 | F18: 0.36 | G18: 0.2475 | H18: 0.48 | I18: 0.2078 | J18: 0.2996 | K18: 2.6519 | L18: 0.43 | M18: 0.6 | N18: 0.84 | O18: 0.41 | P18: 0.52
A19: Beverage (Alcoholic) | B19: 18 | C19: 0.61 | D19: 0.3047 | E19: 0.0828 | F19: 0.5 | G19: 0.0186 | H19: 0.51 | I19: 0.5509 | J19: 0.6308 | K19: 0.2167 | L19: 0.92 | M19: 0.67 | N19: 0.72 | O19: 0.88 | P19: 0.83
A20: Beverage (Soft) | B20: 29 | C20: 0.57 | D20: 0.1973 | E20: 0.0694 | F20: 0.5 | G20: 0.0357 | H20: 0.51 | I20: 0.6427 | J20: 0.4767 | K20: 0.1538 | L20: 1.09 | M20: 0.71 | N20: 1.12 | O20: 1.2 | P20: 0.96
A21: Broadcasting | B21: 22 | C21: 0.92 | D21: 1.4956 | E21: 0.1074 | F21: 0.43 | G21: 0.0947 | H21: 0.48 | I21: 0.539 | J21: 0.526 | K21: 0.2823 | L21: 0.73 | M21: 0.65 | N21: 0.81 | O21: 0.7 | P21: 0.68
A22: Brokerage & Investment Banking | B22: 30 | C22: 0.95 | D22: 1.8659 | E22: 0.1442 | F22: 0.4 | G22: 0.1559 | H22: 0.47 | I22: 0.399 | J22: 0.4049 | K22: 0.5736 | L22: 0.57 | M22: 0.57 | N22: 0.67 | O22: 0.69 | P22: 0.61
A23: Building Materials | B23: 39 | C23: 1.36 | D23: 0.1897 | E23: 0.1911 | F23: 1.19 | G23: 0.0357 | H23: 1.23 | I23: 0.3033 | J23: 0.3475 | K23: 0.4633 | L23: 1.02 | M23: 0.97 | N23: 1.09 | O23: 1.1 | P23: 1.08
A24: Business & Consumer Services | B24: 152 | C24: 1 | D24: 0.1678 | E24: 0.1248 | F24: 0.89 | G24: 0.0327 | H24: 0.92 | I24: 0.4832 | J24: 0.4539 | K24: 0.2612 | L24: 0.89 | M24: 0.83 | N24: 0.99 | O24: 1.02 | P24: 0.93
A25: Cable TV | B25: 9 | C25: 0.96 | D25: 1.2635 | E25: 0.1047 | F25: 0.49 | G25: 0.0219 | H25: 0.5 | I25: 0.4196 | J25: 0.4973 | K25: 0.2809 | L25: 0.78 | M25: 0.7 | N25: 0.66 | O25: 0.71 | P25: 0.72
A26: Chemical (Basic) | B26: 31 | C26: 1.15 | D26: 0.5825 | E26: 0.0797 | F26: 0.8 | G26: 0.0716 | H26: 0.86 | I26: 0.549 | J26: 0.5002 | K26: 0.3853 | L26: 0.99 | M26: 0.76 | N26: 0.94 | O26: 0.96 | P26: 0.9
A27: Chemical (Diversified) | B27: 4 | C27: 0.99 | D27: 1.1312 | E27: 0 | F27: 0.54 | G27: 0.0734 | H27: 0.58 | I27: 0.2709 | J27: 0.4697 | K27: 0.3849 | L27: 1.21 | M27: 1.03 | N27: 1.21 | O27: 1.09 | P27: 1.07
A28: Chemical (Specialty) | B28: 60 | C28: 0.92 | D28: 0.2712 | E28: 0.0999 | F28: 0.76 | G28: 0.0358 | H28: 0.79 | I28: 0.4247 | J28: 0.4815 | K28: 0.1852 | L28: 0.96 | M28: 0.82 | N28: 1 | O28: 1.12 | P28: 0.97
A29: Coal & Related Energy | B29: 16 | C29: 1.18 | D29: 0.0947 | E29: 0.0277 | F29: 1.1 | G29: 0.1287 | H29: 1.27 | I29: 0.4805 | J29: 0.5378 | K29: 2.4543 | L29: 1.05 | M29: 0.56 | N29: 0.82 | O29: 1.43 | P29: 1.02
... A106: Total Market (without financial | B106: 4935 | C106: 1.09 | D106: 0.1929 | E106: 0.0675 | F106: 0.95 | G106: 0.0289 | H106: 0.98 | I106: 0.5139 | J106: 0.574 | K106: 0.2578 | L106: 1.01 | M106: 0.86 | N106: 1.04 | O106: 1.12 | P106: 1
G107: =1/G13 -> 9.7276265
G108: =1/G50 -> 14.245014
G110: =1/G75 -> 9.2936803
G112: =1/G54 -> 19.34236
G114: =1/G56 -> 32.051282
A115: BETAS
A116: Industry Name | B116: Number of firms | C116: Beta | D116: D/E Ratio | E116: Effective Tax rate | F116: Unlevered beta | G116: SOURCE | H116: Tasa Impuestos MXN | I116: Beta Apalancada al Sector
A117: Engineering/Construction | B117: 42 | C117: 0.99 | D117: 0.1792 | E117: 0.1471 | F117: 0.87 | G117: US | H117: 0.3 | I117: =+F117*(1+(1-H117)*D117) -> 0.9791328

Sheet MARCA (2)
B1: VALOR DE MARCA | L1: RANGO DE REGALIAS
B2: INGRESOS REALES | L2: MIN | M2: MAX
L3: 0.025 | M3: 0.05 | N3: **Se puede evaluar la parte cualitativa de la marca.
D4: 2018 | E4: 2019 | F4: 2020 | G4: 2021 | H4: 2022** | I4: CAGR | J4: Sector | L4: MEDIA
B5: INGRESOS HISTORICOS PESOS CORRIENTES | D5: =+'1. Datos'!#REF! -> #REF! | E5: =+'1. Datos'!E8 -> 0 | F5: =+'1. Datos'!F8 -> 0 | G5: =+'1. Datos'!G8 -> 0 | H5: =+'1. Datos'!H8 -> 0 | I5: =+(H5/F5)^(1/2)-1 -> #DIV/0! | J5: =+'Expected Growth25'!E67 -> 0.0312 | K5: =+(H5/D5)^(0.25)-1 -> #REF! | L5: =+M3/2 -> 0.025
B6: INCREMENTOS | F6: =+F5/E5-1 -> #DIV/0! | G6: =+G5/F5-1 -> #DIV/0! | H6: =+H5/G5-1 -> #DIV/0!
L8: Tasa de Regalía | M8: Homologación
B9: PROYECCIÓN | C9: PARAMETROS | D9: 0.5 | E9: 1.5 | F9: 2.5 | G9: 3.5 | H9: 4.5 | I9: VT | L9: =+L5 -> 0.025
B10: AÑOS | D10: 2023 | E10: =+D10+1 -> 2024 | F10: =+E10+1 -> 2025 | G10: =+F10+1 -> 2026 | H10: =+G10+1 -> 2027 | I10: =+H10 -> 2027 | L10: Eficiencia Operativa | M10: -0.4
B11: CRECIMIENTO SECTOR | D11: =+'Expected Growth25'!E67 -> 0.0312 | E11: =+D11 -> 0.0312 | F11: =+'Expected Growth25'!F67 -> 0.0413 | G11: =+F11 -> 0.0413 | H11: =+G11 -> 0.0413 | M11: =+L5*(1+M10) -> 0.015
B12: INGRESOS | D12: =+H5*(1+D11) -> 0 | E12: =+D12*(1+E11) -> 0 | F12: =+E12*(1+F11) -> 0 | G12: =+F12*(1+G11) -> 0 | H12: =+G12*(1+H11) -> 0 | I12: =+H12 -> 0
B13: AHORRO EN REGALÍAS | C13: 0.05 | D13: =+D12*$C$13 -> 0 | E13: =+E12*$C$13 -> 0 | F13: =+F12*$C$13 -> 0 | G13: =+G12*$C$13 -> 0 | H13: =+H12*$C$13 -> 0 | I13: =+I12*$C$13 -> 0
B14: GASTO POR MANTENIMIENTO | C14: 0.05 | D14: =$C$14*D13 -> 0 | E14: =$C$14*E13 -> 0 | F14: =$C$14*F13 -> 0 | G14: =$C$14*G13 -> 0 | H14: =$C$14*H13 -> 0 | I14: =$C$14*I13 -> 0
B16: INGRESOS NETOS DE MARCA | D16: =D13-D14 -> 0 | E16: =E13-E14 -> 0 | F16: =F13-F14 -> 0 | G16: =G13-G14 -> 0 | H16: =H13-H14 -> 0 | I16: =I13-I14 -> 0
B17: TASA DE IMPUESTOS | C17: 0.3 | D17: =+D16*$C$17 -> 0 | E17: =+E16*$C$17 -> 0 | F17: =+F16*$C$17 -> 0 | G17: =+G16*$C$17 -> 0 | H17: =+H16*$C$17 -> 0 | I17: =+I16*$C$17 -> 0
B19: AHORRO EN REGALÍAS NETO | D19: =+D16-D17 -> 0 | E19: =+E16-E17 -> 0 | F19: =+F16-F17 -> 0 | G19: =+G16-G17 -> 0 | H19: =+H16-H17 -> 0 | I19: =+I16-I17 -> 0
I20: =+((I19*(1+C24))/(C22-C24)) -> #VALUE!
B21: Tasa de Descuento Wacc | C21: =+'WACC_SECTOR GREEN ENERGY (2)'!G26 -> #VALUE!
B22: Van de los flujos de Royalty | C22: =+C21 -> #VALUE! | D22: =+D19/(1+$C$21)^D9 -> #VALUE! | E22: =+E19/(1+$C$21)^E9 -> #VALUE! | F22: =+F19/(1+$C$21)^F9 -> #VALUE! | G22: =+G19/(1+$C$21)^G9 -> #VALUE! | H22: =+H19/(1+$C$21)^H9 -> #VALUE! | I22: =+I20/(1+$C$21)^H9 -> #VALUE!
B24: G de largo plazo (expec. Inflaciíón) | C24: 0.0372
B26: Estimación del Valor de Marca | D26: =+SUM(D22:I22) -> #VALUE!
B31: Margen Superior Valor Marca | D31: =+D33*1.2 -> #VALUE!
B33: Estimación del Valor de Marca | D33: =ROUND(D26,-3) -> #VALUE!
B35: Margen Inferior Valor Marca | D35: =+D33*0.8 -> #VALUE!
B37: Beneficio Fiscal | D37: #REF!
B39: VALOR DE MARCA TOTAL | D39: =ROUND(D33*D37,-3) -> #VALUE!

Sheet Expected Growth25
A1: Date updated: | B1: 45662
A2: Created by: | B2: Aswath Damodaran, adamodar@stern.nyu.edu
A3: What is this data? | B3: Historical (compounded annual) growth rate in net income and revenues - last 5 years | F3: Global
A4: Home Page: | B4: http://www.damodaran.com
A5: Data website: | B5: https://pages.stern.nyu.edu/~adamodar/pc/datasets/histgr.xls
A6: Companies in each industry: | B6: https://pages.stern.nyu.edu/~adamodar/pc/datasets/indname.xls
A7: Variable definitions: | B7: https://pages.stern.nyu.edu/~adamodar/New_Home_Page/datafile/variable.htm
A8: Industry Name | B8: Number of Firms | C8: CAGR in Net Income- Last 5 years | D8: CAGR in Revenues- Last 5 years | E8: Expected Growth in Revenues - Next 2 years | F8: Expected Growth in Revenues - Next 5 years | G8: Expected Growth in EPS - Next 5 years
A9: Advertising | B9: 54 | C9: 0.1743 | D9: -0.0162 | E9: 0.0903 | F9: 0.0729 | G9: 0.2298
A10: Aerospace/Defense | B10: 67 | C10: 0.0349 | D10: 0.0821 | E10: 0.117 | F10: 0.1244 | G10: 0.1902
A11: Air Transport | B11: 24 | C11: -0.0359 | D11: 0.0264 | E11: 0.3829 | F11: 0.531 | G11: 0.3525
A12: Apparel | B12: 37 | C12: -0.0359 | D12: 0.0697 | E12: 0.0019 | F12: 0.0232 | G12: 0.0595
A13: Auto & Truck | B13: 34 | C13: 0.0837 | D13: 0.109 | E13: 0.9668 | F13: 0.3519 | G13: 0.1041
A14: Auto Parts | B14: 33 | C14: 0.0516 | D14: 0.0649 | E14: 0.1772 | F14: 0.0801 | G14: 0.1529
A15: Bank (Money Center) | B15: 15 | C15: -0.0436 | D15: 0.06 | E15: 0.0211 | F15: 0.0421 | G15: 0.1192
A16: Banks (Regional) | B16: 591 | C16: 0.046 | D16: 0.0654 | E16: 0.0704 | F16: 0.0507 | G16: 0.065
A17: Beverage (Alcoholic) | B17: 18 | C17: 0.1144 | D17: 0.0509 | E17: -0.0244 | F17: 0.0274 | G17: 0.1117
A18: Beverage (Soft) | B18: 29 | C18: 0.195 | D18: 0.1675 | E18: 0.0378 | F18: 0.0721 | G18: 0.1126
A19: Broadcasting | B19: 22 | C19: -0.0988 | D19: 0.0189 | E19: -0.0046 | F19: -0.0003 | G19: 1.9249
A20: Brokerage & Investment Banking | B20: 30 | C20: 0.1263 | D20: 0.2219 | E20: 0.1612 | F20: 0.071 | G20: 0.1537
... A24: Chemical (Basic) | B24: 31 | C24: 0.0253 | D24: 0.0867 | E24: 0.0408 | F24: 0.0023 | G24: 0.0762
A25: Chemical (Diversified) | B25: 4 | C25: -0.285 | D25: 0.0167 | E25: -0.0085 | F25: #DIV/0! | G25: 0.391
A26: Chemical (Specialty) | B26: 60 | C26: 0.0637 | D26: 0.0919 | E26: 0.188 | F26: 0.1352 | G26: 0.1042
A27: Coal & Related Energy | B27: 16 | C27: 0.2113 | D27: 0.0065 | E27: 4.2476 | F27: 0.6496 | G27: #DIV/0!
A28: Computer Services | B28: 63 | C28: 0.0427 | D28: 0.0934 | E28: 0.032 | F28: 0.3028 | G28: 0.1993
A29: Computers/Peripherals | B29: 35 | C29: 0.0679 | D29: 0.0355 | E29: 0.1036 | F29: 0.0426 | G29: 0.1148
A30: Construction Supplies | B30: 46 | C30: 0.2192 | D30: 0.0375 | E30: 6.1356 | F30: 0.0459 | G30: 0.1101
A31: Diversified | B31: 21 | C31: 0.0856 | D31: 0.1162 | E31: -0.028 | F31: 0.0113 | G31: 0.0544
A32: Drugs (Biotechnology) | B32: 535 | C32: 0.0109 | D32: 0.2377 | E32: 1.3639 | F32: 0.7235 | G32: 0.1795
A33: Drugs (Pharmaceutical) | B33: 231 | C33: -0.0296 | D33: 0.2478 | E33: 0.8018 | F33: 0.3705 | G33: 0.1221
A34: Education | B34: 29 | C34: 0.0579 | D34: 0.0477 | E34: 0.0651 | F34: 0.1131 | G34: 0.1688
A35: Electrical Equipment | B35: 101 | C35: 0.0539 | D35: 0.1329 | E35: 0.3731 | F35: 0.2807 | G35: 0.133
A36: Electronics (Consumer & Office) | B36: 11 | C36: 0 | D36: -0.07 | E36: -0.0402 | F36: #DIV/0! | G36: 0.225
A37: Electronics (General) | B37: 122 | C37: 0.1443 | D37: 0.1059 | E37: 0.1095 | F37: 0.1917 | G37: 0.1589
A38: Engineering/Construction | B38: 42 | C38: 0.227 | D38: 0.0865 | E38: 0.0927 | F38: 0.0618 | G38: 0.1682
A39: Entertainment | B39: 96 | C39: 0.1109 | D39: 0.1325 | E39: 0.0742 | F39: 0.0592 | G39: 0.1453
A40: Environmental & Waste Services | B40: 50 | C40: 0.0991 | D40: 0.1964 | E40: 0.3816 | F40: 0.0994 | G40: 0.1288
A41: Farming/Agriculture | B41: 35 | C41: 0.1486 | D41: 0.2223 | E41: 0.0493 | F41: 0.128 | G41: 0.0754
A42: Financial Svcs. (Non-bank & Insurance) | B42: 166 | C42: 0.0949 | D42: 0.1479 | E42: 0.1115 | F42: 0.0804 | G42: 0.1614
A43: Food Processing | B43: 77 | C43: 0.0511 | D43: 0.1002 | E43: 0.0489 | F43: 0.0318 | G43: 0.1036
A44: Food Wholesalers | B44: 14 | C44: 0.1309 | D44: 0.119 | E44: 0.0198 | F44: 0.0421 | G44: 0.1909
A45: Furn/Home Furnishings | B45: 28 | C45: 0.0629 | D45: -0.0028 | E45: -0.0113 | F45: 0.0369 | G45: 0.1157
A46: Green & Renewable Energy | B46: 18 | C46: 0.0483 | D46: 0.1573 | E46: 0.1506 | F46: 0.0948 | G46: 0.0027
A47: Healthcare Products | B47: 218 | C47: 0.1097 | D47: 0.1461 | E47: 0.3471 | F47: 0.252 | G47: 0.1151
A48: Healthcare Support Services | B48: 113 | C48: 0.0927 | D48: 0.1134 | E48: 0.0966 | F48: 0.0947 | G48: 0.0967
... A71: R.E.I.T. | B71: 192 | C71: 0.0589 | D71: 0.0706 | E71: 0.0424 | F71: 0.0462 | G71: 0.0672
A72: Real Estate (Development) | B72: 15 | C72: 0.1816 | D72: 0.151 | E72: 0.1165 | F72: #DIV/0! | G72: #DIV/0!
A73: Real Estate (General/Diversified) | B73: 11 | C73: 0.0485 | D73: 0.1435 | E73: 0.0225 | F73: #DIV/0! | G73: #DIV/0!
A74: Real Estate (Operations & Services) | B74: 60 | C74: -0.0886 | D74: 0.0453 | E74: 0.0934 | F74: 0.1006 | G74: 0.5393
A75: Recreation | B75: 50 | C75: 0.0435 | D75: 0.0877 | E75: 0.0145 | F75: 0.0404 | G75: 0.0916
A76: Reinsurance | B76: 1 | C76: -0.0049 | D76: 0.0966 | E76: 0.104 | F76: #DIV/0! | G76: #DIV/0!
A77: Restaurant/Dining | B77: 62 | C77: 0.0018 | D77: 0.086 | E77: 0.0956 | F77: 0.1668 | G77: 0.1635
A78: Retail (Automotive) | B78: 29 | C78: 0.0627 | D78: 0.1032 | E78: 0.0491 | F78: 0.0636 | G78: 0.0873
A79: Retail (Building Supply) | B79: 13 | C79: 0.0701 | D79: 0.0515 | E79: -0.0054 | F79: 0.0328 | G79: 0.1548
A80: Retail (Distributors) | B80: 66 | C80: 0.185 | D80: 0.0707 | E80: 0.0324 | F80: 0.0481 | G80: 0.1096
A81: Retail (General) | B81: 24 | C81: 0.069 | D81: 0.144 | E81: 0.0466 | F81: 0.0413 | G81: 0.0391
A82: Retail (Grocery and Food) | B82: 17 | C82: 0.2758 | D82: 0.0928 | E82: 0.0668 | F82: 0.0507 | G82: 0.0952
A83: Retail (REITs) | B83: 28 | C83: 0.0348 | D83: 0.0791 | E83: 0.0446 | F83: 0.0858 | G83: 0.0444
A84: Retail (Special Lines) | B84: 98 | C84: 0.1377 | D84: 0.0679 | E84: 0.0137 | F84: 0.041 | G84: 0.1352
A85: Rubber& Tires | B85: 3 | C85: 0 | D85: 0.0276 | E85: -0.0306 | F85: #DIV/0! | G85: 1.244
A86: Semiconductor | B86: 63 | C86: 0.1936 | D86: 0.0513 | E86: 0.11 | F86: 0.1527 | G86: 0.1752
A87: Semiconductor Equip | B87: 30 | C87: 0.1906 | D87: 0.1167 | E87: 0.1372 | F87: 0.1058 | G87: 0.2104
A88: Shipbuilding & Marine | B88: 8 | C88: 0.2158 | D88: -0.0427 | E88: 0.0737 | F88: #DIV/0! | G88: 0.3325
A89: Shoe | B89: 12 | C89: 0.1948 | D89: 0.0991 | E89: 0.0114 | F89: 0.0551 | G89: 0.1034
A90: Software (Entertainment) | B90: 81 | C90: 0.0026 | D90: 0.2807 | E90: 0.1387 | F90: 0.0995 | G90: 0.1977
A91: Software (Internet) | B91: 29 | C91: 0.2212 | D91: 0.1972 | E91: 0.1334 | F91: 0.1226 | G91: 0.2239
A92: Software (System & Application) | B92: 333 | C92: 0.2326 | D92: 0.1555 | E92: 0.1567 | F92: 0.1319 | G92: 0.2183
A93: Steel | B93: 27 | C93: 0.0882 | D93: 0.0605 | E93: -0.0115 | F93: 0.028 | G93: 0.1141
A94: Telecom (Wireless) | B94: 11 | C94: 0.253 | D94: 0.2807 | E94: -0.0126 | F94: 0.0256 | G94: 0.128
A95: Telecom. Equipment | B95: 61 | C95: 0.0525 | D95: 0.0255 | E95: 0.0884 | F95: 0.0631 | G95: 0.1098
A96: Telecom. Services | B96: 32 | C96: 0.2179 | D96: 0.1058 | E96: 0.0602 | F96: 0.5253 | G96: -0.0298
A97: Tobacco | B97: 12 | C97: 0.1556 | D97: -0.0052 | E97: 0.1346 | F97: 0.0353 | G97: 0.1167
A98: Transportation | B98: 21 | C98: 0.1655 | D98: 0.0857 | E98: 0.0905 | F98: 0.0581 | G98: -0.0631
A99: Transportation (Railroads) | B99: 4 | C99: 0.0023 | D99: 0.0223 | E99: 0.0575 | F99: 0.0351 | G99: 0.0861
A100: Trucking | B100: 24 | C100: 0.0419 | D100: 0.1023 | E100: 0.0373 | F100: 0.0787 | G100: 0.1203
... A104: Total Market (without financials) | B104: 4935 | C104: 0.0939 | D104: 0.1025 | E104: 0.3355 | F104: 0.2516 | G104: 0.155

Sheet MEDICION DE INGRESOS  (2)
F2: Growth(%) | G2: Crecimiento (%)
B3: EMPRESA | E3: Fuente | F3: Revenue Growth Rate (5Y) | G3: Revenue Growth Rate (3Y)*
B4: PayPal Holdings Inc | E4: https://www.reuters.com/markets/companies/pypl.o/financials/income-annual | F4: 0.1853 | G4: 0.1798 | M4: 55000
M5: 3
M6: =+M4/M5 -> 18333.333
B9: FORGUL, S.A. | E9: Promedio | F9: =AVERAGE(F4:F5) -> 0.1853 | G9: =AVERAGE(G4:G5) -> 0.1798
A12: En miles | B12: =+B4 -> PayPal Holdings Inc | C12: 43829 | D12: 44195 | E12: 44286 | F12: Crecimiento por Año | J12: Promedio | K12: CAGR
B13: Ingresos Totales | C13: 9785 | D13: 11453 | E13: 13450 | H13: =+E13/C13-1 -> 0.37455289 | J13: =AVERAGE(F13:I13) -> 0.37455289 | K13: =+(D13/C13)^(1/1)-1 -> 0.170465
B14: Utilidad Operativa | C14: 2719 | D14: 3289 | E14: 4262 | H14: =+E14/C14-1 -> 0.56748805 | J14: =+H14 -> 0.56748805 | K14: =+(D14/C14)^(1/1)-1 -> 0.2096359
B16: =+B5 -> 0 | C16: 44195 | D16: 44560 | E16: 44651 | F16: Crecimiento por Año | J16: Promedio | K16: CAGR
B17: Ingresos Totales | H17: =+D17/C17-1 -> #DIV/0! | I17: =+E17/D17-1 -> #DIV/0! | J17: =AVERAGE(F17:I17) -> #DIV/0! | K17: =+(D17/C17)^(1/1)-1 -> #DIV/0!
B18: Utilidad Operativa | H18: =+D18/C18-1 -> #DIV/0! | I18: =+E18/D18-1 -> #DIV/0! | J18: =AVERAGE(F18:I18) -> #DIV/0! | K18: =+(D18/C18)^(1/1)-1 -> #DIV/0!
B20: PLATAFORMA INMOBILIARIA CIEN LADRILLOS, S.A.P.I. DE C.V. | C20: 44195 | D20: 44560 | E20: 44651 | F20: Crecimiento por Año | J20: Promedio | K20: CAGR
B21: Ingresos Totales | K21: S/D
B22: Utilidad Operativa | K22: S/D
B24: =+B7 -> 0 | C24: 44195 | D24: 44560 | E24: 44651 | F24: Crecimiento por Año | J24: Promedio | K24: CAGR
B25: Ingresos Totales | H25: =+D25/C25-1 -> #DIV/0! | I25: =+E25/D25-1 -> #DIV/0! | J25: =AVERAGE(G25,I25,F25) -> #DIV/0! | K25: =+(E25/#REF!)^(1/3)-1 -> #REF!
B26: Utilidad Operativa | H26: =+D26/C26-1 -> #DIV/0! | I26: =+E26/D26-1 -> #DIV/0! | J26: =AVERAGE(G26) -> #DIV/0! | K26: =+(E26/#REF!)^(1/3)-1 -> #REF!
B28: =+B8 -> 0 | C28: 44195 | D28: 44560 | E28: 44651 | F28: Crecimiento por Año | J28: Promedio | K28: CAGR
B29: Ingresos Totales | H29: =+D29/C29-1 -> #DIV/0! | I29: =+E29/D29-1 -> #DIV/0! | J29: =AVERAGE(G29,F29) -> #DIV/0! | K29: =+(E29/#REF!)^(1/3)-1 -> #REF!
B30: Utilidad Operativa | H30: =+D30/C30-1 -> #DIV/0! | I30: =+E30/D30-1 -> #DIV/0! | J30: =AVERAGE(G30) -> #DIV/0! | K30: =+(E30/#REF!)^(1/3)-1 -> #REF!
B32: **Últimos 3 años. | G32: Crecimiento Promedio | J32: =AVERAGE(J13,J17) -> #DIV/0! | K32: =AVERAGE(K13,K17) -> #DIV/0!
G33: Crecimiento Promedio | J33: =AVERAGE(J14,J18) -> #DIV/0! | K33: =AVERAGE(K14,K18) -> #DIV/0!
A38: En miles | B38: =+B12 -> PayPal Holdings Inc | C38: 43464 | D38: 43829 | E38: 44195 | F38: Crecimiento por Año | J38: Promedio | K38: CAGR
B39: Total Revenue | C39: 12648 | D39: 17059 | E39: 4586 | H39: =+D39/C39-1 -> 0.34875079 | I39: =+E39/D39-1 -> -0.7311683 | J39: =AVERAGE(F39:I39) -> -0.19120875 | K39: =+(D39/C39)^(1/1)-1 -> 0.34875079
B40: Operating Income | C40: 12963 | D40: 17198 | E40: -279 | H40: =+D40/C40-1 -> 0.32669907 | I40: =+E40/D40-1 -> -1.0162228 | J40: =AVERAGE(F40:H40) -> 0.32669907 | K40: =+(D40/C40)^(1/1)-1 -> 0.32669907
C43: 43464 | D43: 43829 | E43: 44195 | F43: Crecimiento por Año | J43: Promedio | K43: CAGR
B44: Total Revenue | H44: =+D44/C44-1 -> #DIV/0! | I44: =+E44/D44-1 -> #DIV/0! | J44: =AVERAGE(F44:I44) -> #DIV/0! | K44: =+(D44/C44)^(1/1)-1 -> #DIV/0!
B45: Operating Income | H45: =+D45/C45-1 -> #DIV/0! | I45: =+E45/D45-1 -> #DIV/0! | J45: =AVERAGE(F45:H45) -> #DIV/0! | K45: =+(D45/C45)^(1/1)-1 -> #DIV/0!
B47: **Últimos 3 años. | G47: Crecimiento Promedio | J47: =AVERAGE(J39,J44) -> #DIV/0! | K47: =AVERAGE(K39,K44) -> #DIV/0!
G48: Crecimiento Promedio | J48: =AVERAGE(J40,J44) -> #DIV/0! | K48: =AVERAGE(K40,K44) -> #DIV/0!
B51: Análisis Vertical
A54: En miles | B54: =+B12 -> PayPal Holdings Inc | C54: 43465 | D54: 43830 | E54: 44196 | F54: Media
B55: Total Revenue | C55: =+C13/C13 -> 1 | D55: =+D13/D13 -> 1 | E55: =+E13/E13 -> 1 | F55: =AVERAGE(C55:E55) -> 1
B56: Operating Income | C56: =+C14/C13 -> 0.2778743 | D56: =+D14/D13 -> 0.28717367 | E56: =+E14/E13 -> 0.31687732 | F56: =AVERAGE(C56:D56) -> 0.28252398
A59: En miles | B59: =+B16 -> 0 | C59: 43465 | D59: 43830 | E59: 44196 | F59: Promedio*
B60: Total Revenue | C60: =+C17/C17 -> #DIV/0! | D60: =+D17/D17 -> #DIV/0! | E60: =+E17/E17 -> #DIV/0! | F60: 1
B61: Operating Income | C61: =+C18/C17 -> #DIV/0! | D61: =+D18/D17 -> #DIV/0! | E61: =+E18/E17 -> #DIV/0! | F61: =AVERAGE(C61:D61) -> #DIV/0!
D63: Promedio Sector | F63: =+AVERAGE(F56,F61) -> #DIV/0!

Sheet VALOR NETO CONTABLE
B3: VALOR CONTABLE | E3: VALOR CONTABLE
B4: ACTIVOS | E4: ACTIVOS
B5: Efectivo y bancos | C5: =+'1. Datos'!J45 -> 0 | E5: Efectivo y bancos
B6: Clientes | C6: =+'1. Datos'!J46 -> 0 | E6: Clientes
B7: Inventarios | C7: =+'1. Datos'!J47 -> 0 | E7: Deudores Diversos
B8: Inversiones | C8: =+'1. Datos'!J55 -> 0 | E8: Impuestos a Favor
B9: Mobiliario y Equipo Neto | C9: =+'1. Datos'!J64 -> 0 | E9: Inventarios
B10: Otros activos | C10: =+'1. Datos'!J48 -> 0 | E10: Bienes inmobiliarios
E11: Dep. En Garantia
B13: TOTAL DE ACTIVOS | C13: =+SUM(C5:C12) -> 0 | E13: TOTAL DE ACTIVOS | F13: =+SUM(F5:F11) -> 0
B15: PASIVOS | E15: PASIVOS
B16: Acreedores Diversos | C16: =+'1. Datos'!J105+'1. Datos'!J113 -> 0 | E16: Proveedores
B17: Impuestos y Derechos por pagar | C17: =+'1. Datos'!J106 -> 0 | E17: Acreedores a corto plazo
B18: Otros pasivos | C18: =+'1. Datos'!J107 -> 0 | E18: Impuestos por pagar
B19: Documentos por pagar | E19: Otros Pasivos
E20: TOTAL DE PASIVOS
B21: TOTAL DE PASIVOS | C21: =SUM(C16:C20) -> 0
E22: VALOR NETO CONTABLE | F22: =+F10-F20 -> 0
B23: VALOR NETO CONTABLE | C23: =+C13-C21 -> 0

Sheet 1. Datos
C2: GRUPO OVANDO CONTRUCCIÓN- IMOBILIARIA- TRANSPORTES S.A. de C.V.
C3: Estado de Resultados
G4: =G6/F6-1 -> #DIV/0! | H4: =H6/G6-1 -> #DIV/0! | I4: =I6/H6-1 -> #DIV/0! | K4: =K6/I6-1 -> #DIV/0! | L4: =+AVERAGE(F4:K4) -> #DIV/0!
D5: 2019 | E5: =+D5+1 -> 2020 | F5: =E5+1 -> 2021 | G5: =F5+1 -> 2022 | H5: =G5+1 -> 2023 | I5: =H5+1 -> 2024 | J5: 2025 | K5: 2025 proyecctado
C6: Ventas | K6: =+L6*12 -> 0 | L6: =+J6/9 -> 0
L7: =+J7/9 -> 0
C8: VENTAS NETAS | D8: =+D6-D7 -> 0 | E8: =+E6-E7 -> 0 | F8: =+F6-F7 -> 0 | G8: =+G6-G7 -> 0 | H8: =+H6-H7 -> 0 | I8: =+I6-I7 -> 0 | J8: =+J6-J7 -> 0 | K8: =+K6-K7 -> 0 | L8: =+J8/9 -> 0
C9: Costo de Ventas | D9: 0 | L9: =+J9/9 -> 0
C10: UTILIDAD BRUTA | D10: =+D8-D9 -> 0 | E10: =+E8-E9 -> 0 | F10: =+F8-F9 -> 0 | G10: =+G8-G9 -> 0 | H10: =+H8-H9 -> 0 | I10: =+I8-I9 -> 0 | J10: =+J8-J9 -> 0 | K10: =+K8-K9 -> 0 | L10: =+J10/9 -> 0
L11: =+J11/9 -> 0
C12: COSTOS Y GASTOS | D12: =SUM(D13:D17) -> 0 | E12: =SUM(E13:E17) -> 0 | L12: =+J12/9 -> 0 | M12: =7859990-J9 -> 7859990
C13: Gastos de operación | L13: =+J13/9 -> 0
C14: Gastos generales | L14: =+J14/9 -> 0
C15: Gastos de administracion | L15: =+J15/9 -> 0
L16: =+J16/9 -> 0
K17: =(I17/4)*12 -> 0 | L17: =+J17/9 -> 0
L18: =+J18/9 -> 0
C19: UITILIDAD DE LA OPERACIÓN | D19: =+D10-D12 -> 0 | E19: =+E10-E12 -> 0 | F19: =+F10-F12 -> 0 | G19: =+G10-G12 -> 0 | H19: =+H10-H12 -> 0 | I19: =+I10-I12 -> 0 | J19: =+J10-J12 -> 0 | K19: =+K10-K12 -> 0 | L19: =+J19/9 -> 0
C20: Otros Gastos | D20: 0 | G20: 0 | H20: 0 | I20: 0 | J20: 0 | K20: 0 | L20: =+J20/9 -> 0
C21: Otros Ingresos | L21: =+J21/9 -> 0 | M21: 288830
L22: =+J22/9 -> 0
L23: =+J23/9 -> 0
C24: RESULTADO INTEGRAL DE FINANCIAMIENTO | D24: =SUM(D20:D21) -> 0 | E24: =SUM(E20:E23) -> 0 | F24: =SUM(F20:F23) -> 0 | G24: =SUM(G20:G23) -> 0 | H24: =SUM(H20:H23) -> 0 | I24: =SUM(I20:I23) -> 0 | J24: =SUM(J20:J23) -> 0 | K24: =SUM(K20:K23) -> 0 | L24: =+J24/10 -> 0
C25: ISR diferido | L25: =+J25/10 -> 0
C26: ISR | D26: 0 | L26: =+J26/10 -> 0
C27: Provision de PTU | L27: =+J27/10 -> 0
L28: =+J28/10 -> 0
C29: Total Impts | D29: =SUM(D25:D28) -> 0 | E29: =SUM(E25:E28) -> 0 | F29: =SUM(F25:F28) -> 0 | G29: =SUM(G25:G28) -> 0 | H29: =SUM(H25:H28) -> 0 | I29: =SUM(I25:I27) -> 0 | J29: =SUM(J25:J28) -> 0 | K29: =SUM(K25:K27) -> 0
C30: UTILDIDAD O PERDIDA NETA DEL AÑO | D30: =D19+D24-D29 -> 0 | E30: =E19+E24-E29 -> 0 | F30: =F19+F24-F29 -> 0 | G30: =G19+G24-G29 -> 0 | H30: =H19+H24-H29 -> 0 | I30: =I19+I24-I29 -> 0 | J30: =J19+J24-J29 -> 0 | K30: =K19+K24-K29 -> 0
C33: =#REF! -> #REF! | D33: =+D5 -> 2019 | E33: =+E5 -> 2020 | G33: =+G5 -> 2022
C34: =#REF! -> #REF! | D34: =#REF! -> #REF! | E34: =#REF! -> #REF! | G34: =#REF! -> #REF!
C35: =#REF! -> #REF! | D35: =#REF! -> #REF! | E35: =#REF! -> #REF! | G35: =#REF! -> #REF!
C36: =#REF! -> #REF! | D36: =#REF! -> #REF! | E36: =#REF! -> #REF! | G36: =#REF! -> #REF!
C39: =+C2 -> GRUPO OVANDO CONTRUCCIÓN- IMOBILIARIA- TRANSPORTES S.A. de C.V.
D42: 2019 | E42: =+D42+1 -> 2020 | F42: =E42+1 -> 2021 | G42: =F42+1 -> 2022 | H42: =G42+1 -> 2023 | I42: 2024 | J42: =+I42+1 -> 2025
C43: ACTIVO
C44: Activo Circulante | D44: =SUM(D45:D63) -> 0 | E44: =SUM(E45:E63) -> 6046273
C45: Efectivo y equivalentes de efectivo
C46: Cuentas por cobrar
C47: Impuestos a favor
C48: otros activos circulantes | G48: 0
C49: Deudores diversos | F49: 0 | H49: 0 | I49: 0 | J49: 0
C50: Pagos anticipados | F50: 0 | H50: 0 | I50: 0 | J50: 0
E52: 6046273
C64: Activo No Circulante (Largo Plazo) | D64: =+SUM(D65:D88) -> 0 | E64: =+SUM(E65:E76) -> 0 | G64: =+SUM(G65:G82) -> 0
C65: Equipo de transporte | H65: =+G65 -> 0 | J65: =+H65 -> 0
C66: Equipo de Computo | D66: 0 | H66: =+G66 -> 0 | I66: =+H66 -> 0
C67: Mobiliario y equipo de oficina | D67: 0 | H67: =+G67 -> 0
C68: Depreciación acumulada | D68: 0
D69: 0
D70: 0
C83: Activos Diferidos | D83: =+SUM(D90:D94) -> 0 | E83: =+SUM(E84:E92) -> 0 | F83: =+SUM(F84:F92) -> 0 | G83: =+SUM(G84:G92) -> 0 | H83: =+SUM(H84:H92) -> 0 | I83: =+SUM(I84:I92) -> 0 | J83: =+SUM(J84:J92) -> 0
D90: 0
C95: Activo Total | D95: =+SUM(D44,D64,D83) -> 0 | F95: =+SUM(F44,F64,F83) -> 0 | G95: =+SUM(G44,G64,G83) -> 0 | H95: =+SUM(H44,H64,H83) -> 0 | I95: =+SUM(I44,I64,I83) -> 0 | J95: =+SUM(J44,J64,J83) -> 0
K96: =+I95-33670456 -> -33670456
C97: DEPRECIACION ACUMULADA | D97: =+D73 -> 0 | E97: =+E66+E68+E70+E72+E74+E76 -> 0 | F97: =+F68 -> 0 | G97: =+G68 -> 0 | H97: =+H68 -> 0 | I97: =+I68 -> 0 | J97: =+J68 -> 0
C98: DEPRECIACION POR PERIODO | E98: =+E97-D97 -> 0 | F98: =+F97-E97 -> 0 | G98: =+G97-F97 -> 0 | H98: =+H97-G97 -> 0 | I98: =+I97-H97 -> 0 | J98: =+J97-I97 -> 0
D102: =+D42 -> 2019 | E102: =+E42 -> 2020 | F102: =+F42 -> 2021 | G102: =+G42 -> 2022 | H102: 2023 | I102: 2024 | J102: =+I102+1 -> 2025
C103: PASIVO
C104: Pasivo Circulante | D104: =SUM(D105:D118) -> 0 | E104: =SUM(E105:E118) -> 0
C105: Cuentas y documentos por pagar
C106: Impuestos por pagar
C107: Otros pasivos | G107: 0
C108: Acreedores diversos | F108: 0 | H108: 0 | I108: 0 | J108: 0
C109: Provisiones | F109: 0 | H109: 0 | I109: 0 | J109: 0
E110: 0
E111: 0
E112: 0
C119: Pasivo a largo plazo | D119: =SUM(D120:D122) -> 0 | F119: =SUM(F120:F122) -> 0 | G119: =SUM(G120:G122) -> 0 | H119: =SUM(H120:H122) -> 0 | I119: =SUM(I120:I122) -> 0 | J119: =SUM(J120:J122) -> 0
C120: Dividendos decretados | E120: 2125000
C121: Pasivo por arrendamiento
C123: Pasivo Total | D123: =+D104+D119 -> 0 | E123: =+E104+E119 -> 0 | F123: =+F104+F119 -> 0 | G123: =+G104+G119 -> 0 | H123: =+H104+H119 -> 0 | I123: =+I104+I119 -> 0 | J123: =+J104+J119 -> 0
C125: Capital | D125: =SUM(D126:D134) -> 0
C126: Capital social
C127: Resultados acumulados
C128: Resultado del ejercicio
E130: -7955610
E131: -1112137
C135: Capital Total | D135: =D125 -> 0 | E135: =E125 -> 0 | F135: =F125 -> 0 | G135: =G125 -> 0 | H135: =H125 -> 0 | I135: =I125 -> 0 | J135: =J125 -> 0
C137: Total Pasivo + Capital | D137: =+D123+D135 -> 0 | E137: =+E123+E135 -> 0 | F137: =+F123+F135 -> 0 | G137: =+G123+G135 -> 0 | H137: =+H135+H123 -> 0 | I137: =+I135+I123 -> 0 | J137: =+J135+J123 -> 0
D138: =+D95 -> 0 | E138: =+E95 -> 0 | F138: =+F95 -> 0 | G138: =+G95 -> 0 | H138: =+H95 -> 0 | I138: =+I95 -> 0 | J138: =+J95 -> 0
D139: =+D137-D138 -> 0 | E139: =+E137-E95 -> 0 | F139: =+F137-F95 -> 0 | G139: =+G137-G95 -> 0 | H139: =+H137-H95 -> 0 | I139: =+I137-I95 -> 0 | J139: =+J137-J95 -> 0
C141: =#REF! -> #REF! | D141: =+#REF! -> #REF! | E141: =#REF! -> #REF! | G141: =#REF! -> #REF! | O141: % | P141: =+G160 -> 0
A142: =#REF! -> #REF! | C142: =#REF! -> #REF! | D142: =+#REF!/#REF! -> #REF! | E142: =#REF! -> #REF! | G142: =+E142/E$145 -> #REF! | O142: =+#REF!/#REF! -> #REF!
C143: =#REF! -> #REF! | D143: =+#REF!/#REF! -> #REF! | E143: =#REF! -> #REF! | G143: =+E143/E$145 -> #REF! | O143: =+#REF!/#REF! -> #REF!
A144: =#REF! -> #REF! | C144: =#REF! -> #REF! | D144: =+#REF!/#REF! -> #REF! | E144: =#REF! -> #REF! | G144: =+E144/E$145 -> #REF! | O144: =+#REF!/#REF! -> #REF!
C145: =#REF! -> #REF! | D145: =+#REF!/#REF! -> #REF! | E145: =#REF! -> #REF! | G145: =+E145/E$145 -> #REF! | O145: =+#REF!/#REF! -> #REF!
C146: =#REF! -> #REF! | D146: =+#REF!/#REF! -> #REF! | E146: =#REF! -> #REF! | G146: =+E146/E$145 -> #REF! | O146: =+#REF!/#REF! -> #REF!
C164: EDO DE RESULTADOS | D164: 2019 | E164: =+D164+1 -> 2020 | F164: =E164+1 -> 2021 | G164: =F164+1 -> 2022 | H164: =G164+1 -> 2023 | I164: =H164+1 -> 2024 | J164: =+I164+1 -> 2025
C165: VENTAS NETAS (1) | D165: =D8 -> 0 | E165: =E8 -> 0 | F165: =F8 -> 0 | G165: =G8 -> 0 | H165: =H8 -> 0 | I165: =I8 -> 0 | J165: =K8 -> 0
C166: COSTOS DE VENTAS (2) | D166: =D206 -> 0 | E166: =E206 -> 0 | F166: =F206 -> 0 | G166: =G206 -> 0 | H166: =H206 -> 0 | I166: =I206 -> 0 | J166: =J206 -> 0
C167: UTILIDAD BRUTA | D167: =D207 -> 0 | E167: =E207 -> 0 | F167: =F207 -> 0 | G167: =G207 -> 0 | H167: =H207 -> 0 | I167: =I207 -> 0 | J167: =J207 -> 0
C168: GASTOS DE VENTAS (2) | D168: =D208 -> 0 | E168: =E208 -> 0 | F168: =F208 -> 0 | G168: =G208 -> 0 | H168: =H208 -> 0 | I168: =I208 -> 0 | J168: =J208 -> 0
C169: EBIT (UT OPERATIVA) | D169: =D209 -> 0 | E169: =E209 -> 0 | F169: =F209 -> 0 | G169: =G209 -> 0 | H169: =H209 -> 0 | I169: =I209 -> 0 | J169: =J209 -> 0
C170: RESULTADO INTEGRAL DE FINANCIAMIENTO | D170: =+D24 -> 0 | E170: =+E24 -> 0 | F170: =+F24 -> 0 | G170: =+G24 -> 0 | H170: =+H24 -> 0 | I170: =+I24 -> 0 | J170: =+J24 -> 0
C171: UTILIDAD ANTES DE IMPUESTOS (UAI) | D171: =+D169-D170 -> 0 | E171: =+SUM(E169:E170) -> 0 | F171: =+SUM(F169:F170) -> 0 | G171: =+SUM(G169:G170) -> 0 | H171: =+SUM(H169:H170) -> 0 | I171: =+SUM(I169:I170) -> 0 | J171: =+SUM(J169:J170) -> 0
C173: (1) INFORMACION PROPORCIONADA DE VENTAS NETAS REALES. INFORMACIÓN PROPORCIONADA POR CLINICA FUTURA.
C174: (2) INFORMACION DE ESTADOS FINANCIEROS PROPORCIONADOS POR LA EMPRESA CLINICA FUTURA.
C178: ANÁLISIS VERTICAL RESULTADOS | D178: =+D164 -> 2019 | E178: =+E164 -> 2020 | F178: =+F164 -> 2021 | G178: =+G164 -> 2022 | H178: =+H164 -> 2023 | I178: =+I164 -> 2024 | J178: =+J164 -> 2025 | K178: PROMEDIO | L178: DESVEST | M178: Max | N178: Min
C179: Ventas Netas | D179: =+D165/D$165 -> #DIV/0! | E179: =+E165/E$165 -> #DIV/0! | F179: =+F165/F$165 -> #DIV/0! | G179: =+G165/G$165 -> #DIV/0! | H179: =+H165/H$165 -> #DIV/0! | I179: =+I165/I$165 -> #DIV/0! | J179: =+J165/J$165 -> #DIV/0!
...

Sheet 2.Cálculos (2)
C5: 2019 | D5: =+C5+1 -> 2020 | E5: =+D5+1 -> 2021 | F5: =+E5+1 -> 2022 | G5: =+F5+1 -> 2023 | H5: 2024 | I5: 2025
B6: Utilidad Neta | C6: ='1. Datos'!D30 -> 0 | D6: ='1. Datos'!E30 -> 0 | E6: ='1. Datos'!F30 -> 0 | F6: ='1. Datos'!G30 -> 0 | G6: ='1. Datos'!H30 -> 0 | H6: ='1. Datos'!I30 -> 0 | I6: ='1. Datos'!J30 -> 0
B7: Capital Total | C7: =+'1. Datos'!D135 -> 0 | D7: =+'1. Datos'!E135 -> 0 | E7: =+'1. Datos'!F135 -> 0 | F7: =+'1. Datos'!G135 -> 0 | G7: =+'1. Datos'!H135 -> 0 | H7: =+'1. Datos'!I135 -> 0 | I7: =+'1. Datos'!J135 -> 0
B8: ROE | C8: =C6/C7 -> #DIV/0! | D8: =D6/D7 -> #DIV/0! | E8: =E6/E7 -> #DIV/0! | F8: =F6/F7 -> #DIV/0! | G8: =G6/G7 -> #DIV/0! | H8: =H6/H7 -> #DIV/0! | I8: =I6/I7 -> #DIV/0! | K8: Promedio de reinversión | N8: =AVERAGE(E11:H11) -> #DIV/0!
B9: Dividendos | C9: 0 | D9: 0 | E9: 0 | F9: 0 | G9: 0 | H9: 0 | I9: 0
B10: % de Dividendos | C10: =C9/C6 -> #DIV/0! | D10: =D9/D6 -> #DIV/0! | E10: =E9/E6 -> #DIV/0! | F10: =F9/F6 -> #DIV/0! | G10: =G9/G6 -> #DIV/0! | H10: =H9/H6 -> #DIV/0! | I10: =I9/I6 -> #DIV/0!
B11: Tasa de Reinversión | C11: =1-C10 -> #DIV/0! | D11: =1-D10 -> #DIV/0! | E11: =1-E10 -> #DIV/0! | F11: =1-F10 -> #DIV/0! | G11: =1-G10 -> #DIV/0! | H11: =1-H10 -> #DIV/0! | I11: =1-I10 -> #DIV/0! | K11: Crecimiento (g) Promedio | N11: =+AVERAGE(F12:I12) -> #DIV/0!
B12: Crecimiento (g) | C12: =C8*C11 -> #DIV/0! | D12: =D8*D11 -> #DIV/0! | E12: =E8*E11 -> #DIV/0! | F12: =F8*F11 -> #DIV/0! | G12: =G8*G11 -> #DIV/0! | H12: =H8*H11 -> #DIV/0! | I12: =I8*I11 -> #DIV/0!
B14: CAMBIO NETO EN CAPITAL DE TRABAJO OPERATIVO | L14: mediageom | N14: =+GEOMEAN(F12,I12) -> #DIV/0!
K15: ROE=
B17: Activo Circulante | C17: =+'1. Datos'!D44 -> 0 | D17: =+'1. Datos'!E44 -> 6046273 | E17: =+'1. Datos'!F44 -> 0 | F17: =+'1. Datos'!G44 -> 0 | G17: =+'1. Datos'!H44 -> 0 | H17: =+'1. Datos'!I44 -> 0 | I17: =+'1. Datos'!J44 -> 0
B18: Pasivo Circulante | C18: =+'1. Datos'!D104 -> 0 | D18: =+'1. Datos'!E104 -> 0 | E18: =+'1. Datos'!F104 -> 0 | F18: =+'1. Datos'!G104 -> 0 | G18: =+'1. Datos'!H104 -> 0 | H18: =+'1. Datos'!I104 -> 0 | I18: =+'1. Datos'!J104 -> 0
B19: Capital de Trabajo (AC-PC) | C19: =+C17-C18 -> 0 | D19: =+D17-D18 -> 6046273 | E19: =+E17-E18 -> 0 | F19: =+F17-F18 -> 0 | G19: =+G17-G18 -> 0 | H19: =+H17-H18 -> 0 | I19: =+I17-I18 -> 0
A20: 3 | B20: Δ Capital de Trabajo | C20: =C19 -> 0 | D20: =D19 -> 6046273 | E20: =E19 -> 0 | F20: =F19 -> 0 | G20: =G19 -> 0 | H20: =H19 -> 0 | I20: =I19 -> 0 | N20: =AVERAGE(D21:H21) -> #DIV/0!
C21: 0 | F21: =+F22/E22-1 -> #DIV/0! | G21: =+G22/F22-1 -> #DIV/0! | H21: =+H22/G22-1 -> #DIV/0! | I21: =+I22/H22-1 -> #DIV/0!
B22: Utilidad de Operación (EBIT) | C22: =+'1. Datos'!D19 -> 0 | D22: =+'1. Datos'!E19 -> 0 | E22: =+'1. Datos'!F19 -> 0 | F22: =+'1. Datos'!G19 -> 0 | G22: =+'1. Datos'!H19 -> 0 | H22: =+'1. Datos'!I19 -> 0 | I22: =+'1. Datos'!K19 -> 0
B23: Impuestos (Tax) | C23: =+'1. Datos'!D25 -> 0 | D23: =+'1. Datos'!E25 -> 0 | E23: =+'1. Datos'!F25 -> 0 | F23: =+'1. Datos'!G25 -> 0 | G23: =+'1. Datos'!H25 -> 0 | H23: =+'1. Datos'!I25 -> 0 | I23: =+'1. Datos'!J25 -> 0
B24: Utilidad Antes de Impuestos | C24: =+C22 -> 0 | D24: =+D22 -> 0 | E24: =+E22 -> 0 | F24: =+F22 -> 0 | G24: =+G22 -> 0 | H24: =+H22 -> 0 | I24: =+I22 -> 0
B25: Tasa Impositiva (t) | C25: 0.3 | D25: 0.3 | E25: 0.3 | F25: 0.3 | G25: 0.3 | H25: 0.3 | I25: 0.3
B26: EBIT*(1-t) | C26: =C22*(1-C25) -> 0 | D26: =D22*(1-D25) -> 0 | E26: =E22*(1-E25) -> 0 | F26: =F22*(1-F25) -> 0 | G26: =G22*(1-G25) -> 0 | H26: =H22*(1-H25) -> 0 | I26: =I22*(1-I25) -> 0
B27: Depreciación | C27: 0 | D27: =-'1. Datos'!E98 -> 0 | E27: =+-'1. Datos'!F98 -> 0 | F27: =+-'1. Datos'!G98 -> 0 | G27: =+-'1. Datos'!H98 -> 0 | H27: =+-'1. Datos'!I98 -> 0 | I27: =+-'1. Datos'!J98 -> 0
B28: Flujo Bruto de Efectivo (FBE) | C28: =C27+C26 -> 0 | D28: =D27+D26 -> 0 | E28: =E27+E26 -> 0 | F28: =F27+F26 -> 0 | G28: =G27+G26 -> 0 | H28: =H27+H26 -> 0 | I28: =I27+I26 -> 0
B30: Δ Capital de Trabajo | C30: =+C20 -> 0 | D30: =+D20 -> 6046273 | E30: =+E20 -> 0 | F30: =+F20 -> 0 | G30: =+G20 -> 0 | H30: =+H20 -> 0 | I30: =+I20 -> 0
B31: Depreciación | C31: 0 | D31: =D27 -> 0 | E31: =E27 -> 0 | F31: =F27 -> 0 | G31: =G27 -> 0 | H31: =H27 -> 0 | I31: =I27 -> 0
B32: Capex | C32: ='2.Cálculos (2)'!C81 -> 0 | D32: ='2.Cálculos (2)'!C81 -> 0 | E32: =+E81 -> 0 | F32: =+F81 -> 0 | G32: =+G81 -> 0 | H32: =+H81 -> 0 | I32: =+I81 -> 0
B33: Incremento Otros Activos
B34: =B28 -> Flujo Bruto de Efectivo (FBE) | C34: =C28 -> 0 | D34: =D28 -> 0 | E34: =E28 -> 0 | F34: =F28 -> 0 | G34: =G28 -> 0 | H34: =H28 -> 0 | I34: =I28 -> 0
B35: Inversión Bruta | C35: =C33+C32+C30 -> 0 | D35: =D33+D32+D30 -> 6046273 | E35: =E33+E32+E30 -> 0 | F35: =F33+F32+F30 -> 0 | G35: =G33+G32+G30 -> 0 | H35: =H33+H32+H30 -> 0 | I35: =I33+I32+I30 -> 0
B36: Flujo de Caja Libre (FCF) | C36: =C34-C35 -> 0 | D36: =D34-D35 -> -6046273 | E36: =E34-E35 -> 0 | F36: =F34-F35 -> 0 | G36: =G34-G35 -> 0 | H36: =H34-H35 -> 0 | I36: =I34-I35 -> 0 | K36: Promedio de FCF% | N36: =AVERAGE(D37:I37) -> #DIV/0!
B37: FCF% = FCF / EBIT(1-t) | C37: =1-(C35)/C34 -> #DIV/0! | D37: =1-(D34)/D35 -> 1 | E37: =1-(E26)/E36 -> #DIV/0! | F37: =1-(F26)/F36 -> #DIV/0! | G37: =1-(G26)/G36 -> #DIV/0! | H37: =1-(H26)/H36 -> #DIV/0! | I37: =1-(I36)/I35 -> #DIV/0!
B38: Reinversión (1-FCF%) | C38: =1-C37 -> #DIV/0! | D38: =1-D37 -> 0 | E38: =1-E37 -> #DIV/0! | F38: =1-F37 -> #DIV/0! | G38: =1-G37 -> #DIV/0! | H38: =1-H37 -> #DIV/0! | I38: =1-I37 -> #DIV/0!
K39: Promedio de Reinversión% | N39: =AVERAGE(D38:I38) -> #DIV/0!
B44: Rentabilidad = EBIT / CAPITAL
D47: 0.56719583 | E47: 0.91954389
B51: NO SE OCUPA
B52: NO SE OCUPA | C52: =+C5 -> 2019 | D52: =+D5 -> 2020 | E52: =+E5 -> 2021 | F52: =+F5 -> 2022
B53: Activo Circulante
B54: #REF! | C54: #ERROR! | D54: #REF! | E54: #REF! | F54: #REF!
B55: (Incremento) de efectivo operativo | C55: =C54-#REF! -> #VALUE! | D55: =D54-#REF! -> #REF! | E55: =E54-D54 -> #REF! | F55: =F54-E54 -> #REF!
B56: #ERROR! | C56: #ERROR! | D56: #ERROR! | E56: #ERROR! | F56: #ERROR!
B57: (Incremento) de cuentas por cobrar | C57: =C56-#REF! -> #VALUE! | D57: =D56-#REF! -> #VALUE! | E57: =E56-D56 -> #VALUE! | F57: =F56-E56 -> #VALUE!
B58: #ERROR! | C58: #ERROR! | D58: #ERROR! | E58: #ERROR! | F58: #ERROR!
B59: (Incremento) de inventarios | C59: =C58+#REF! -> #VALUE! | D59: =D58+#REF! -> #VALUE! | E59: =E58+D58 -> #VALUE! | F59: =F58+E58 -> #VALUE!
B60: Otros activos circulantes | C60: 0 | D60: 0 | E60: 0 | F60: 0
B61: (Incremento) de otros activos circulantes | C61: =C60-#REF! -> #REF! | D61: =D60-#REF! -> #REF! | E61: =E60-D60 -> 0 | F61: =F60-E60 -> 0
B62: Δ En Activo Circulante | C62: =C55+C57+C59+C61 -> #VALUE! | D62: =D55+D57+D59+D61 -> #REF! | E62: =E55+E57+E59+E61 -> #REF! | F62: =F55+F57+F59+F61 -> #REF!
B64: Pasivo Circulante
B65: Cuentas por pagar | C65: 0 | D65: 0 | E65: 0 | F65: 0
B66: (Incremento) de cuentas por pagar | D66: =D65-#REF! -> #REF! | E66: =E65-D65 -> 0 | F66: =F65-E65 -> 0
B67: #ERROR! | C67: #ERROR! | D67: #ERROR! | E67: #ERROR! | F67: #ERROR!
B68: (Incremento) de otros pasivos circulantes | C68: =C67-#REF! -> #VALUE! | D68: =D67-#REF! -> #VALUE! | E68: =E67-D67 -> #VALUE! | F68: =F67-E67 -> #VALUE!
B69: Δ En PasivoCirculante | C69: =C66+C68 -> #VALUE! | D69: =D66+D68 -> #REF! | E69: =E66+E68 -> #VALUE! | F69: =F66+F68 -> #VALUE!
B71: CAMBIO NETO EN CAPITAL DE TRABAJO | C71: =C62-C69 -> #VALUE! | D71: =D62-D69 -> #REF! | E71: =E62-E69 -> #REF! | F71: =F62-F69 -> #REF!
B74: CAPEX
C77: 2020 | D77: 2021 | E77: 2021 | F77: =E77+1 -> 2022 | G77: =F77+1 -> 2023 | H77: =G77+1 -> 2024 | I77: =+H77+1 -> 2025
B78: Inmuebles, planta y equipo (Neto) | C78: =+'1. Datos'!E64 -> 0 | D78: =+'1. Datos'!F64 -> 0 | E78: =+'1. Datos'!F64 -> 0 | F78: =+'1. Datos'!G64 -> 0 | G78: =+'1. Datos'!H64 -> 0 | H78: =+'1. Datos'!I64 -> 0 | I78: =+'1. Datos'!J64 -> 0
B79: Δ Inmuebles, planta y Equipo | D79: =+D78-C78 -> 0 | E79: =+E78-D78 -> 0 | F79: =+F78-E78 -> 0 | G79: =+G78-F78 -> 0 | H79: =+H78-G78 -> 0 | I79: =+I78-H78 -> 0
B80: Depreciación | C80: =-'1. Datos'!E98 -> 0 | D80: =-'1. Datos'!F98 -> 0 | E80: =+'1. Datos'!F98 -> 0 | F80: =+'1. Datos'!G98 -> 0 | G80: =+'1. Datos'!H98 -> 0 | H80: =+'1. Datos'!I98 -> 0 | I80: =+'1. Datos'!J98 -> 0
B81: CAPEX | C81: =C79+C80 -> 0 | D81: =D79+D80 -> 0 | E81: =E79+E80 -> 0 | F81: =F79+F80 -> 0 | G81: =G79+G80 -> 0 | H81: =H79+H80 -> 0 | I81: =I79+I80 -> 0
B84: Capex en % de la Depreciación | C84: =+C81/C80 -> #DIV/0! | D84: =+D81/D80 -> #DIV/0! | E84: =+E81/E80 -> #DIV/0! | F84: =F81/F80 -> #DIV/0!
A88: SE PODRÍA ANALIZAR Y MEJORAR EL CALCULO DEL ROIC
C90: =+C77 -> 2020 | D90: =+D77 -> 2021 | E90: =+E77 -> 2021 | F90: =+F77 -> 2022 | G90: =+G77 -> 2023 | H90: =H77 -> 2024 | I90: =+H90+1 -> 2025
B91: Activo Total | C91: =+'1. Datos'!E95 -> 0 | D91: =+'1. Datos'!F95 -> 0 | E91: =+'1. Datos'!F95 -> 0 | F91: =+'1. Datos'!G95 -> 0 | G91: =+'1. Datos'!H95 -> 0 | H91: =+'1. Datos'!I95 -> 0 | I91: =+'1. Datos'!J95 -> 0
B92: Pasivo Circulante (Corto Plazo) | C92: =+'1. Datos'!E104 -> 0 | D92: =+'1. Datos'!F104 -> 0 | E92: =+'1. Datos'!F104 -> 0 | F92: =+'1. Datos'!G104 -> 0 | G92: =+'1. Datos'!H104 -> 0 | H92: =+'1. Datos'!I104 -> 0 | I92: =+'1. Datos'!J104 -> 0
B93: Capital Invertido (Ic) | C93: =C91-C92 -> 0 | D93: =D91-D92 -> 0 | E93: =E91-E92 -> 0 | F93: =F91-F92 -> 0 | G93: =G91-G92 -> 0 | H93: =H91-H92 -> 0 | I93: =I91-I92 -> 0
B94: ='2.Cálculos (2)'!B6 -> Utilidad Neta | C94: =+'1. Datos'!E30 -> 0 | D94: =+'1. Datos'!F30 -> 0 | E94: =+'1. Datos'!F30 -> 0 | F94: =+'1. Datos'!G30 -> 0 | G94: =+'1. Datos'!H30 -> 0 | H94: =+'1. Datos'!I30 -> 0 | I94: =+'1. Datos'!J30 -> 0
B95: ROIC | C95: =C94/C93 -> #DIV/0! | D95: =D94/D93 -> #DIV/0! | E95: =E94/E93 -> #DIV/0! | F95: =F94/F93 -> #DIV/0! | G95: =G94/G93 -> #DIV/0! | H95: =H94/H93 -> #DIV/0! | I95: =I94/I93 -> #DIV/0! | J95: =AVERAGE(F95:I95) -> #DIV/0! | K95: Si ROIC> WACC hay excedente de utilidades, lo que genera valor intangible.

Sheet MARCA
B1: VALOR DE MARCA | M1: RANGO DE REGALIAS
B2: INGRESOS REALES | N2: MIN | O2: MAX
M3: 0.025 | N3: 0.05
C4: 2020 | D4: =+C4+1 -> 2021 | E4: =+D4+1 -> 2022 | F4: =+E4+1 -> 2023 | G4: =+F4+1 -> 2024 | H4: =+G4+1 -> 2025 | J4: CAGR | K4: Sector | L4: CAGR Empresa | M4: MEDIA
B5: INGRESOS HISTORICOS PESOS CORRIENTES | C5: =+'1. Datos'!E6 -> 0 | D5: =+'1. Datos'!F6 -> 0 | E5: =+'1. Datos'!G6 -> 0 | F5: =+'1. Datos'!H6 -> 0 | G5: =+'1. Datos'!I6 -> 0 | H5: =+'1. Datos'!K6 -> 0 | J5: =+(H5/E5)^(1/4)-1 -> #DIV/0! | K5: =+'Expected Growth25'!E38 -> 0.0927 | L5: =+AVERAGE(F6:H6) -> #DIV/0! | M5: =+N3/2 -> 0.025
B6: INCREMENTOS | E6: =+E5/D5-1 -> #DIV/0! | F6: =+F5/E5-1 -> #DIV/0! | G6: =+G5/F5-1 -> #DIV/0! | H6: =+H5/G5-1 -> #DIV/0!
N8: Tasa de Regalía | O8: Homologación
B9: PROYECCIÓN | C9: PARAMETROS | D9: 0.5 | E9: 1.5 | F9: 2.5 | G9: 3.5 | H9: 4.5 | I9: VT | M9: =+M5 -> 0.025
B10: AÑOS | D10: 2026 | E10: =+D10+1 -> 2027 | F10: =+E10+1 -> 2028 | G10: =+F10+1 -> 2029 | H10: =+G10+1 -> 2030 | I10: =+H10 -> 2030 | M10: Eficiencia Operativa | N10: -0.4
B11: CRECIMIENTO SECTOR | D11: =+K5 -> 0.0927 | E11: =D11 -> 0.0927 | F11: =+'Expected Growth25'!F38 -> 0.0618 | G11: =+F11 -> 0.0618 | H11: =+G11 -> 0.0618 | I11: =H11 -> 0.0618 | N11: =+M5*(1+N10) -> 0.015
B12: INGRESOS | D12: =+H5*(1+D11) -> 0 | E12: =+D12*(1+E11) -> 0 | F12: =+E12*(1+F11) -> 0 | G12: =+F12*(1+G11) -> 0 | H12: =+G12*(1+H11) -> 0 | I12: =+H12 -> 0 | K12: -
B13: AHORRO EN REGALÍAS | C13: 0.025 | D13: =+D12*$C$13 -> 0 | E13: =+E12*$C$13 -> 0 | F13: =+F12*$C$13 -> 0 | G13: =+G12*$C$13 -> 0 | H13: =+H12*$C$13 -> 0 | I13: =+I12*$C$13 -> 0
B14: GASTO POR MANTENIMIENTO | C14: 0.05 | D14: =$C$14*D13 -> 0 | E14: =$C$14*E13 -> 0 | F14: =$C$14*F13 -> 0 | G14: =$C$14*G13 -> 0 | H14: =$C$14*H13 -> 0 | I14: =$C$14*I13 -> 0
B16: INGRESOS NETOS DE MARCA | D16: =D13-D14 -> 0 | E16: =E13-E14 -> 0 | F16: =F13-F14 -> 0 | G16: =G13-G14 -> 0 | H16: =H13-H14 -> 0 | I16: =I13-I14 -> 0
B17: TASA DE IMPUESTOS | C17: 0.3 | D17: =+D16*$C$17 -> 0 | E17: =+E16*$C$17 -> 0 | F17: =+F16*$C$17 -> 0 | G17: =+G16*$C$17 -> 0 | H17: =+H16*$C$17 -> 0 | I17: =+I16*$C$17 -> 0
B19: AHORRO EN REGALÍAS NETO | D19: =+D16-D17 -> 0 | E19: =+E16-E17 -> 0 | F19: =+F16-F17 -> 0 | G19: =+G16-G17 -> 0 | H19: =+H16-H17 -> 0 | I19: =+((H19*(1+C24))/(C22-C24)) -> 0
B21: Tasa de Descuento Wacc | C21: =+WACC!K26+0.01 -> 0.16953943
B22: Van de los flujos de Royalty | C22: =+C21 -> 0.16953943 | D22: =+D19/(1+$C$21)^D9 -> 0 | E22: =+E19/(1+$C$21)^E9 -> 0 | F22: =+F19/(1+$C$21)^F9 -> 0 | G22: =+G19/(1+$C$21)^G9 -> 0 | H22: =+H19/(1+$C$21)^H9 -> 0 | I22: =+I19/(1+$C$21)^H9 -> 0
B24: G de largo plazo (expec. Inflaciíón) | C24: =+'4.Resumen-Escenario'!AU18 -> 0.0443
B26: Estimación del Valor de Marca | D26: =+ROUND(SUM(D22:I22),-3) -> 0
B29: Margen Superior Valor Marca | D29: =+D31*1.2 -> 0
B31: Margen Inferior Valor Marca | D31: =ROUND(D26,-3) -> 0
B33: Beneficio Fiscal | D33: =+'BENEFICIO FISCAL'!O30 -> #DIV/0!
B35: VALOR DE MARCA TOTAL | D35: =ROUND(D31*D33,3) -> #DIV/0!

Sheet 4.Resumen-Escenario1
X2: Tasa Crecimiento ROE/Dividendos
P3: FLUJOS DE EFECTIVO | X3: ='Expected Growth25'!E66 -> 0.0196 | AC3: Modelo a Perpetuidad (Conservador) | BG3: Modelo de Ventaja Competitiva
O4: DIRECCION Y CONTROL DE FRANQUICIAS S.A DE C.V | AP4: =+O4 -> DIRECCION Y CONTROL DE FRANQUICIAS S.A DE C.V
M5: HISTÓRICO | X5: G SECTOR 2 YEARS | AA5: PROYECCIÓN | AP5: PROYECCIÓN | AU5: VT | BF5: PROYECCIÓN
M6: 1 | N6: 1 | O6: 1 | P6: 1 | Q6: 2 | R6: 3 | S6: 4 | T6: 5 | U6: 6 | X6: ='Expected Growth25'!E66 -> 0.0196 | AA6: 1 | AB6: 2 | AC6: 3 | AD6: 4 | AE6: 5 | AF6: 5 | AM6: 0 | AP6: 1 | AQ6: 2 | AR6: 3 | AS6: 4 | AT6: 5 | AU6: 5 | BF6: 1 | BG6: 2 | BH6: 3 | BI6: 4 | BJ6: 5 | BK6: 5 | BM6: Tasa de Crecimiento para Perpetuidad**
M7: 2014 | N7: 2015 | O7: 2018 | P7: 2019 | Q7: =+P7+1 -> 2020 | R7: =+Q7+1 -> 2021 | S7: 2022 | T7: 2023 | U7: 2024 | AP7: 2025 | AQ7: =+AP7+1 -> 2026 | AR7: =+AQ7+1 -> 2027 | AS7: =+AR7+1 -> 2028 | AT7: =+AS7+1 -> 2029 | AU7: =+AT7 -> 2029 | AW7: Tasa de Crecimiento para Perpetuidad** | BF7: =+AA7 -> 0 | BG7: =+AB7 -> 0 | BH7: =+AC7 -> 0 | BI7: =+AD7 -> 0 | BJ7: =+AE7 -> 0 | BK7: =+BJ7 -> 0 | BM7: 0.04
Q8: =+Q11/P11-1 -> #REF! | R8: =+R11/Q11-1 -> #REF! | S8: =+S11/R11-1 -> #DIV/0! | T8: =+T11/S11-1 -> #DIV/0! | U8: =+U11/T11-1 -> #DIV/0! | BF8: =+AP8 -> 0 | BG8: =+BF8*(1+BG9) -> 0 | BH8: =+BG8*(1+BH9) -> 0 | BI8: =+BH8*(1+BI9) -> 0 | BJ8: =+BI8*(1+BJ9) -> 0 | BK8: =+BJ8*(1+BK9) -> 0
AW9: 0.0465 | BC9: G crecimiento | BF9: 0.1833 | BG9: =0.1825*(BG6)^(-0.253) -> 0.15314481 | BH9: =0.1825*(BH6)^(-0.253) -> 0.13821373 | BI9: =0.1825*(BI6)^(-0.253) -> 0.12851141 | BJ9: =0.1825*(BJ6)^(-0.253) -> 0.12145725 | BK9: =0.1825*(BK6)^(-0.253) -> 0.12145725 | BM9: **Variación Anual Promedio INPC útlimos 9 años
J11: EBIT | M11: #ERROR! | N11: #REF! | O11: =+'1. Datos'!D15 -> 0 | P11: =+'1. Datos'!#REF! -> #REF! | Q11: =+'1. Datos'!#REF! -> #REF! | R11: =+'1. Datos'!E15 -> 0 | S11: =+'1. Datos'!F15 -> 0 | T11: =+'1. Datos'!G15 -> 0 | U11: =+'1. Datos'!I15 -> 0 | X11: WACC | AA11: =+#REF! -> #REF! | AM11: WACC | AP11: =WACC!G28 -> #DIV/0! | AX11: Inflacion | BC11: WACC | BF11: =+AP11 -> #DIV/0! | BM11: Reinversion= | BN11: #REF!
AY12: Se tomo en consideracion la tasa inflacionaria de 3.65% de acuerdo con las perspectivas de inflacion de Banco Mexico
J14: t | M14: 0.3 | N14: 0.3 | O14: 0.3 | P14: 0.3 | Q14: 0.3 | R14: 0.3 | S14: 0.3 | T14: 0.3 | U14: 0.3 | AF14: =+(AE15*(1+X3))/AA11 -> #REF! | AM14: G | AN14: =AP18 -> #DIV/0!
J15: NOPAT = EBIT (1-t) | M15: =M11*(1-M14) -> #VALUE! | N15: =N11*(1-N14) -> #REF! | O15: =O11*(1-O14) -> 0 | P15: =P11*(1-P14) -> #REF! | Q15: =Q11*(1-Q14) -> #REF! | R15: =R11*(1-R14) -> 0 | S15: =S11*(1-S14) -> 0 | T15: =T11*(1-T14) -> 0 | U15: =U11*(1-U14) -> 0 | X15: EBIT (1-t) | AA15: =+AA8*$U$16 -> 0 | AB15: =+AB8*$U$16 -> 0 | AC15: =+AC8*$U$16 -> 0 | AD15: =+AD8*$U$16 -> 0 | AE15: =+AE8*$U$16 -> 0 | AF15: =+(AF8*$U$16)/AA11 -> #REF! | AM15: EBIT (1-t) | AP15: =+U15 -> 0 | AQ15: =+AP19 -> #DIV/0! | AR15: =+AQ19 -> #DIV/0! | AS15: =+AR19 -> #DIV/0! | AT15: =+AS19 -> #DIV/0! | AU15: =+AT19 -> #DIV/0! | BC15: EBIT (1-t) | BF15: =+BF8*$U$16 -> 0 | BG15: =+BG8*$U$16 -> 0 | BH15: =+BH8*$U$16 -> 0 | BI15: =+BI8*$U$16 -> 0 | BJ15: =+BJ8*$U$16 -> 0 | BK15: =((BK8*$U$16)*(1-(X3/BN11))/(BF11-BM7)) -> #REF!
J18: DEPRECIACIÓN | M18: #REF! | N18: 0 | O18: ='2.Cálculos (2)'!C26 -> 0 | P18: =+'2.Cálculos (2)'!#REF! -> #REF! | Q18: =+'2.Cálculos (2)'!D27 -> 0 | R18: =+'2.Cálculos (2)'!E27 -> 0 | S18: =+'2.Cálculos (2)'!F27 -> 0 | T18: =+'2.Cálculos (2)'!G27 -> 0 | U18: =+'2.Cálculos (2)'!H27 -> 0 | AP18: ='1. Datos'!L192 -> #DIV/0! | AQ18: =+AP18 -> #DIV/0! | AR18: =+AQ18 -> #DIV/0! | AS18: =+AR18 -> #DIV/0! | AT18: =+AS18 -> #DIV/0! | AU18: =+AT18 -> #DIV/0! | AW18: Valor Terminal = NOPLAT (1+g)
J19: FLUJO BRUTO DE EFECTIVO (FBE) | M19: =M15+M18 -> #VALUE! | N19: =N15+N18 -> #REF! | O19: =O15+O18 -> 0 | P19: =P15+P18 -> #REF! | Q19: =Q15+Q18 -> #REF! | R19: =R15+R18 -> 0 | S19: =S15+S18 -> 0 | T19: =T15+T18 -> 0 | U19: =U15+U18 -> 0 | X19: EBIT (1-t) | AA19: =AA15*(1+AA18) -> 0 | AB19: =AB15*(1+AB18) -> 0 | AC19: =AC15*(1+AC18) -> 0 | AD19: =AD15*(1+AD18) -> 0 | AE19: =AE15*(1+AE18) -> 0 | AF19: =AF15*(1+AF18) -> #REF! | AM19: FLUJO PROYECTADO = EBIT(1-T)* (1+g) | AP19: =AP15*(1+AP18) -> #DIV/0! | AQ19: =AQ15*(1+AQ18) -> #DIV/0! | AR19: =AR15*(1+AR18) -> #DIV/0! | AS19: =AS15*(1+AS18) -> #DIV/0! | AT19: =AT15*(1+AT18) -> #DIV/0! | AU19: =+(AU15*(1+AU18))/(AP11-AW9) -> #DIV/0! | AX19: WACC -g | BC19: FLUJO PROYECTADO = EBIT(1-T)* (1+g) | BF19: =BF15*(1+BF18) -> 0 | BG19: =BG15*(1+BG18) -> 0 | BH19: =BH15*(1+BH18) -> 0 | BI19: =BI15*(1+BI18) -> 0 | BJ19: =BJ15*(1+BJ18) -> 0 | BK19: =BK15*(1+BK18) -> #REF!
J21: ='2.Cálculos (2)'!B20 -> Δ Capital de Trabajo | O21: =+'2.Cálculos (2)'!C30 -> 0 | P21: =+'2.Cálculos (2)'!#REF! -> #REF! | Q21: =+'2.Cálculos (2)'!D30 -> 6046273 | R21: =+'2.Cálculos (2)'!E30 -> 0 | S21: =+'2.Cálculos (2)'!F30 -> 0 | T21: =+'2.Cálculos (2)'!G30 -> 0 | U21: =+'2.Cálculos (2)'!H30 -> 0 | X21: VALOR TERMINAL | AA21: =AF19 -> #REF! | AM21: VALOR TERMINAL | AP21: =AU19 -> #DIV/0! | BC21: VALOR TERMINAL | BF21: =BK19 -> #REF!
J22: ='2.Cálculos (2)'!B32 -> Capex | O22: =+'2.Cálculos (2)'!C32 -> 0 | P22: =+'2.Cálculos (2)'!#REF! -> #REF! | Q22: =+'2.Cálculos (2)'!D32 -> 0 | R22: =+'2.Cálculos (2)'!E32 -> 0 | S22: =+'2.Cálculos (2)'!F32 -> 0 | T22: =+'2.Cálculos (2)'!G32 -> 0 | U22: =+'2.Cálculos (2)'!H32 -> 0
X23: FCF | AA23: =AA19*$O$32 -> #DIV/0! | AB23: =AB19*$O$32 -> #DIV/0! | AC23: =AC19*$O$32 -> #DIV/0! | AD23: =AD19*$O$32 -> #DIV/0! | AE23: =AE19*$O$32 -> #DIV/0! | AF23: =AF19*$O$32 -> #REF! | AM23: FCF | AP23: =AP19*$O$37 -> #DIV/0! | AQ23: =AQ19*$O$37 -> #DIV/0! | AR23: =AR19*$O$37 -> #DIV/0! | AS23: =AS19*$O$37 -> #DIV/0! | AT23: =AT19*$O$37 -> #DIV/0! | AU23: =AU19*$O$37 -> #DIV/0! | BC23: FCF | BF23: =BF19*$O$32 -> #DIV/0! | BG23: =BG19*$O$32 -> #DIV/0! | BH23: =BH19*$O$32 -> #DIV/0! | BI23: =BI19*$O$32 -> #DIV/0! | BJ23: =BJ19*$O$32 -> #DIV/0! | BK23: =BK19*$O$32 -> #REF!
J24: INVERSION BRUTA | O24: =SUM(O21:O23) -> 0 | P24: =SUM(P21:P23) -> #REF! | Q24: =SUM(Q21:Q23) -> 6046273 | R24: =SUM(R21:R23) -> 0 | S24: =SUM(S21:S23) -> 0 | T24: =SUM(T21:T23) -> 0 | U24: =SUM(U21:U23) -> 0 | X24: REINVERSION | AA24: =AA19-AA23 -> #DIV/0! | AB24: =AB19-AB23 -> #DIV/0! | AC24: =AC19-AC23 -> #DIV/0! | AD24: =AD19-AD23 -> #DIV/0! | AE24: =AE19-AE23 -> #DIV/0! | AF24: =AF19-AF23 -> #REF! | AM24: REINVERSION | AP24: =AP19-AP23 -> #DIV/0! | AQ24: =AQ19-AQ23 -> #DIV/0! | AR24: =AR19-AR23 -> #DIV/0! | AS24: =AS19-AS23 -> #DIV/0! | AT24: =AT19-AT23 -> #DIV/0! | AU24: =AU19-AU23 -> #DIV/0! | BC24: REINVERSION | BF24: =BF19-BF23 -> #DIV/0! | BG24: =BG19-BG23 -> #DIV/0! | BH24: =BH19-BH23 -> #DIV/0! | BI24: =BI19-BI23 -> #DIV/0! | BJ24: =BJ19-BJ23 -> #DIV/0! | BK24: =BK19-BK23 -> #REF!
J26: FLUJO DE CAJA LIBRE (FCF) | O26: =+O19-O24 -> 0 | P26: =+P19-P24 -> #REF! | Q26: =+Q19-Q24 -> #REF! | R26: =+R19-R24 -> 0 | S26: =+S19-S24 -> 0 | T26: =T19+T24 -> 0 | U26: =U19+U24 -> 0 | X26: VALOR PRESENTE | AA26: =AA23/((1+$AA$11)^AA6) -> #DIV/0! | AB26: =AB23/((1+$AA$11)^AB6) -> #DIV/0! | AC26: =AC23/((1+$AA$11)^AC6) -> #DIV/0! | AD26: =AD23/((1+$AA$11)^AD6) -> #DIV/0! | AE26: =AE23/((1+$AA$11)^AE6) -> #DIV/0! | AF26: =AF23/((1+$AA$11)^AF6) -> #REF! | AM26: VALOR PRESENTE | AP26: =AP23/((1+$AP$11)^AP6) -> #DIV/0! | AQ26: =AQ23/((1+$AP$11)^AQ6) -> #DIV/0! | AR26: =AR23/((1+$AP$11)^AR6) -> #DIV/0! | AS26: =AS23/((1+$AP$11)^AS6) -> #DIV/0! | AT26: =AT23/((1+$AP$11)^AT6) -> #DIV/0! | AU26: =AU23/((1+$AP$11)^AU6) -> #DIV/0! | BC26: VALOR PRESENTE | BF26: =BF23/((1+$AA$11)^BF6) -> #DIV/0! | BG26: =BG23/((1+$AA$11)^BG6) -> #DIV/0! | BH26: =BH23/((1+$AA$11)^BH6) -> #DIV/0! | BI26: =BI23/((1+$AA$11)^BI6) -> #DIV/0! | BJ26: =BJ23/((1+$AA$11)^BJ6) -> #DIV/0! | BK26: =BK23/((1+$AA$11)^BK6) -> #REF!
J27: REINVERSIÓN | O27: =1-(O26/O15) -> #DIV/0! | P27: =1-(P26/P15) -> #REF! | Q27: =1-(Q26/Q15) -> #REF! | R27: =1-(R26/R15) -> #DIV/0! | S27: =1-(S26/S15) -> #DIV/0! | T27: =1-(T26/T15) -> #DIV/0! | U27: =1-(U26/U15) -> #DIV/0!
J28: FCF % | O28: =1-O27 -> #DIV/0! | P28: =1-P27 -> #REF! | Q28: =1-Q27 -> #REF! | R28: =1-R27 -> #DIV/0! | S28: =1-S27 -> #DIV/0! | T28: =1-T27 -> #DIV/0! | U28: =1-U27 -> #DIV/0! | X28: ∑ VP | AA28: =SUM(AA26:AF26) -> #DIV/0! | AM28: ∑ VP | AP28: =IF(SUM(AP26:AU26)>0,SUM(AP26:AU26),0) -> #DIV/0! | BC28: ∑ VP | BF28: =SUM(BF26:BK26) -> #DIV/0!
J30: MEDIA FCF % | O30: =MEDIAN(T27,U27) -> #DIV/0! | X30: DEUDA | AA30: #REF! | AM30: DEUDA LARGO PLAZO | AP30: =+'1. Datos'!H119 -> 0 | BC30: DEUDA | BF30: #REF!
J32: PROMEDIO FCF % | O32: =+AVERAGE(N28:R28) -> #DIV/0! | X32: VALOR DEL NEGOCIO | AA32: =#REF! -> #REF! | AM32: VALOR DEL NEGOCIO Números redondos | AP32: =ROUND(#REF!+#REF!,-3) -> #REF! | BC32: VALOR DE CAPITAL ACCIONARIO CAP | BF32: =BF28-BF30 -> #DIV/0!
J33: PARA EL FCF%
AA34: =AA26+AA24 -> #DIV/0! | AM34: VALOR NEGOCIO | AP34: =+AP28-AP30 -> #DIV/0!
J35: REINVERSIÓN | O35: =AVERAGE(T28:U28) -> #DIV/0! | BC35: VALOR DEL NEGOCIO | BF35: =BF32 -> #DIV/0!
AM36: VALOR NEG REDONDEADO | AP36: =+ROUND(AP34,-3) -> #DIV/0!
J37: REINVERSIÓN [Damodaran] | O37: =1-'reinvestment us'!D77 -> 0.61280731 | BC37: VALOR DE LA FIRMA | BF37: =BF32+BF30 -> #DIV/0!
AM38: VALOR FIRMA | AP38: =+AP36+AP30 -> #DIV/0!
AW39: Articulo sexto | BC39: NÚMERO DE ACCIONES | BF39: =+AP36 -> #DIV/0!
X40: VALOR DE LA FIRMA | AA40: =#REF!+AA30 -> #REF! | AM40: VALOR TOTAL DE LA ENTIDAD | AP40: =+AP32+AP34 -> #REF!
AC41: #REF! | BC41: VALOR POR ACCIÓN | BF41: =BF35/BF39 -> #DIV/0!
AP48: Valor Empresa | AQ48: =AP36 -> #DIV/0!
AP49: Valor Marca
AN51: VENTAS ANUALES POR EL MULTIPLO DE LAS VENTAS | AP51: %Valor sobre Neg.
AN52: =+AS48*'EV SALES'!E46 -> 0 | AS52: PROPIO | AT52: SECTOR | AU52: FACTOR DE HOMOLOGACION
AP53: Factor Homologacion Operacion + Crecimiento | AR53: 0.8 | AS53: ='1. Datos'!L192 -> #DIV/0! | AT53: ='Expected Growth25'!E48 -> 0.0966 | AU53: 0.8
AP54: Factor Homologacion (Rentabilidad) | AR54: 0.2 | AS54: ='1. Datos'!G183 -> #DIV/0! | AT54: ='operating margin'!E49 -> 0.036514259 | AU54: 0.8
AT55: f.h. | AU55: 0.6
AQ58: EBIT / EV (FCFF ) | AR58: EBIT SECTOR | AS58: EBT HOMOLOGADO
AP59: EBIT/ EV | AQ59: =AP36/U11 -> #DIV/0! | AR59: ='Industry Averages (3)'!E49 -> 15.603649 | AS59: =AR59*AU55 -> 9.3621896
AP60: SALES/EV | AQ60: =AP36/'1. Datos'!G6 -> #DIV/0! | AR60: ='EV SALES'!E48 -> 0.53 | AS60: =AR60*AU55 -> 0.318
AR63: MIN | AS63: =(U11*AQ59) -> #DIV/0!
AR64: MAX | AS64: =AS59*U11 -> 0
K68: Corporativo González Vergara S.A de C.V | Q68: 52 ACCIONES
K69: Vidal Julián Elías Murillo | Q69: 24 ACCIONES | AQ69: EV/EBIT (FCFF)
K70: Juan Alberto Nacíf Figueroa | Q70: 24 ACCIONES | AQ70: EV/EBIT (SECTOR HOMOLOGADO)
AQ71: VALOR MINIMO DE LA EMPRESA (FCFF)
AQ72: VALOR MAXIMO DE LA EMPRESA (SECTOR HOMOLOGADO)
AQ73: VALOR PROMEDIO DE CONCLUSIÒN (MULTIPLO SECTOR HOMOLOGADO)

Sheet 4.Resumen-Escenario
X2: Tasa Crecimiento ROE/Dividendos
P3: FLUJOS DE EFECTIVO | X3: ='Expected Growth25'!F39 -> 0.0592 | AC3: Modelo a Perpetuidad (Conservador) | AM3: ='Expected Growth25'!E39 -> 0.0742 | BG3: Modelo de Ventaja Competitiva
O4: ='1. Datos'!C2 -> GRUPO OVANDO CONTRUCCIÓN- IMOBILIARIA- TRANSPORTES S.A. de C.V. | AP4: =O4 -> GRUPO OVANDO CONTRUCCIÓN- IMOBILIARIA- TRANSPORTES S.A. de C.V.
M5: HISTÓRICO | X5: G | AA5: PROYECCIÓN | AP5: PROYECCIÓN | AU5: VT | BF5: PROYECCIÓN
M6: 1 | N6: 1 | O6: 1 | P6: 1 | Q6: 1 | R6: =+Q6+1 -> 2 | S6: =+R6+1 -> 3 | T6: =+S6+1 -> 4 | U6: =+T6+1 -> 5 | X6: =AP18 -> #DIV/0! | AA6: 1 | AB6: 2 | AC6: 3 | AD6: 4 | AE6: 5 | AF6: 5 | AM6: 0 | AP6: 1 | AQ6: 2 | AR6: 3 | AS6: 4 | AT6: 5 | AU6: 5 | BF6: 1 | BG6: 2 | BH6: 3 | BI6: 4 | BJ6: 5 | BK6: 5 | BM6: Tasa de Crecimiento para Perpetuidad**
M7: 2014 | N7: 2015 | O7: 2020 | P7: 2020 | Q7: 2021 | R7: =Q7+1 -> 2022 | S7: =R7+1 -> 2023 | T7: =S7+1 -> 2024 | U7: =T7+1 -> 2025 | AP7: 2026 | AQ7: =+AP7+1 -> 2027 | AR7: =+AQ7+1 -> 2028 | AS7: =+AR7+1 -> 2029 | AT7: =+AS7+1 -> 2030 | AU7: =+AT7 -> 2030 | AW7: Tasa de Crecimiento para Perpetuidad** | BF7: =+AA7 -> 0 | BG7: =+AB7 -> 0 | BH7: =+AC7 -> 0 | BI7: =+AD7 -> 0 | BJ7: =+AE7 -> 0 | BK7: =+BJ7 -> 0 | BM7: 0.04
R8: =+R11/Q11-1 -> #DIV/0! | S8: =+S11/R11-1 -> #DIV/0! | T8: =+T11/S11-1 -> #DIV/0! | U8: =+U11/T11-1 -> #DIV/0! | BF8: =+AP8 -> 0 | BG8: =+BF8*(1+BG9) -> 0 | BH8: =+BG8*(1+BH9) -> 0 | BI8: =+BH8*(1+BI9) -> 0 | BJ8: =+BI8*(1+BJ9) -> 0 | BK8: =+BJ8*(1+BK9) -> 0
AW9: 0.0554 | BC9: G crecimiento | BF9: 0.1833 | BG9: =0.1825*(BG6)^(-0.253) -> 0.15314481 | BH9: =0.1825*(BH6)^(-0.253) -> 0.13821373 | BI9: =0.1825*(BI6)^(-0.253) -> 0.12851141 | BJ9: =0.1825*(BJ6)^(-0.253) -> 0.12145725 | BK9: =0.1825*(BK6)^(-0.253) -> 0.12145725 | BM9: **Variación Anual Promedio INPC útlimos 9 años
J11: EBIT | M11: #ERROR! | N11: #REF! | O11: =+'1. Datos'!D15 -> 0 | P11: =+'1. Datos'!E19 -> 0 | Q11: =+'1. Datos'!F19 -> 0 | R11: =+'1. Datos'!G19 -> 0 | S11: =+'1. Datos'!H19 -> 0 | T11: =+'1. Datos'!I19 -> 0 | U11: =+'1. Datos'!K19 -> 0 | X11: WACC | AA11: =+#REF! -> #REF! | AM11: WACC | AP11: =WACC!K26 -> 0.15953943 | AX11: Inflacion | BC11: WACC | BF11: =+AP11 -> 0.15953943 | BM11: Reinversion= | BN11: #REF!
AY12: Se tomo en consideracion la tasa inflacionaria de 3.65% de acuerdo con las perspectivas de inflacion de Banco Mexico
J14: t | M14: 0.3 | N14: 0.3 | O14: 0.3 | P14: 0.3 | Q14: 0.3 | R14: 0.3 | S14: 0.3 | T14: 0.3 | U14: 0.3 | AF14: =+(AE15*(1+X3))/AA11 -> #REF! | AM14: G | AN14: =+'1. Datos'!L192 -> #DIV/0!
J15: NOPAT = EBIT (1-t) | M15: =M11*(1-M14) -> #VALUE! | N15: =N11*(1-N14) -> #REF! | O15: =O11*(1-O14) -> 0 | P15: =P11*(1-P14) -> 0 | Q15: =Q11*(1-Q14) -> 0 | R15: =R11*(1-R14) -> 0 | S15: =S11*(1-S14) -> 0 | T15: =T11*(1-T14) -> 0 | U15: =U11*(1-U14) -> 0 | X15: EBIT (1-t) | AA15: =+AA8*$U$16 -> 0 | AB15: =+AB8*$U$16 -> 0 | AC15: =+AC8*$U$16 -> 0 | AD15: =+AD8*$U$16 -> 0 | AE15: =+AE8*$U$16 -> 0 | AF15: =+(AF8*$U$16)/AA11 -> #REF! | AM15: EBIT (1-t) | AP15: =+U15 -> 0 | AQ15: =+AP19 -> #DIV/0! | AR15: =+AQ19 -> #DIV/0! | AS15: =+AR19 -> #DIV/0! | AT15: =+AS19 -> #DIV/0! | AU15: =+AT19 -> #DIV/0! | BC15: EBIT (1-t) | BF15: =+BF8*$U$16 -> 0 | BG15: =+BG8*$U$16 -> 0 | BH15: =+BH8*$U$16 -> 0 | BI15: =+BI8*$U$16 -> 0 | BJ15: =+BJ8*$U$16 -> 0 | BK15: =((BK8*$U$16)*(1-(X3/BN11))/(BF11-BM7)) -> #REF!
J18: DEPRECIACIÓN | M18: #REF! | N18: 0 | O18: 0 | P18: ='2.Cálculos (2)'!E27 -> 0 | Q18: ='2.Cálculos (2)'!E27 -> 0 | R18: ='2.Cálculos (2)'!F27 -> 0 | S18: ='2.Cálculos (2)'!G27 -> 0 | T18: ='2.Cálculos (2)'!H27 -> 0 | U18: ='2.Cálculos (2)'!I27 -> 0 | AP18: =+AN14 -> #DIV/0! | AQ18: =+AP18 -> #DIV/0! | AR18: =+'Expected Growth25'!F38 -> 0.0618 | AS18: =+AR18 -> 0.0618 | AT18: =+AS18 -> 0.0618 | AU18: 0.0443 | AW18: Valor Terminal = NOPLAT (1+g)
J19: FLUJO BRUTO DE EFECTIVO (FBE) | M19: =M15+M18 -> #VALUE! | N19: =N15+N18 -> #REF! | O19: =O15+O18 -> 0 | P19: =P15+P18 -> 0 | Q19: =Q15+Q18 -> 0 | R19: =R15+R18 -> 0 | S19: =S15+S18 -> 0 | T19: =T15+T18 -> 0 | U19: =U15+U18 -> 0 | X19: EBIT (1-t) | AA19: =AA15*(1+AA18) -> 0 | AB19: =AB15*(1+AB18) -> 0 | AC19: =AC15*(1+AC18) -> 0 | AD19: =AD15*(1+AD18) -> 0 | AE19: =AE15*(1+AE18) -> 0 | AF19: =AF15*(1+AF18) -> #REF! | AM19: FLUJO PROYECTADO = EBIT(1-T)* (1+g) | AP19: =AP15*(1+AP18) -> #DIV/0! | AQ19: =AQ15*(1+AQ18) -> #DIV/0! | AR19: =AR15*(1+AR18) -> #DIV/0! | AS19: =AS15*(1+AS18) -> #DIV/0! | AT19: =AT15*(1+AT18) -> #DIV/0! | AU19: =+(AU15*(1+AU18))/(AP11-AW9) -> #DIV/0! | AX19: WACC -g | BC19: FLUJO PROYECTADO = EBIT(1-T)* (1+g) | BF19: =BF15*(1+BF18) -> 0 | BG19: =BG15*(1+BG18) -> 0 | BH19: =BH15*(1+BH18) -> 0 | BI19: =BI15*(1+BI18) -> 0 | BJ19: =BJ15*(1+BJ18) -> 0 | BK19: =BK15*(1+BK18) -> #REF!
J21: ='2.Cálculos (2)'!B20 -> Δ Capital de Trabajo | O21: =+'2.Cálculos (2)'!C30 -> 0 | P21: =+'2.Cálculos (2)'!D30 -> 6046273 | Q21: =+'2.Cálculos (2)'!E30 -> 0 | R21: =+'2.Cálculos (2)'!F30 -> 0 | S21: =+'2.Cálculos (2)'!G30 -> 0 | T21: =+'2.Cálculos (2)'!H30 -> 0 | U21: =+'2.Cálculos (2)'!I30 -> 0 | X21: VALOR TERMINAL | AA21: =AF19 -> #REF! | AM21: VALOR TERMINAL | AP21: =AU19 -> #DIV/0! | BC21: VALOR TERMINAL | BF21: =BK19 -> #REF!
J22: ='2.Cálculos (2)'!B32 -> Capex | O22: =+'2.Cálculos (2)'!C32 -> 0 | P22: =+'2.Cálculos (2)'!D32 -> 0 | Q22: =+'2.Cálculos (2)'!E32 -> 0 | R22: =+'2.Cálculos (2)'!F32 -> 0 | S22: =+'2.Cálculos (2)'!G32 -> 0 | T22: =+'2.Cálculos (2)'!H32 -> 0 | U22: =+'2.Cálculos (2)'!I32 -> 0
X23: FCF | AA23: =AA19*$O$32 -> #DIV/0! | AB23: =AB19*$O$32 -> #DIV/0! | AC23: =AC19*$O$32 -> #DIV/0! | AD23: =AD19*$O$32 -> #DIV/0! | AE23: =AE19*$O$32 -> #DIV/0! | AF23: =AF19*$O$32 -> #REF! | AM23: FCF | AP23: =AP19-AP24 -> #DIV/0! | AQ23: =AQ19-AQ24 -> #DIV/0! | AR23: =AR19-AR24 -> #DIV/0! | AS23: =AS19-AS24 -> #DIV/0! | AT23: =AT19-AT24 -> #DIV/0! | AU23: =AU19-AU24 -> #DIV/0! | BC23: FCF | BF23: =BF19*$O$32 -> #DIV/0! | BG23: =BG19*$O$32 -> #DIV/0! | BH23: =BH19*$O$32 -> #DIV/0! | BI23: =BI19*$O$32 -> #DIV/0! | BJ23: =BJ19*$O$32 -> #DIV/0! | BK23: =BK19*$O$32 -> #REF!
J24: INVERSION BRUTA | O24: =SUM(O21:O23) -> 0 | P24: =SUM(P21:P23) -> 6046273 | Q24: =SUM(Q21:Q23) -> 0 | R24: =SUM(R21:R23) -> 0 | S24: =SUM(S21:S23) -> 0 | T24: =SUM(T21:T23) -> 0 | U24: =SUM(U21:U23) -> 0 | X24: REINVERSION | AA24: =AA19-AA23 -> #DIV/0! | AB24: =AB19-AB23 -> #DIV/0! | AC24: =AC19-AC23 -> #DIV/0! | AD24: =AD19-AD23 -> #DIV/0! | AE24: =AE19-AE23 -> #DIV/0! | AF24: =AF19-AF23 -> #REF! | AM24: REINVERSION | AP24: =AP19*$O$35 -> #DIV/0! | AQ24: =AQ19*$O$35 -> #DIV/0! | AR24: =AR19*$O$35 -> #DIV/0! | AS24: =AS19*$O$35 -> #DIV/0! | AT24: =AT19*$O$35 -> #DIV/0! | AU24: =AU19*$O$35 -> #DIV/0! | BC24: REINVERSION | BF24: =BF19-BF23 -> #DIV/0! | BG24: =BG19-BG23 -> #DIV/0! | BH24: =BH19-BH23 -> #DIV/0! | BI24: =BI19-BI23 -> #DIV/0! | BJ24: =BJ19-BJ23 -> #DIV/0! | BK24: =BK19-BK23 -> #REF!
J26: FLUJO DE CAJA LIBRE (FCF) | O26: =+O19-O24 -> 0 | P26: =+P19-P24 -> -6046273 | Q26: =+Q19-Q24 -> 0 | R26: =+R19-R24 -> 0 | S26: =+S19-S24 -> 0 | T26: =T19+T24 -> 0 | U26: =U19+U24 -> 0 | X26: VALOR PRESENTE | AA26: =AA23/((1+$AA$11)^AA6) -> #DIV/0! | AB26: =AB23/((1+$AA$11)^AB6) -> #DIV/0! | AC26: =AC23/((1+$AA$11)^AC6) -> #DIV/0! | AD26: =AD23/((1+$AA$11)^AD6) -> #DIV/0! | AE26: =AE23/((1+$AA$11)^AE6) -> #DIV/0! | AF26: =AF23/((1+$AA$11)^AF6) -> #REF! | AM26: VALOR PRESENTE | AP26: =AP23/((1+$AP$11)^AP6) -> #DIV/0! | AQ26: =AQ23/((1+$AP$11)^AQ6) -> #DIV/0! | AR26: =AR23/((1+$AP$11)^AR6) -> #DIV/0! | AS26: =AS23/((1+$AP$11)^AS6) -> #DIV/0! | AT26: =AT23/((1+$AP$11)^AT6) -> #DIV/0! | AU26: =AU23/((1+$AP$11)^AU6) -> #DIV/0! | BC26: VALOR PRESENTE | BF26: =BF23/((1+$AA$11)^BF6) -> #DIV/0! | BG26: =BG23/((1+$AA$11)^BG6) -> #DIV/0! | BH26: =BH23/((1+$AA$11)^BH6) -> #DIV/0! | BI26: =BI23/((1+$AA$11)^BI6) -> #DIV/0! | BJ26: =BJ23/((1+$AA$11)^BJ6) -> #DIV/0! | BK26: =BK23/((1+$AA$11)^BK6) -> #REF!
J27: REINVERSIÓN | O27: =1-(O26/O15) -> #DIV/0! | P27: =1-(P15/P26) -> 1 | Q27: =1-(Q15/Q26) -> #DIV/0! | R27: =1-(R15/R26) -> #DIV/0! | S27: =1-(S15/S26) -> #DIV/0! | T27: =1-(T15/T26) -> #DIV/0! | U27: =1-(U15/U26) -> #DIV/0!
J28: FCF % | O28: =1-O27 -> #DIV/0! | P28: =1-P27 -> 0 | Q28: =1-Q27 -> #DIV/0! | R28: =1-R27 -> #DIV/0! | S28: =1-S27 -> #DIV/0! | T28: =1-T27 -> #DIV/0! | U28: =1-U27 -> #DIV/0! | X28: ∑ VP | AA28: =SUM(AA26:AF26) -> #DIV/0! | AM28: ∑ VP | AP28: =IF(SUM(AP26:AU26)>0,SUM(AP26:AU26),0) -> #DIV/0! | BC28: ∑ VP | BF28: =SUM(BF26:BK26) -> #DIV/0!
J30: MEDIA FCF % | O30: =+AVERAGE(U28,R28,Q28,ABS(T28)) -> #DIV/0! | X30: DEUDA | AA30: #REF! | AM30: DEUDA LARGO PLAZO | AP30: =+'1. Datos'!J119 -> 0 | BC30: DEUDA | BF30: #REF!
J32: PROMEDIO FCF % | O32: =+AVERAGE(N28:R28) -> #DIV/0! | X32: VALOR DEL NEGOCIO | AA32: =#REF! -> #REF! | AM32: VALOR DEL NEGOCIO Números redondos | AP32: =ROUND(#REF!+#REF!,-3) -> #REF! | BC32: VALOR DE CAPITAL ACCIONARIO CAP | BF32: =BF28-BF30 -> #DIV/0!
J33: PARA EL FCF%
AA34: =AA26+AA24 -> #DIV/0! | AM34: VALOR NEGOCIO | AP34: =+AP28-AP30 -> #DIV/0!
J35: REINVERSIÓN | O35: =1-O30 -> #DIV/0! | BC35: VALOR DEL NEGOCIO | BF35: =BF32 -> #DIV/0!
AM36: VALOR NEG REDONDEADO | AP36: =+ROUND(AP34,-3) -> #DIV/0!
J37: REINVERSIÓN [Damodaran] | O37: =+'reinvestment us'!D38 -> 0.84197589 | BC37: VALOR DE LA FIRMA | BF37: =BF32+BF30 -> #DIV/0!
AM38: VALOR FIRMA | AP38: =+AP36+AP30 -> #DIV/0!
AW39: Articulo sexto | BC39: NÚMERO DE ACCIONES | BF39: =+AP36 -> #DIV/0!
X40: VALOR DE LA FIRMA | AA40: =#REF!+AA30 -> #REF! | AM40: VALOR TOTAL DE LA ENTIDAD | AP40: =+AP32+AP34 -> #REF!
AC41: #REF! | BC41: VALOR POR ACCIÓN | BF41: =BF35/BF39 -> #DIV/0!
AR46: =+AP28*30% -> #DIV/0!
AP48: Valor Empresa | AQ48: =AP36 -> #DIV/0!
AP49: Valor Marca
AN51: VENTAS ANUALES POR EL MULTIPLO DE LAS VENTAS | AP51: %Valor sobre Neg.
AN52: =+AS48*'EV SALES'!E46 -> 0 | AS52: PROPIO | AT52: SECTOR | AU52: FACTOR DE HOMOLOGACION
AP53: Factor Homologacion Operacion + Crecimiento | AR53: 0.8 | AS53: =AP18 -> #DIV/0! | AT53: ='Expected Growth25'!E38 -> 0.0927 | AU53: 1
AP54: Factor Homologacion (Rentabilidad) | AR54: 0.2 | AS54: 40%(APROXIM.) | AT54: ='operating margin'!E39 -> 0.060445903 | AU54: 1
AT55: f.h. | AU55: 0.8
AQ58: EBIT / EV (FCFF ) | AR58: EBIT SECTOR | AS58: EBIT HOMOLOGADO
AP59: EBIT/ EV | AQ59: =AP36/U11 -> #DIV/0! | AR59: ='Industry Averages (3)'!E39 -> 13.874886 | AS59: =AR59 -> 13.874886 | AT59: =AR59*AP15 -> 0
AP60: SALES/EV | AQ60: =AP36/'1. Datos'!I6 -> #DIV/0! | AR60: ='Multiplos damodaran'!E42 -> 1.41 | AS60: =AR60 -> 1.41 | AT60: ='1. Datos'!J6*AR60 -> 0 | AU60: =(AT60+AT59)/2 -> 0
AR62: VALOR DE MERCADO
AR63: MIN | AS63: =AP36 -> #DIV/0!
AR64: MAX | AS64: =+AT59 -> 0
AQ69: EV/EBIT (FCFF)
AQ70: EV/EBIT (SECTOR HOMOLOGADO)
AQ71: VALOR MINIMO DE LA EMPRESA (FCFF)
AN72: 80000000 | AQ72: VALOR MAXIMO DE LA EMPRESA (SECTOR HOMOLOGADO)
AN73: 128000000 | AP73: =(AN73/AN72)-1 -> 0.6 | AQ73: VALOR PROMEDIO DE CONCLUSIÒN (MULTIPLO SECTOR HOMOLOGADO)
AN74: 281600000 | AP74: =(AN74/AN73)-1 -> 1.2
AN75: 760000000 | AP75: =(AN75/AN74)-1 -> 1.6988636
AR81: https://medicalcentertecamac.com/especialidades-1

Sheet Industry Averages (3)
A1: Date updated: | B1: 45662
A2: Created by: | B2: Aswath Damodaran, adamodar@stern.nyu.edu
A3: What is this data? | B3: Enterprise value multiples by sector | F3: Global
A4: Home Page: | B4: http://www.damodaran.com
A5: Data website: | B5: https://pages.stern.nyu.edu/~adamodar/pc/datasets/vebitdaGlobal.xls
A6: Companies in each industry: | B6: https://pages.stern.nyu.edu/~adamodar/pc/datasets/indname.xls
A7: Variable definitions: | B7: https://pages.stern.nyu.edu/~adamodar/New_Home_Page/datafile/variable.htm
C8: Only positive EBITDA firms | G8: All firms
A9: Industry Name | B9: Number of firms | C9: EV/EBITDAR&D | D9: EV/EBITDA | E9: EV/EBIT | F9: EV/EBIT (1-t) | G9: EV/EBITDAR&D | H9: EV/EBITDA | I9: EV/EBIT | J9: EV/EBIT (1-t)
A10: Advertising | B10: 417 | C10: 11.951228 | D10: 12.920253 | E10: 19.470706 | F10: 26.878975 | G10: 14.093445 | H10: 15.385578 | I10: 20.504836 | J10: 28.306573
A11: Aerospace/Defense | B11: 300 | C11: 12.712865 | D11: 17.817018 | E11: 27.4934 | F11: 34.175159 | G11: 15.491837 | H11: 22.485446 | I11: 30.858645 | J11: 38.358264
A12: Air Transport | B12: 151 | C12: 8.7540372 | D12: 8.859744 | E12: 16.544136 | F12: 20.470246 | G12: 9.4110322 | H12: 9.5308538 | I12: 16.879171 | J12: 20.884789
A13: Apparel | B13: 1194 | C13: 12.389602 | D13: 12.737552 | E13: 15.694507 | F13: 21.003911 | G13: 12.618165 | H13: 12.971024 | I13: 16.05052 | J13: 21.480361
A14: Auto & Truck | B14: 162 | C14: 8.7560075 | D14: 12.125556 | E14: 19.801842 | F14: 26.646041 | G14: 9.1324282 | H14: 12.718381 | I14: 20.35556 | J14: 27.391143
A15: Auto Parts | B15: 780 | C15: 5.1174633 | D15: 7.2426585 | E15: 13.350116 | F15: 17.580831 | G15: 5.6693147 | H15: 8.2314601 | I15: 13.942311 | J15: 18.360696
A16: Bank (Money Center) | B16: 621 | C16: NA | D16: NA | E16: NA | F16: NA | G16: NA | H16: NA | I16: NA | J16: NA
A17: Banks (Regional) | B17: 849 | C17: NA | D17: NA | E17: NA | F17: NA | G17: NA | H17: NA | I17: NA | J17: NA
A18: Beverage (Alcoholic) | B18: 216 | C18: 10.744599 | D18: 10.864404 | E18: 12.94736 | F18: 17.202742 | G18: 11.168437 | H18: 11.296785 | I18: 13.062258 | J18: 17.355402
A19: Beverage (Soft) | B19: 101 | C19: 15.688124 | D19: 15.971324 | E19: 19.414654 | F19: 24.665307 | G19: 16.611511 | H19: 16.928952 | I19: 19.439609 | J19: 24.697011
A20: Broadcasting | B20: 126 | C20: 7.4066686 | D20: 7.4336341 | E20: 11.248086 | F20: 13.964721 | G20: 9.641293 | H20: 9.6843515 | I20: 11.94564 | J20: 14.830748
A21: Brokerage & Investment Banking | B21: 606 | C21: 197.63625 | D21: NA | E21: NA | F21: NA | G21: NA | H21: NA | I21: NA | J21: NA
A22: Building Materials | B22: 462 | C22: 10.685097 | D22: 11.90787 | E22: 16.651119 | F22: 21.476296 | G22: 11.189672 | H22: 12.522764 | I22: 16.820313 | J22: 21.694519
A23: Business & Consumer Services | B23: 974 | C23: 14.822166 | D23: 15.97957 | E23: 22.033241 | F23: 29.27826 | G23: 16.406338 | H23: 17.794158 | I23: 22.648666 | J23: 30.09605
A24: Cable TV | B24: 45 | C24: 7.2170718 | D24: 7.2771082 | E24: 13.502589 | F24: 17.456933 | G24: 7.3999807 | H24: 7.4625253 | I24: 13.628205 | J24: 17.619337
A25: Chemical (Basic) | B25: 897 | C25: 9.3634977 | D25: 10.877089 | E25: 25.707502 | F25: 32.830525 | G25: 10.318605 | H25: 12.064442 | I25: 27.242217 | J25: 34.790478
A26: Chemical (Diversified) | B26: 64 | C26: 6.7487265 | D26: 8.4191756 | E26: 17.463822 | F26: 23.83518 | G26: 7.4396265 | H26: 9.3722684 | I26: 18.523609 | J26: 25.281611
A27: Chemical (Specialty) | B27: 951 | C27: 11.04853 | D27: 12.545314 | E27: 20.102125 | F27: 26.274212 | G27: 11.532509 | H27: 13.105039 | I27: 20.863074 | J27: 27.268802
A28: Coal & Related Energy | B28: 216 | C28: 5.2057745 | D28: 5.3519535 | E28: 7.3831426 | F28: 9.4576694 | G28: 5.0475661 | H28: 5.178015 | I28: 7.7612834 | J28: 9.9420607
A29: Computer Services | B29: 1182 | C29: 13.288968 | D29: 15.245954 | E29: 20.351275 | F29: 26.311207 | G29: 14.085009 | H29: 16.249645 | I29: 20.784982 | J29: 26.871926
A30: Computers/Peripherals | B30: 342 | C30: 14.083232 | D30: 19.044383 | E30: 25.458165 | F30: 31.977043 | G30: 15.468901 | H30: 21.615524 | I30: 25.617042 | J30: 32.176602
A31: Construction Supplies | B31: 804 | C31: 8.675648 | D31: 10.268126 | E31: 14.965943 | F31: 19.692014 | G31: 9.0630295 | H31: 10.776976 | I31: 15.24606 | J31: 20.06059
A32: Diversified | B32: 335 | C32: 8.0512909 | D32: 8.3981307 | E32: 10.126119 | F32: 12.30905 | G32: 8.9177114 | H32: 9.3405878 | I32: 10.23147 | J32: 12.437112
A33: Drugs (Biotechnology) | B33: 1223 | C33: 6.7521401 | D33: 15.972191 | E33: NA | F33: NA | G33: 13.365284 | H33: 78.883305 | I33: NA | J33: NA
A34: Drugs (Pharmaceutical) | B34: 1271 | C34: 8.3014459 | D34: 13.408666 | E34: 18.824918 | F34: 22.005997 | G34: 9.2588473 | H34: 15.793394 | I34: 19.328373 | J34: 22.594527
A35: Education | B35: 272 | C35: 9.8943147 | D35: 11.187385 | E35: 16.921324 | F35: 21.065557 | G35: 11.857715 | H35: 13.67444 | I35: 17.642644 | J35: 21.963537
A36: Electrical Equipment | B36: 1101 | C36: 13.309449 | D36: 17.143812 | E36: 27.802777 | F36: 35.336822 | G36: 15.410444 | H36: 20.43045 | I36: 29.302372 | J36: 37.24278
A37: Electronics (Consumer & Office) | B37: 125 | C37: 6.1658952 | D37: 10.518161 | E37: 16.117105 | F37: 21.057075 | G37: 6.8496627 | H37: 12.451225 | I37: 16.467914 | J37: 21.515409
A38: Electronics (General) | B38: 1480 | C38: 9.9666566 | D38: 13.898834 | E38: 26.487675 | F38: 32.675601 | G38: 11.523052 | H38: 16.742766 | I38: 27.790547 | J38: 34.282844
A39: Engineering/Construction | B39: 1327 | C39: 8.0825353 | D39: 9.9450246 | E39: 13.874886 | F39: 18.109961 | G39: 8.7005863 | H39: 10.808447 | I39: 14.342987 | J39: 18.720942
A40: Entertainment | B40: 748 | C40: 8.7608033 | D40: 10.018114 | E40: 35.037372 | F40: 46.748949 | G40: 17.067134 | H40: 22.173994 | I40: 37.195869 | J40: 49.628945
A41: Environmental & Waste Services | B41: 391 | C41: 13.515497 | D41: 13.975562 | E41: 23.293638 | F41: 30.560563 | G41: 15.501101 | H41: 16.088878 | I41: 24.073054 | J41: 31.583134
A42: Farming/Agriculture | B42: 429 | C42: 9.7050767 | D42: 11.01046 | E42: 15.699243 | F42: 20.332624 | G42: 9.9192642 | H42: 11.248308 | I42: 16.100502 | J42: 20.852309
A43: Financial Svcs. (Non-bank & Insurance) | B43: 1117 | C43: 43.119726 | D43: 46.493361 | E43: 59.411574 | F43: NA | G43: 88.947975 | H43: 96.73581 | I43: 110.46097 | J43: NA
A44: Food Processing | B44: 1424 | C44: 10.275741 | D44: 10.759608 | E44: 15.155317 | F44: 19.645843 | G44: 11.34736 | H44: 11.932124 | I44: 15.357235 | J44: 19.907589
A45: Food Wholesalers | B45: 188 | C45: 10.336078 | D45: 10.393488 | E45: 15.929687 | F45: 21.104872 | G45: 11.609647 | H45: 11.681125 | I45: 16.151248 | J45: 21.398414
A46: Furn/Home Furnishings | B46: 380 | C46: 7.966626 | D46: 10.231659 | E46: 14.106461 | F46: 17.185075 | G46: 8.6045963 | H46: 11.193217 | I46: 14.584418 | J46: 17.767343
A47: Green & Renewable Energy | B47: 260 | C47: 13.529234 | D47: 13.69759 | E47: 22.890412 | F47: 29.015021 | G47: 14.139961 | H47: 14.322033 | I47: 23.129877 | J47: 29.318558
A48: Healthcare Products | B48: 850 | C48: 14.143983 | D48: 19.377323 | E48: 30.316856 | F48: 36.95442 | G48: 16.028866 | H48: 22.718316 | I48: 31.512736 | J48: 38.412125
A49: Healthcare Support Services | B49: 480 | C49: 10.560821 | D49: 10.837306 | E49: 15.603649 | F49: 20.457361 | G49: 11.550283 | H49: 11.876699 | I49: 15.841466 | J49: 20.769153
A50: Heathcare Information and Technology | B50: 435 | C50: 16.949695 | D50: 21.558804 | E50: 38.098256 | F50: 46.467102 | G50: 19.438283 | H50: 25.39088 | I50: 39.844156 | J50: 48.596515
A51: Homebuilding | B51: 165 | C51: 8.2823211 | D51: 8.3146553 | E51: 9.4632268 | F51: 12.414921 | G51: 9.1044999 | H51: 9.1432138 | I51: 9.554175 | J51: 12.534237
A52: Hospitals/Healthcare Facilities | B52: 245 | C52: 11.893563 | D52: 11.947381 | E52: 17.878504 | F52: 22.380372 | G52: 13.634387 | H52: 13.704713 | I52: 17.991464 | J52: 22.521775
A53: Hotel/Gaming | B53: 660 | C53: 12.931767 | D53: 14.079987 | E53: 23.51851 | F53: 28.562881 | G53: 14.971873 | H53: 16.492583 | I53: 24.082054 | J53: 29.247297
A54: Household Products | B54: 554 | C54: 13.920581 | D54: 15.311206 | E54: 18.692511 | F54: 24.780903 | G54: 14.615059 | H54: 16.141283 | I54: 18.850876 | J54: 24.990849
A55: Information Services | B55: 85 | C55: 10.369811 | D55: 11.286514 | E55: 16.835615 | F55: 21.952927 | G55: 11.248621 | H55: 12.318905 | I55: 17.072594 | J55: 22.261937
... A105: Total Market (without financials) | B105: 42750 | C105: 10.112723 | D105: 12.152628 | E105: 18.667602 | F105: 23.717039 | G105: 11.225883 | H105: 13.678109 | I105: 19.401987 | J105: 24.650069

Sheet Proyeccion ngresos
B2: 2026 | C2: 26729035
B3: 2027 | C3: 32101571
B4: 2028 | C4: 38553988
B5: 2029 | C5: 46303339
B6: 2030 | C6: 55610310

Sheet 4.Resumen-Escenario CONSERVADOR
X2: Tasa Crecimiento ROE/Dividendos
P3: FLUJOS DE EFECTIVO | X3: ='Expected Growth25'!E51 -> 0.0581 | AC3: Modelo a Perpetuidad (Conservador) | BG3: Modelo de Ventaja Competitiva
O4: MEDICAL CENTER TECAMAC | AP4: MEDICAL CENTER TECAMAC
M5: HISTÓRICO | X5: G | AA5: PROYECCIÓN | AP5: PROYECCIÓN | AU5: VT | BF5: PROYECCIÓN
M6: 1 | N6: 1 | O6: 1 | P6: 1 | Q6: 2 | R6: 3 | S6: 4 | T6: 5 | U6: 6 | X6: =+'Expected Growth25'!D51 -> 0.0157 | AA6: 1 | AB6: 2 | AC6: 3 | AD6: 4 | AE6: 5 | AF6: 5 | AM6: 0 | AP6: 1 | AQ6: 2 | AR6: 3 | AS6: 4 | AT6: 5 | AU6: 5 | BF6: 1 | BG6: 2 | BH6: 3 | BI6: 4 | BJ6: 5 | BK6: 5 | BM6: Tasa de Crecimiento para Perpetuidad**
M7: 2014 | N7: 2015 | O7: 2018 | P7: 2019 | Q7: =+P7+1 -> 2020 | R7: =+Q7+1 -> 2021 | S7: 2022 | T7: 2023 | U7: 2024 | AP7: 2025 | AQ7: =+AP7+1 -> 2026 | AR7: =+AQ7+1 -> 2027 | AS7: =+AR7+1 -> 2028 | AT7: =+AS7+1 -> 2029 | AU7: =+AT7 -> 2029 | AW7: Tasa de Crecimiento para Perpetuidad** | BF7: =+AA7 -> 0 | BG7: =+AB7 -> 0 | BH7: =+AC7 -> 0 | BI7: =+AD7 -> 0 | BJ7: =+AE7 -> 0 | BK7: =+BJ7 -> 0 | BM7: 0.04
P8: =+P11/O11-1 -> #DIV/0! | Q8: =+Q11/P11-1 -> #DIV/0! | R8: =+R11/Q11-1 -> #DIV/0! | S8: =+S11/R11-1 -> #DIV/0! | T8: =+T11/S11-1 -> #DIV/0! | U8: =+U11/T11-1 -> #DIV/0! | BF8: =+AP8 -> 0 | BG8: =+BF8*(1+BG9) -> 0 | BH8: =+BG8*(1+BH9) -> 0 | BI8: =+BH8*(1+BI9) -> 0 | BJ8: =+BI8*(1+BJ9) -> 0 | BK8: =+BJ8*(1+BK9) -> 0
AW9: 0.0359 | BC9: G crecimiento | BF9: 0.1833 | BG9: =0.1825*(BG6)^(-0.253) -> 0.15314481 | BH9: =0.1825*(BH6)^(-0.253) -> 0.13821373 | BI9: =0.1825*(BI6)^(-0.253) -> 0.12851141 | BJ9: =0.1825*(BJ6)^(-0.253) -> 0.12145725 | BK9: =0.1825*(BK6)^(-0.253) -> 0.12145725 | BM9: **Variación Anual Promedio INPC útlimos 9 años
J11: EBIT | M11: #ERROR! | N11: #REF! | O11: =+'1. Datos'!D15 -> 0 | P11: =+'1. Datos'!D15 -> 0 | Q11: =+'1. Datos'!E15 -> 0 | R11: =+'1. Datos'!F15 -> 0 | S11: =+'1. Datos'!G15 -> 0 | T11: =+'1. Datos'!H15 -> 0 | U11: ='1. Datos'!I6 -> 0 | X11: WACC | AA11: =+#REF! -> #REF! | AM11: WACC | AP11: =WACC!K26 -> 0.15953943 | AX11: Inflacion | BC11: WACC | BF11: =+AP11 -> 0.15953943 | BM11: Reinversion= | BN11: #REF!
AY12: Se tomo en consideracion la tasa inflacionaria de 3.65% de acuerdo con las perspectivas de inflacion de Banco Mexico
J14: t | M14: 0.3 | N14: 0.3 | O14: 0.3 | P14: 0.3 | Q14: 0.3 | R14: 0.3 | S14: 0.3 | T14: 0.3 | U14: 0.3 | AF14: =+(AE15*(1+X3))/AA11 -> #REF! | AM14: G | AN14: =X3 -> 0.0581
J15: NOPAT = EBIT (1-t) | M15: =M11*(1-M14) -> #VALUE! | N15: =N11*(1-N14) -> #REF! | O15: =O11*(1-O14) -> 0 | P15: =P11*(1-P14) -> 0 | Q15: =Q11*(1-Q14) -> 0 | R15: =R11*(1-R14) -> 0 | S15: =S11*(1-S14) -> 0 | T15: =T11*(1-T14) -> 0 | U15: =U11*(1-U14) -> 0 | X15: EBIT (1-t) | AA15: =+AA8*$U$16 -> 0 | AB15: =+AB8*$U$16 -> 0 | AC15: =+AC8*$U$16 -> 0 | AD15: =+AD8*$U$16 -> 0 | AE15: =+AE8*$U$16 -> 0 | AF15: =+(AF8*$U$16)/AA11 -> #REF! | AM15: EBIT (1-t) | AP15: #REF! | AQ15: =+AP19 -> #REF! | AR15: =+AQ19 -> #REF! | AS15: =+AR19 -> #REF! | AT15: =+AS19 -> #REF! | AU15: =+AT19 -> #REF! | BC15: EBIT (1-t) | BF15: =+BF8*$U$16 -> 0 | BG15: =+BG8*$U$16 -> 0 | BH15: =+BH8*$U$16 -> 0 | BI15: =+BI8*$U$16 -> 0 | BJ15: =+BJ8*$U$16 -> 0 | BK15: =((BK8*$U$16)*(1-(X3/BN11))/(BF11-BM7)) -> #REF!
J18: DEPRECIACIÓN | M18: #REF! | N18: 0 | O18: ='2.Cálculos (2)'!C26 -> 0 | P18: ='2.Cálculos (2)'!#REF! -> #REF! | Q18: ='2.Cálculos (2)'!D27 -> 0 | R18: ='2.Cálculos (2)'!E27 -> 0 | S18: ='2.Cálculos (2)'!F27 -> 0 | T18: ='2.Cálculos (2)'!G27 -> 0 | U18: ='2.Cálculos (2)'!H27 -> 0 | AP18: ='4.Resumen-Escenario'!X6 -> #DIV/0! | AQ18: =+AP18 -> #DIV/0! | AR18: =16% -> 0.16 | AS18: =+AR18 -> 0.16 | AT18: =+AS18 -> 0.16 | AU18: =+AW9 -> 0.0359 | AW18: Valor Terminal = NOPLAT (1+g)
J19: FLUJO BRUTO DE EFECTIVO (FBE) | M19: =M15+M18 -> #VALUE! | N19: =N15+N18 -> #REF! | O19: =O15+O18 -> 0 | P19: =P15+P18 -> #REF! | Q19: =Q15+Q18 -> 0 | R19: =R15+R18 -> 0 | S19: =S15+S18 -> 0 | T19: =T15+T18 -> 0 | U19: =U15+U18 -> 0 | X19: EBIT (1-t) | AA19: =AA15*(1+AA18) -> 0 | AB19: =AB15*(1+AB18) -> 0 | AC19: =AC15*(1+AC18) -> 0 | AD19: =AD15*(1+AD18) -> 0 | AE19: =AE15*(1+AE18) -> 0 | AF19: =AF15*(1+AF18) -> #REF! | AM19: FLUJO PROYECTADO = EBIT(1-T)* (1+g) | AP19: =AP15*(1+AP18) -> #REF! | AQ19: =AQ15*(1+AQ18) -> #REF! | AR19: =AR15*(1+AR18) -> #REF! | AS19: =AS15*(1+AS18) -> #REF! | AT19: =AT15*(1+AT18) -> #REF! | AU19: =+(AU15*(1+AU18))/(AP11-AW9) -> #REF! | AX19: WACC -g | BC19: FLUJO PROYECTADO = EBIT(1-T)* (1+g) | BF19: =BF15*(1+BF18) -> 0 | BG19: =BG15*(1+BG18) -> 0 | BH19: =BH15*(1+BH18) -> 0 | BI19: =BI15*(1+BI18) -> 0 | BJ19: =BJ15*(1+BJ18) -> 0 | BK19: =BK15*(1+BK18) -> #REF!
J21: ='2.Cálculos (2)'!B20 -> Δ Capital de Trabajo | O21: =+'2.Cálculos (2)'!C30 -> 0 | P21: =+'2.Cálculos (2)'!#REF! -> #REF! | Q21: =+'2.Cálculos (2)'!D30 -> 6046273 | R21: =+'2.Cálculos (2)'!E30 -> 0 | S21: =+'2.Cálculos (2)'!F30 -> 0 | T21: =+'2.Cálculos (2)'!G30 -> 0 | U21: =+'2.Cálculos (2)'!H30 -> 0 | X21: VALOR TERMINAL | AA21: =AF19 -> #REF! | AM21: VALOR TERMINAL | AP21: =AU19 -> #REF! | BC21: VALOR TERMINAL | BF21: =BK19 -> #REF!
J22: ='2.Cálculos (2)'!B32 -> Capex | O22: =+'2.Cálculos (2)'!C32 -> 0 | P22: =+'2.Cálculos (2)'!#REF! -> #REF! | Q22: =+'2.Cálculos (2)'!D32 -> 0 | R22: =+'2.Cálculos (2)'!E32 -> 0 | S22: =+'2.Cálculos (2)'!F32 -> 0 | T22: =+'2.Cálculos (2)'!G32 -> 0 | U22: =+'2.Cálculos (2)'!H32 -> 0
X23: FCF | AA23: =AA19*$O$32 -> #DIV/0! | AB23: =AB19*$O$32 -> #DIV/0! | AC23: =AC19*$O$32 -> #DIV/0! | AD23: =AD19*$O$32 -> #DIV/0! | AE23: =AE19*$O$32 -> #DIV/0! | AF23: =AF19*$O$32 -> #REF! | AM23: FCF | AP23: =AP19-AP24 -> #REF! | AQ23: =AQ19-AQ24 -> #REF! | AR23: =AR19-AR24 -> #REF! | AS23: =AS19-AS24 -> #REF! | AT23: =AT19-AT24 -> #REF! | AU23: =AU19-AU24 -> #REF! | BC23: FCF | BF23: =BF19*$O$32 -> #DIV/0! | BG23: =BG19*$O$32 -> #DIV/0! | BH23: =BH19*$O$32 -> #DIV/0! | BI23: =BI19*$O$32 -> #DIV/0! | BJ23: =BJ19*$O$32 -> #DIV/0! | BK23: =BK19*$O$32 -> #REF!
J24: INVERSION BRUTA | O24: =SUM(O21:O23) -> 0 | P24: =SUM(P21:P23) -> #REF! | Q24: =SUM(Q21:Q23) -> 6046273 | R24: =SUM(R21:R23) -> 0 | S24: =SUM(S21:S23) -> 0 | T24: =SUM(T21:T23) -> 0 | U24: =SUM(U21:U23) -> 0 | X24: REINVERSION | AA24: =AA19-AA23 -> #DIV/0! | AB24: =AB19-AB23 -> #DIV/0! | AC24: =AC19-AC23 -> #DIV/0! | AD24: =AD19-AD23 -> #DIV/0! | AE24: =AE19-AE23 -> #DIV/0! | AF24: =AF19-AF23 -> #REF! | AM24: REINVERSION | AP24: =AP19*$O$35 -> #REF! | AQ24: =AQ19*$O$35 -> #REF! | AR24: =AR19*$O$35 -> #REF! | AS24: =AS19*$O$35 -> #REF! | AT24: =AT19*$O$35 -> #REF! | AU24: =AU19*$O$35 -> #REF! | BC24: REINVERSION | BF24: =BF19-BF23 -> #DIV/0! | BG24: =BG19-BG23 -> #DIV/0! | BH24: =BH19-BH23 -> #DIV/0! | BI24: =BI19-BI23 -> #DIV/0! | BJ24: =BJ19-BJ23 -> #DIV/0! | BK24: =BK19-BK23 -> #REF!
J26: FLUJO DE CAJA LIBRE (FCF) | O26: =+O19-O24 -> 0 | P26: =+P19-P24 -> #REF! | Q26: =+Q19-Q24 -> -6046273 | R26: =+R19-R24 -> 0 | S26: =+S19-S24 -> 0 | T26: =T19+T24 -> 0 | U26: =U19+U24 -> 0 | X26: VALOR PRESENTE | AA26: =AA23/((1+$AA$11)^AA6) -> #DIV/0! | AB26: =AB23/((1+$AA$11)^AB6) -> #DIV/0! | AC26: =AC23/((1+$AA$11)^AC6) -> #DIV/0! | AD26: =AD23/((1+$AA$11)^AD6) -> #DIV/0! | AE26: =AE23/((1+$AA$11)^AE6) -> #DIV/0! | AF26: =AF23/((1+$AA$11)^AF6) -> #REF! | AM26: VALOR PRESENTE | AP26: =AP23/((1+$AP$11)^AP6) -> #REF! | AQ26: =AQ23/((1+$AP$11)^AQ6) -> #REF! | AR26: =AR23/((1+$AP$11)^AR6) -> #REF! | AS26: =AS23/((1+$AP$11)^AS6) -> #REF! | AT26: =AT23/((1+$AP$11)^AT6) -> #REF! | AU26: =AU23/((1+$AP$11)^AU6) -> #REF! | BC26: VALOR PRESENTE | BF26: =BF23/((1+$AA$11)^BF6) -> #DIV/0! | BG26: =BG23/((1+$AA$11)^BG6) -> #DIV/0! | BH26: =BH23/((1+$AA$11)^BH6) -> #DIV/0! | BI26: =BI23/((1+$AA$11)^BI6) -> #DIV/0! | BJ26: =BJ23/((1+$AA$11)^BJ6) -> #DIV/0! | BK26: =BK23/((1+$AA$11)^BK6) -> #REF!
J27: REINVERSIÓN | O27: =1-(O26/O15) -> #DIV/0! | P27: =1-(P26/P15) -> #REF! | Q27: =1-(Q26/Q15) -> #DIV/0! | R27: =1-(R26/R15) -> #DIV/0! | S27: =1-(S26/S15) -> #DIV/0! | T27: =1-(T26/T15) -> #DIV/0! | U27: =1-(U26/U15) -> #DIV/0!
J28: FCF % | O28: =1-O27 -> #DIV/0! | P28: =1-P27 -> #REF! | Q28: =1-Q27 -> #DIV/0! | R28: =1-R27 -> #DIV/0! | S28: =1-S27 -> #DIV/0! | T28: =1-T27 -> #DIV/0! | U28: =1-U27 -> #DIV/0! | X28: ∑ VP | AA28: =SUM(AA26:AF26) -> #DIV/0! | AM28: ∑ VP | AP28: =IF(SUM(AP26:AU26)>0,SUM(AP26:AU26),0) -> #REF! | BC28: ∑ VP | BF28: =SUM(BF26:BK26) -> #DIV/0!
J30: MEDIA FCF % | O30: =+U28 -> #DIV/0! | X30: DEUDA | AA30: #REF! | AM30: DEUDA LARGO PLAZO | AP30: =+'1. Datos'!H119 -> 0 | BC30: DEUDA | BF30: #REF!
J32: PROMEDIO FCF % | O32: =+AVERAGE(N28:R28) -> #DIV/0! | X32: VALOR DEL NEGOCIO | AA32: =#REF! -> #REF! | AM32: VALOR DEL NEGOCIO Números redondos | AP32: =ROUND(#REF!+#REF!,-3) -> #REF! | BC32: VALOR DE CAPITAL ACCIONARIO CAP | BF32: =BF28-BF30 -> #DIV/0!
J33: PARA EL FCF%
AA34: =AA26+AA24 -> #DIV/0! | AM34: VALOR NEGOCIO | AP34: =+AP28-AP30 -> #REF!
J35: REINVERSIÓN | O35: 0.3 | BC35: VALOR DEL NEGOCIO | BF35: =BF32 -> #DIV/0!
AM36: VALOR NEG REDONDEADO | AP36: =+ROUND(AP34,-3) -> #REF!
J37: REINVERSIÓN [Damodaran] | O37: =1-'reinvestment us'!D12 -> 1.3375347 | BC37: VALOR DE LA FIRMA | BF37: =BF32+BF30 -> #DIV/0!
AM38: VALOR FIRMA | AP38: =+AP36+AP30 -> #REF!
AW39: Articulo sexto | BC39: NÚMERO DE ACCIONES | BF39: =+AP36 -> #REF!
X40: VALOR DE LA FIRMA | AA40: =#REF!+AA30 -> #REF! | AM40: VALOR TOTAL DE LA ENTIDAD | AP40: =+AP32+AP34 -> #REF!
AC41: #REF! | BC41: VALOR POR ACCIÓN | BF41: =BF35/BF39 -> #DIV/0!
AP48: Valor Empresa | AQ48: =AP36 -> #REF!
AP49: Valor Marca
AN51: VENTAS ANUALES POR EL MULTIPLO DE LAS VENTAS | AP51: %Valor sobre Neg.
AN52: =+AS48*'EV SALES'!E46 -> 0 | AS52: PROPIO | AT52: SECTOR | AU52: FACTOR DE HOMOLOGACION
AP53: Factor Homologacion Operacion + Crecimiento | AR53: 0.8 | AS53: =AP18 -> #DIV/0! | AT53: ='reinvestment us'!E51 -> 0.071954485 | AU53: 0.8
AP54: Factor Homologacion (Rentabilidad) | AR54: 0.2 | AS54: NO HAY DATOS | AT54: ='operating margin'!C52 -> 0.382486 | AU54: 0.5
AT55: f.h. | AU55: 0.5
AU56: =AVERAGE(AU53:AU55) -> 0.6
AQ58: EBIT / EV (FCFF ) | AR58: EBIT SECTOR | AS58: EBT HOMOLOGADO
AP59: EBIT/ EV | AQ59: =AP36/U11 -> #REF! | AR59: ='Industry Averages (3)'!I52 -> 17.991464 | AS59: =AR59*AU54 -> 8.9957321
AP60: SALES/EV | AQ60: 25 | AR60: ='EV SALES'!E51 -> 1.48 | AS60: =AR60*AU55 -> 0.74
AR63: MIN | AS63: =(U11*AQ59) -> #REF!
AR64: MAX | AS64: =AS59*U11 -> 0
AQ69: EV/EBIT (FCFF)
AQ70: EV/EBIT (SECTOR HOMOLOGADO)
AQ71: VALOR MINIMO DE LA EMPRESA (FCFF)
AQ72: VALOR MAXIMO DE LA EMPRESA (SECTOR HOMOLOGADO)
AQ73: VALOR PROMEDIO DE CONCLUSIÒN (MULTIPLO SECTOR HOMOLOGADO)

Sheet Multiplos damodaran
A1: Revenue Multiples by Sector (US)
A3: Data Used: Multiple data services
A5: Date of Analysis: Data used is as of January 2025
A7: Download as an excel file instead: https://www.stern.nyu.edu/~adamodar/pc/datasets/psdata.xls
A9: For global datasets: https://www.stern.nyu.edu/~adamodar/New_Home_Page/data.html
A12: Indusry Name | B12: Number of firms | C12: Price/Sales | D12: Net Margin | E12: EV/Sales | F12: Pre-tax Operating Margin
A13: Advertising | B13: 54 | C13: 2.33 | D13: 0.03 | E13: 2.75 | F13: 0.1125
A14: Aerospace/Defense | B14: 67 | C14: 2.21 | D14: 0.0437 | E14: 2.6 | F14: 0.0766
A15: Air Transport | B15: 24 | C15: 0.55 | D15: 0.0221 | E15: 1.02 | F15: 0.0546
A16: Apparel | B16: 37 | C16: 1.09 | D16: 0.0298 | E16: 1.41 | F16: 0.0961
A17: Auto & Truck | B17: 34 | C17: 2.94 | D17: 0.0377 | E17: 3.47 | F17: 0.0321
A18: Auto Parts | B18: 33 | C18: 0.55 | D18: 0.0227 | E18: 0.75 | F18: 0.0521
A19: Bank (Money Center) | B19: 15 | C19: NA | D19: NA | E19: NA | F19: NA
A20: Banks (Regional) | B20: 591 | C20: NA | D20: NA | E20: NA | F20: NA
A21: Beverage (Alcoholic) | B21: 18 | C21: 2.58 | D21: 0.0929 | E21: 3.3 | F21: 0.2288
A22: Beverage (Soft) | B22: 29 | C22: 3.47 | D22: 0.1407 | E22: 4 | F22: 0.2013
A23: Broadcasting | B23: 22 | C23: 0.57 | D23: -0.0564 | E23: 1.29 | F23: 0.1251
A24: Brokerage & Investment Banking | B24: 30 | C24: NA | D24: NA | E24: NA | F24: NA
A25: Building Materials | B25: 39 | C25: 2.03 | D25: 0.1056 | E25: 2.33 | F25: 0.135
A26: Business & Consumer Services | B26: 152 | C26: 2.6 | D26: 0.0709 | E26: 2.93 | F26: 0.1224
A27: Cable TV | B27: 9 | C27: 1.03 | D27: 0.0758 | E27: 2.27 | F27: 0.1817
A28: Chemical (Basic) | B28: 31 | C28: 0.7 | D28: 0.0276 | E28: 1.03 | F28: 0.0625
A29: Chemical (Diversified) | B29: 4 | C29: 0.51 | D29: -0.005 | E29: 1 | F29: 0.0448
A30: Chemical (Specialty) | B30: 60 | C30: 2.26 | D30: 0.0646 | E30: 2.77 | F30: 0.1217
A31: Coal & Related Energy | B31: 16 | C31: 1.64 | D31: 0.1006 | E31: 1.57 | F31: 0.1111
A32: Computer Services | B32: 63 | C32: 1.16 | D32: 0.0415 | E32: 1.38 | F32: 0.0631
A33: Computers/Peripherals | B33: 35 | C33: 6.46 | D33: 0.1678 | E33: 6.68 | F33: 0.2267
A34: Construction Supplies | B34: 46 | C34: 2.1 | D34: 0.1123 | E34: 2.46 | F34: 0.1519
A35: Diversified | B35: 21 | C35: 2.61 | D35: 0.2515 | E35: 2.91 | F35: 0.3297
A36: Drugs (Biotechnology) | B36: 535 | C36: 6.11 | D36: -0.132 | E36: 6.79 | F36: 0.013
... A108: Total Market (without financials) | B108: 4935 | C108: 2.58 | D108: 0.0733 | E108: 2.99 | F108: 0.1187

Sheet reinvestment us
A1: Date updated: | B1: 45662
A2: Created by: | B2: Aswath Damodaran, adamodar@stern.nyu.edu
A3: What is this data? | B3: Fundamental (Sustainable) growth rate in operating income | F3: US companies
A4: Home Page: | B4: http://www.damodaran.com
A5: Data website: | B5: https://pages.stern.nyu.edu/adamodar/pc/datasets/fundgrEB.xls
A6: Companies in each industry: | B6: https://pages.stern.nyu.edu/~adamodar/pc/datasets/indname.xls
A7: Variable definitions: | B7: https://pages.stern.nyu.edu/~adamodar/New_Home_Page/datafile/variable.htm
A8: Industry Name | B8: Number of Firms | C8: ROC | D8: Reinvestment Rate | E8: Expected Growth in EBIT
A9: Advertising | B9: 54 | C9: 0.34913077 | D9: 0.16148109 | E9: 0.056378015
A10: Aerospace/Defense | B10: 67 | C10: 0.14025351 | D10: 0.65008606 | E10: 0.091176853
A11: Air Transport | B11: 24 | C11: 0.084763986 | D11: 0.99545339 | E11: 0.084378597
A12: Apparel | B12: 37 | C12: 0.15256209 | D12: -0.33753473 | E12: -0.051495005
A13: Auto & Truck | B13: 34 | C13: 0.031538761 | D13: 0.31341819 | E13: 0.0098848213
A14: Auto Parts | B14: 33 | C14: 0.08659675 | D14: 0.98724784 | E14: 0.085492454
A15: Bank (Money Center) | B15: 15 | C15: NA | D15: NA | E15: NA
A16: Banks (Regional) | B16: 591 | C16: NA | D16: NA | E16: NA
A17: Beverage (Alcoholic) | B17: 18 | C17: 0.17863486 | D17: 0.35708516 | E17: 0.063787858
A18: Beverage (Soft) | B18: 29 | C18: 0.30609597 | D18: 0.26994041 | E18: 0.082627674
A19: Broadcasting | B19: 22 | C19: 0.12676647 | D19: 2.0277458 | E19: 0.25705017
A20: Brokerage & Investment Banking | B20: 30 | C20: NA | D20: NA | E20: NA
A21: Building Materials | B21: 39 | C21: 0.26836667 | D21: 1.357634 | E21: 0.36434372
A22: Business & Consumer Services | B22: 152 | C22: 0.26832207 | D22: 0.046745076 | E22: 0.012542735
A23: Cable TV | B23: 9 | C23: 0.13752245 | D23: 0.04818005 | E23: 0.0066258386
A24: Chemical (Basic) | B24: 31 | C24: 0.087115256 | D24: 0.69395624 | E24: 0.060454176
A25: Chemical (Diversified) | B25: 4 | C25: 0.053536736 | D25: 0.2143221 | E25: 0.011474106
A26: Chemical (Specialty) | B26: 60 | C26: 0.11308896 | D26: 0.54297215 | E26: 0.061404153
A27: Coal & Related Energy | B27: 16 | C27: 0.13136099 | D27: 0.7841825 | E27: 0.10301099
A28: Computer Services | B28: 63 | C28: 0.2051186 | D28: -0.1352498 | E28: -0.027742249
A29: Computers/Peripherals | B29: 35 | C29: 0.41408712 | D29: 0.021789697 | E29: 0.0090228328
A30: Construction Supplies | B30: 46 | C30: 0.18411663 | D30: 0.4233188 | E30: 0.077940033
A31: Diversified | B31: 21 | C31: 0.24653408 | D31: 0.10870946 | E31: 0.026800586
A32: Drugs (Biotechnology) | B32: 535 | C32: 0.030814784 | D32: NA | E32: NA
A33: Drugs (Pharmaceutical) | B33: 231 | C33: 0.1407987 | D33: 1.1762437 | E33: 0.16561358
A34: Education | B34: 29 | C34: 0.11855547 | D34: 0.30448849 | E34: 0.036098776
A35: Electrical Equipment | B35: 101 | C35: 0.12226468 | D35: 2.0270788 | E35: 0.24784015
A36: Electronics (Consumer & Office) | B36: 11 | C36: -0.058115332 | D36: NA | E36: NA
A37: Electronics (General) | B37: 122 | C37: 0.13112418 | D37: 0.54226763 | E37: 0.071104397
A38: Engineering/Construction | B38: 42 | C38: 0.19158079 | D38: 0.84197589 | E38: 0.1613064
A39: Entertainment | B39: 96 | C39: 0.099413466 | D39: -0.71185667 | E39: -0.070768139
A40: Environmental & Waste Services | B40: 50 | C40: 0.31722931 | D40: 0.5897644 | E40: 0.18709055
A41: Farming/Agriculture | B41: 35 | C41: 0.099660979 | D41: 0.44796407 | E41: 0.044644538
A42: Financial Svcs. (Non-bank & Insurance) | B42: 166 | C42: NA | D42: 0.14977712 | E42: NA
A43: Food Processing | B43: 77 | C43: 0.17900874 | D43: 0.41589524 | E43: 0.074448885
A44: Food Wholesalers | B44: 14 | C44: 0.1730373 | D44: 0.72301944 | E44: 0.12510933
A45: Furn/Home Furnishings | B45: 28 | C45: 0.10653951 | D45: 0.11503778 | E45: 0.012256069
A46: Green & Renewable Energy | B46: 18 | C46: 0.036682308 | D46: 1.5993934 | E46: 0.058669442
A47: Healthcare Products | B47: 218 | C47: 0.14710426 | D47: 0.55462868 | E47: 0.081588239
A48: Healthcare Support Services | B48: 113 | C48: 0.44602956 | D48: 0.45953028 | E48: 0.20496409
A49: Heathcare Information and Technology | B49: 116 | C49: 0.12742981 | D49: 0.3802678 | E49: 0.048457455
A50: Homebuilding | B50: 30 | C50: 0.21045793 | D50: 0.51379466 | E50: 0.10813216
A51: Hospitals/Healthcare Facilities | B51: 33 | C51: 0.21189862 | D51: 0.33957034 | E51: 0.071954485
A52: Hotel/Gaming | B52: 65 | C52: 0.12172347 | D52: 0.25417209 | E52: 0.030938709
A53: Household Products | B53: 101 | C53: 0.33557668 | D53: 0.012952165 | E53: 0.0043464443
A54: Information Services | B54: 16 | C54: 0.24548991 | D54: 0.44710104 | E54: 0.10975879
... A72: Real Estate (Development) | B72: 15 | C72: 0.037347091 | D72: -1.0603867 | E72: -0.039602359
A73: Real Estate (General/Diversified) | B73: 11 | C73: 0.039730511 | D73: 1.0821106 | E73: 0.042992808 | G73: =AVERAGE(D73,D72,D51,D33,D31) -> 0.32924948
A74: Real Estate (Operations & Services) | B74: 60 | C74: 0.028763125 | D74: 3.6429856 | E74: 0.10478365
A75: Recreation | B75: 50 | C75: 0.079461316 | D75: 0.14852086 | E75: 0.011801663
A76: Reinsurance | B76: 1 | C76: 0.098903244 | D76: 0.5108018 | E76: 0.050519955
A77: Restaurant/Dining | B77: 62 | C77: 0.20394892 | D77: 0.38719269 | E77: 0.078967531
A78: Retail (Automotive) | B78: 29 | C78: 0.1211501 | D78: 0.82898584 | E78: 0.10043172
A79: Retail (Building Supply) | B79: 13 | C79: 0.36284597 | D79: 0.71689216 | E79: 0.26012143
A80: Retail (Distributors) | B80: 66 | C80: 0.17536862 | D80: 1.0195444 | E80: 0.17879609
A81: Retail (General) | B81: 24 | C81: 0.11983291 | D81: 0.46411455 | E81: 0.055616195
A82: Retail (Grocery and Food) | B82: 17 | C82: 0.092473762 | D82: 0.14685771 | E82: 0.013580485
A83: Retail (REITs) | B83: 28 | C83: 0.049993891 | D83: -0.74880213 | E83: -0.037435532
A84: Retail (Special Lines) | B84: 98 | C84: 0.17678385 | D84: 0.23842468 | E84: 0.042149633
A85: Rubber& Tires | B85: 3 | C85: 0.057556754 | D85: 0.16171849 | E85: 0.0093079915
... A104: Total Market (without financials) | B104: 4935 | C104: 0.15008473 | D104: 0.50790119 | E104: 0.076228212
C105: =AVERAGE(C22,C54) -> 0.25690599 | D105: =AVERAGE(D22,D54) -> 0.24692306 | E105: =AVERAGE(E22,E54) -> 0.061150764

Sheet Razones financieras
B1: RAZONES FINANCIERAS
B3: Pesos Constantes
B4: DATOS | D4: 2015 | E4: 2019 | F4: =+E4+1 -> 2020 | G4: =+F4+1 -> 2021 | H4: =+G4+1 -> 2022 | I4: =+H4+1 -> 2023 | J4: =+I4+1 -> 2024
B5: Ventas Netas | D5: =+#REF! -> #REF! | E5: =+'1. Datos'!D8 -> 0 | F5: =+'1. Datos'!E8 -> 0 | G5: =+'1. Datos'!F8 -> 0 | H5: =+'1. Datos'!G8 -> 0 | I5: =+'1. Datos'!H8 -> 0 | J5: =+'1. Datos'!I8 -> 0
B6: UN (Utilidad Neta) | D6: =+#REF! -> #REF! | E6: =+'1. Datos'!D30 -> 0 | F6: =+'1. Datos'!E30 -> 0 | G6: =+'1. Datos'!F30 -> 0 | H6: =+'1. Datos'!G30 -> 0 | I6: =+'1. Datos'!H30 -> 0 | J6: =+'1. Datos'!I30 -> 0
B7: Activo Total | D7: =+#REF! -> #REF! | E7: =+'1. Datos'!D95 -> 0 | F7: =+'1. Datos'!E95 -> 0 | G7: =+'1. Datos'!F95 -> 0 | H7: =+'1. Datos'!G95 -> 0 | I7: =+'1. Datos'!H95 -> 0 | J7: =+'1. Datos'!I95 -> 0
B8: Pasivo Total | D8: =+#REF! -> #REF! | E8: =+'1. Datos'!D123 -> 0 | F8: =+'1. Datos'!E123 -> 0 | G8: =+'1. Datos'!F123 -> 0 | H8: =+'1. Datos'!G123 -> 0 | I8: =+'1. Datos'!H123 -> 0 | J8: =+'1. Datos'!I123 -> 0
B9: Capital Contable | D9: =+#REF! -> #REF! | E9: =+'1. Datos'!D135 -> 0 | F9: =+'1. Datos'!E135 -> 0 | G9: =+'1. Datos'!F135 -> 0 | H9: =+'1. Datos'!G135 -> 0 | I9: =+'1. Datos'!H135 -> 0 | J9: =+'1. Datos'!I135 -> 0
B10: AC (Activo Circulante) | D10: =+#REF! -> #REF! | E10: =+'1. Datos'!D44 -> 0 | F10: =+'1. Datos'!E44 -> 6046273 | G10: =+'1. Datos'!F44 -> 0 | H10: =+'1. Datos'!G44 -> 0 | I10: =+'1. Datos'!H44 -> 0 | J10: =+'1. Datos'!I44 -> 0
B11: PC (Pasivo Circulante) | D11: =+#REF! -> #REF! | E11: =+'1. Datos'!D104 -> 0 | F11: =+'1. Datos'!E104 -> 0 | G11: =+'1. Datos'!F104 -> 0 | H11: =+'1. Datos'!G104 -> 0 | I11: =+'1. Datos'!H104 -> 0 | J11: =+'1. Datos'!I104 -> 0
B12: AT (Activo Total) | D12: =+#REF! -> #REF! | E12: =+'1. Datos'!D95 -> 0 | F12: =+'1. Datos'!E95 -> 0 | G12: =+'1. Datos'!F95 -> 0 | H12: =+'1. Datos'!G95 -> 0 | I12: =+'1. Datos'!H95 -> 0 | J12: =+'1. Datos'!I95 -> 0
B13: PLP (Pasivo de Largo Plazo) | D13: =+#REF! -> #REF! | E13: =+'1. Datos'!D119 -> 0 | F13: =+'1. Datos'!E119 -> 0 | G13: =+'1. Datos'!F119 -> 0 | H13: =+'1. Datos'!G119 -> 0 | I13: =+'1. Datos'!H119 -> 0 | J13: =+'1. Datos'!I119 -> 0
B14: PT (Pasivo Total) | D14: =+#REF! -> #REF! | E14: =+'1. Datos'!D123 -> 0 | F14: =+'1. Datos'!E123 -> 0 | G14: =+'1. Datos'!F123 -> 0 | H14: =+'1. Datos'!G123 -> 0 | I14: =+'1. Datos'!H123 -> 0 | J14: =+'1. Datos'!I123 -> 0
B15: CC (Capital Contable) | D15: =+#REF! -> #REF! | E15: =+'1. Datos'!D125 -> 0 | F15: =+'1. Datos'!E125 -> 0 | G15: =+'1. Datos'!F125 -> 0 | H15: =+'1. Datos'!G125 -> 0 | I15: =+'1. Datos'!H125 -> 0 | J15: =+'1. Datos'!I125 -> 0
B16: CV (Costo de Ventas) | D16: =+#REF! -> #REF! | E16: =+'1. Datos'!D9 -> 0 | F16: =+'1. Datos'!E9 -> 0 | G16: =+'1. Datos'!F9 -> 0 | H16: =+'1. Datos'!G9 -> 0 | I16: =+'1. Datos'!H9 -> 0 | J16: =+'1. Datos'!I9 -> 0
B17: CxC Cuentas por Cobrar | D17: =+#REF! -> #REF! | E17: =+'1. Datos'!D47 -> 0 | F17: =+'1. Datos'!E47 -> 0 | G17: =+'1. Datos'!F47 -> 0 | H17: =+'1. Datos'!G47 -> 0 | I17: =+'1. Datos'!H47 -> 0 | J17: =+'1. Datos'!I47 -> 0
B18: CxP Cuentas por Pagar | D18: =+#REF! -> #REF! | E18: =+'1. Datos'!D104 -> 0 | F18: =+'1. Datos'!E104 -> 0 | G18: =+'1. Datos'!F104 -> 0 | H18: =+'1. Datos'!G104 -> 0 | I18: =+'1. Datos'!H104 -> 0 | J18: =+'1. Datos'!I104 -> 0
B19: UB (Utilidad Bruta) | D19: =+#REF! -> #REF! | E19: =+'1. Datos'!D10 -> 0 | F19: =+'1. Datos'!E10 -> 0 | G19: =+'1. Datos'!F10 -> 0 | H19: =+'1. Datos'!G10 -> 0 | I19: =+'1. Datos'!H10 -> 0 | J19: =+'1. Datos'!I10 -> 0
B20: UO (Utilidad Operativa) | D20: =+#REF! -> #REF! | E20: =+'1. Datos'!D15 -> 0 | F20: =+'1. Datos'!E15 -> 0 | G20: =+'1. Datos'!F15 -> 0 | H20: =+'1. Datos'!G15 -> 0 | I20: =+'1. Datos'!H15 -> 0 | J20: =+'1. Datos'!I15 -> 0
B21: Inventarios | D21: =+#REF! -> #REF! | E21: =+'1. Datos'!D57 -> 0 | F21: =+'1. Datos'!E57 -> 0 | G21: =+'1. Datos'!F57 -> 0 | H21: =+'1. Datos'!G57 -> 0 | I21: =+'1. Datos'!H57 -> 0 | J21: =+'1. Datos'!I57 -> 0
B22: AFn Activo Fijo Neto | D22: =+#REF! -> #REF! | E22: =+'1. Datos'!D44 -> 0 | F22: =+'1. Datos'!E44 -> 6046273 | G22: =+'1. Datos'!F44 -> 0 | H22: =+'1. Datos'!G44 -> 0 | I22: =+'1. Datos'!H44 -> 0 | J22: =+'1. Datos'!I44 -> 0
B23: Gastos Financieros (Intereses) | D23: =+#REF! -> #REF! | E23: =+'1. Datos'!D20 -> 0 | F23: =+'1. Datos'!E20 -> 0 | G23: =+'1. Datos'!F20 -> 0 | H23: =+'1. Datos'!G20 -> 0 | I23: =+'1. Datos'!H20 -> 0 | J23: =+'1. Datos'!I20 -> 0
B24: EBIT | E24: =+E20 -> 0 | F24: =+F20 -> 0 | G24: =+G20 -> 0 | H24: =+H20 -> 0 | I24: =+I20 -> 0 | J24: =+J20 -> 0
B26: ROE | E26: =+E6/E9 -> #DIV/0! | F26: =+F6/F9 -> #DIV/0! | G26: =+G6/G9 -> #DIV/0! | H26: =+H6/H9 -> #DIV/0! | I26: =+I6/I9 -> #DIV/0! | J26: =+J6/J9 -> #DIV/0! | K26: =+K6/K9 -> #DIV/0! | L26: Rentabilidad Patrimonial
A27: ROA | B27: ROA (Rentabilidad de Activos) | E27: =+E6/E7 -> #DIV/0! | F27: =+F6/F7 -> #DIV/0! | G27: =+G6/G7 -> #DIV/0! | H27: =+H6/H7 -> #DIV/0! | I27: =+I6/I7 -> #DIV/0! | J27: =+J6/J7 -> #DIV/0! | K27: =+K6/K7 -> #DIV/0! | L27: Palanqueo Operativo
A28: AF | B28: Apalancamiento Financiero | E28: =+E7/E9 -> #DIV/0! | F28: =+F7/F9 -> #DIV/0! | G28: =+G7/G9 -> #DIV/0! | H28: =+H7/H9 -> #DIV/0! | I28: =+I7/I9 -> #DIV/0! | J28: =+J7/J9 -> #DIV/0! | K28: =+K7/K9 -> #DIV/0! | L28: Palanqueo Financiero
A31: ROA | B31: Margen Neto | E31: =+E6/E5 -> #DIV/0! | F31: =+F6/F5 -> #DIV/0! | H31: =+H6/H5 -> #DIV/0! | I31: =+I6/I5 -> #DIV/0! | J31: =+J6/J5 -> #DIV/0! | K31: =+K6/K5 -> #DIV/0!
B32: Rotación de Activo Total | E32: =+E5/E7 -> #DIV/0! | F32: =+F5/F7 -> #DIV/0! | G32: =+G5/G7 -> #DIV/0! | H32: =+H5/H7 -> #DIV/0! | I32: =+I5/I7 -> #DIV/0! | J32: =+J5/J7 -> #DIV/0! | K32: =+K5/K7 -> #DIV/0!
A33: AF | B33: Apalancamiento Financiero | E33: =+E7/E9 -> #DIV/0! | F33: =+F7/F9 -> #DIV/0! | G33: =+G7/G9 -> #DIV/0! | H33: =+H7/H9 -> #DIV/0! | I33: =+I7/I9 -> #DIV/0! | J33: =+J7/J9 -> #DIV/0! | K33: =+K7/K9 -> #DIV/0!
B34: ROE [ROA*Apalanca. Fin] | E34: =+E31*E32*E33 -> #DIV/0! | F34: =+F31*F32*F33 -> #DIV/0! | G34: =+G31*G32*G33 -> #DIV/0! | H34: =+H31*H32*H33 -> #DIV/0! | I34: =+I31*I32*I33 -> #DIV/0! | J34: =+J31*J32*J33 -> #DIV/0! | K34: =+K31*K32*K33 -> #DIV/0!
B35: Prueba | E35: =+E26-E34 -> #DIV/0! | F35: =+F26-F34 -> #DIV/0! | G35: =+G26-G34 -> #DIV/0! | H35: =+H26-H34 -> #DIV/0! | I35: =+I26-I34 -> #DIV/0! | J35: =+J26-J34 -> #DIV/0!
B37: Razón Financiera | C37: Expresión | D37: =+D4 | E37: =+E4 | F37: =+F4 | G37: =+G4 | H37: =+H4 | I37: =+I4 | J37: =+J4 | K37: Promedio
B38: Circulante | C38: AC/PC | E38: =+E10/E11 -> #DIV/0! | F38: =+F10/F11 -> #DIV/0! | G38: =+G10/G11 -> #DIV/0! | H38: =+H10/H11 -> #DIV/0! | I38: =+I10/I11 -> #DIV/0! | J38: =+J10/J11 -> #DIV/0! | K38: =+AVERAGE(G38:J38) -> #DIV/0!
B39: Esta razón muestra la liquidez de la empresa. La empresa en los últimos 5 años ha cubierto su deuda de Corto Plazo a razon de 11.34 veces.
B41: Ácido | C41: (AC-Inv)/PC | E41: =+(E10-E21)/E11 -> #DIV/0! | F41: =+(F10-F21)/F11 -> #DIV/0! | G41: =+(G10-G21)/G11 -> #DIV/0! | H41: =+(H10-H21)/H11 -> #DIV/0! | I41: =+(I10-I21)/I11 -> #DIV/0! | J41: =+(J10-J21)/J11 -> #DIV/0!
B42: Esta razón muestra la liquidez de la empresa sin contar con los inventarios. La empresa muestra capacidad de liquidez sobre la deuda a corto plazo.
B44: Rotación cuentas por cobrar (días) | C44: (CxC*365) /Ventas | E44: =+(E17*365)/E5 -> #DIV/0! | F44: =+(F17*365)/F5 -> #DIV/0! | G44: =+(G17*365)/G5 -> #DIV/0! | H44: =+(H17*365)/H5 -> #DIV/0! | I44: =+(I17*365)/I5 -> #DIV/0! | J44: =+(J17*365)/J5 -> #DIV/0! | K44: =+AVERAGE(D44:J44) -> #DIV/0!
B45: Esto se refiere al número de días que se tarda la empresa en cobrar sus CxC. En promedio la empresa tarda 72 días en cobrar sus Cuentas por Cobrar.
B47: Rotación del inventario (días) | C47: (Inv*365)/CV | E47: =+(E21*365)/E16 -> #DIV/0! | F47: =+(F21*365)/F16 -> #DIV/0! | G47: =+(G21*365)/G16 -> #DIV/0! | H47: =+(H21*365)/H16 -> #DIV/0! | I47: =+AVERAGE(D47:H47) -> #DIV/0!
B48: Esta relación se refiere al número de días que tarda la empresa en vender sus inventarios. En promedio la empresa tarda 162 días en vender sus inventarios.
B50: Rotación del activo fijo | C50: Ventas netas/ AFn | D50: =+D5/D22 -> #REF! | E50: =+E5/E22 -> #DIV/0! | F50: =+F5/F22 -> 0 | G50: =+G5/G22 -> #DIV/0! | H50: =+H5/H22 -> #DIV/0! | I50: =+AVERAGE(E50:H50) -> #DIV/0!
B51: Esta razón financiera no es posible analizarla, ya que la empresa no reporta activo fijo en las declaraciones fiscales.
B53: Apalancamiento | C53: PT/CC | E53: =+E14/E15 -> #DIV/0! | F53: =+F14/F15 -> #DIV/0! | G53: =+G14/G15 -> #DIV/0! | H53: =+H14/H15 -> #DIV/0! | I53: =AVERAGE(E53:H53) -> #DIV/0!
B54: Esta razón se refiere a la proporcion que representa el Pasivo Total del Capital Contable. Esta razón muestra un eudentadmiento elevado.
B56: Capitalización | C56: PLP/CC | F56: =+F13/F15 -> #DIV/0! | G56: =+G13/G15 -> #DIV/0! | I56: =+AVERAGE(D56:H56) -> #DIV/0!
B57: Esta relación muestra la proporción que representa el Pasivo de Largo Plazo del Capital Contable. En los últimos 3 años se tiene un 33% de relación de la deuda de largo plazo con el capital contable. | J57: NA Sin suficiente información
B59: Cobertura de Intereses | C59: EBIT/Gastos Financieros(Intereses) | E59: =+E24/E23 -> #DIV/0! | F59: =+F24/F23 -> #DIV/0! | G59: =+G24/G23 -> #DIV/0! | H59: =+H24/H23 -> #DIV/0! | I59: =+AVERAGE(D59:H59) -> #DIV/0!
B60: No se analiza esta razón financiera.
B62: Margen Bruto de Venta | C62: UB/Ventas | E62: =+E19/E5 -> #DIV/0! | F62: =+F19/F5 -> #DIV/0! | G62: =+G19/G5 -> #DIV/0! | H62: =+H19/H5 -> #DIV/0! | I62: =+I19/I5 -> #DIV/0! | J62: =+J19/J5 -> #DIV/0! | K62: =+AVERAGE(G62:J62) -> #DIV/0!
B63: Se refiere a la proporción que representa la Utilidad Bruta de las Ventas. La empresa presenta un margen bruto del 89%. Esto representa el beneficio que se obtiene de la diferencia de un producto y su coste de producción.
B65: Margen Operativo de Venta | C65: UO/Ventas | E65: =+E20/E5 -> #DIV/0! | F65: =+F20/F5 -> #DIV/0! | G65: =+G20/G5 -> #DIV/0! | H65: =+H20/H5 -> #DIV/0! | I65: =+I20/I5 -> #DIV/0! | J65: =+J20/J5 -> #DIV/0! | K65: =+AVERAGE(G65:J65) -> #DIV/0!
B66: Se refiere a la proporción que representa la Utilidad Operativa de las ventas. Como se aprecia, el promedio de los últimos 4 años corresponde al 5%.

Sheet Estructura de deuda
A1: Date updated: | B1: 45662
A2: Created by: | B2: Aswath Damodaran, adamodar@stern.nyu.edu | I2: YouTube Video Guide
A3: What is this data? | B3: Cost of equity and capital (updateable) | F3: US companies
A4: Home Page: | B4: http://www.damodaran.com
A5: Data website: | B5: https://pages.stern.nyu.edu/adamodar/pc/datasets/waccGlobal.xls
A6: Companies in each industry: | B6: https://www.stern.nyu.edu/~adamodar/pc/datasets/indname.xls
A7: Variable definitions: | B7: https://www.stern.nyu.edu/~adamodar/New_Home_Page/datafile/variable.htm
A8: To update this spreadsheet, enter the following | G8: Cost of Debt Lookup Table (based on std dev in stock prices)
A9: Long Term Treasury bond rate = | D9: 0.0458 | G9: Standard Deviation | I9: Basis Spread
A10: Risk Premium to Use for Equity = | D10: 0.0571 | G10: 0 | H10: 0.3 | I10: 0.005
A11: Global Default Spread to add to cost of debt = | D11: 0.0104 | G11: 0.30001 | H11: 0.45 | I11: 0.0095
A12: Do you want to use the marginal tax rate for cost of debt? | F12: Yes | G12: 0.45001 | H12: 0.65 | I12: 0.012
A13: If yes, enter the marginal tax rate to use | F13: 0.2522 | G13: 0.650001 | H13: 0.8 | I13: 0.0183
G14: 0.800001 | H14: 0.9 | I14: 0.03
A15: These costs of capital are in US$. To convert to a different currency, please enter | G15: 0.900001 | H15: 1 | I15: 0.0442
A16: Expected inflation rate in local currency = | C16: 0.015 | G16: 1.000001 | H16: 10 | I16: 0.0728
A17: Expected inflation rate in US $ = | C17: 0.015
A19: Industry Name | B19: Number of Firms | C19: Beta | D19: Cost of Equity | E19: E/(D+E) | F19: Std Dev in Stock | G19: Cost of Debt | H19: Tax Rate | I19: After-tax Cost of Debt | J19: D/(D+E) | K19: Cost of Capital
A20: Advertising | B20: 417 | C20: 1.2544098 | D20: =$D$9+C20*$D$10 -> 0.1174268 | E20: 0.78092992 | F20: 0.4740903 | G20: =$D$9+VLOOKUP(F20,$G$10:$I$16,3)+$D$11 -> 0.0682 | H20: 0.14376235 | I20: =IF($F$12="Yes",G20*(1-$F$13),G20*(1-H20)) -> 0.05099996 | J20: =1-E20 -> 0.21907008 | K20: =D20*(1-J20)+I20*J20 -> 0.10287467
A21: Aerospace/Defense | B21: 300 | C21: 1.0371955 | D21: =$D$9+C21*$D$10 -> 0.10502386 | E21: 0.84083708 | F21: 0.4068127 | G21: =$D$9+VLOOKUP(F21,$G$10:$I$16,3)+$D$11 -> 0.0657 | H21: 0.094028579 | I21: =IF($F$12="Yes",G21*(1-$F$13),G21*(1-H21)) -> 0.04913046 | J21: =1-E21 -> 0.15916292 | K21: =D21*(1-J21)+I21*J21 -> 0.096127704
A22: Air Transport | B22: 151 | C22: 1.2946168 | D22: =$D$9+C22*$D$10 -> 0.11972262 | E22: 0.5196021 | F22: 0.34980433 | G22: =$D$9+VLOOKUP(F22,$G$10:$I$16,3)+$D$11 -> 0.0657 | H22: 0.12181028 | I22: =IF($F$12="Yes",G22*(1-$F$13),G22*(1-H22)) -> 0.04913046 | J22: =1-E22 -> 0.4803979 | K22: =D22*(1-J22)+I22*J22 -> 0.085810293
A23: Apparel | B23: 1194 | C23: 0.75053974 | D23: =$D$9+C23*$D$10 -> 0.088655819 | E23: 0.83583386 | F23: 0.38575066 | G23: =$D$9+VLOOKUP(F23,$G$10:$I$16,3)+$D$11 -> 0.0657 | H23: 0.13732623 | I23: =IF($F$12="Yes",G23*(1-$F$13),G23*(1-H23)) -> 0.04913046 | J23: =1-E23 -> 0.16416614 | K23: =D23*(1-J23)+I23*J23 -> 0.082167093
A24: Auto & Truck | B24: 162 | C24: 1.5289122 | D24: =$D$9+C24*$D$10 -> 0.13310089 | E24: 0.66839838 | F24: 0.4791066 | G24: =$D$9+VLOOKUP(F24,$G$10:$I$16,3)+$D$11 -> 0.0682 | H24: 0.099703363 | I24: =IF($F$12="Yes",G24*(1-$F$13),G24*(1-H24)) -> 0.05099996 | J24: =1-E24 -> 0.33160162 | K24: =D24*(1-J24)+I24*J24 -> 0.10587609
A25: Auto Parts | B25: 780 | C25: 1.2988008 | D25: =$D$9+C25*$D$10 -> 0.11996153 | E25: 0.73574085 | F25: 0.36388827 | G25: =$D$9+VLOOKUP(F25,$G$10:$I$16,3)+$D$11 -> 0.0657 | H25: 0.16103259 | I25: =IF($F$12="Yes",G25*(1-$F$13),G25*(1-H25)) -> 0.04913046 | J25: =1-E25 -> 0.26425915 | K25: =D25*(1-J25)+I25*J25 -> 0.10124377
A26: Bank (Money Center) | B26: 621 | C26: 0.79703325 | D26: =$D$9+C26*$D$10 -> 0.091310598 | E26: 0.27394055 | F26: 0.23784038 | G26: =$D$9+VLOOKUP(F26,$G$10:$I$16,3)+$D$11 -> 0.0612 | H26: 0.21638526 | I26: =IF($F$12="Yes",G26*(1-$F$13),G26*(1-H26)) -> 0.04576536 | J26: =1-E26 -> 0.72605945 | K26: =D26*(1-J26)+I26*J26 -> 0.058242048
A27: Banks (Regional) | B27: 849 | C27: 0.55704109 | D27: =$D$9+C27*$D$10 -> 0.077607046 | E27: 0.30646193 | F27: 0.27469873 | G27: =$D$9+VLOOKUP(F27,$G$10:$I$16,3)+$D$11 -> 0.0612 | H27: 0.18284346 | I27: =IF($F$12="Yes",G27*(1-$F$13),G27*(1-H27)) -> 0.04576536 | J27: =1-E27 -> 0.69353807 | K27: =D27*(1-J27)+I27*J27 -> 0.055523625
A28: Beverage (Alcoholic) | B28: 216 | C28: 0.86351324 | D28: =$D$9+C28*$D$10 -> 0.095106606 | E28: 0.80989113 | F28: 0.32159699 | G28: =$D$9+VLOOKUP(F28,$G$10:$I$16,3)+$D$11 -> 0.0657 | H28: 0.16215855 | I28: =IF($F$12="Yes",G28*(1-$F$13),G28*(1-H28)) -> 0.04913046 | J28: =1-E28 -> 0.19010887 | K28: =D28*(1-J28)+I28*J28 -> 0.086366133
A29: Beverage (Soft) | B29: 101 | C29: 0.57262637 | D29: =$D$9+C29*$D$10 -> 0.078496966 | E29: 0.84382469 | F29: 0.34852094 | G29: =$D$9+VLOOKUP(F29,$G$10:$I$16,3)+$D$11 -> 0.0657 | H29: 0.11828587 | I29: =IF($F$12="Yes",G29*(1-$F$13),G29*(1-H29)) -> 0.04913046 | J29: =1-E29 -> 0.15617531 | K29: =D29*(1-J29)+I29*J29 -> 0.073910642
A30: Broadcasting | B30: 126 | C30: 1.0043908 | D30: =$D$9+C30*$D$10 -> 0.10315072 | E30: 0.54483752 | F30: 0.39297439 | G30: =$D$9+VLOOKUP(F30,$G$10:$I$16,3)+$D$11 -> 0.0657 | H30: 0.14865863 | I30: =IF($F$12="Yes",G30*(1-$F$13),G30*(1-H30)) -> 0.04913046 | J30: =1-E30 -> 0.45516248 | K30: =D30*(1-J30)+I30*J30 -> 0.078562722
A31: Brokerage & Investment Banking | B31: 606 | C31: 0.9085138 | D31: =$D$9+C31*$D$10 -> 0.097676138 | E31: 0.31599792 | F31: 0.38888892 | G31: =$D$9+VLOOKUP(F31,$G$10:$I$16,3)+$D$11 -> 0.0657 | H31: 0.1318549 | I31: =IF($F$12="Yes",G31*(1-$F$13),G31*(1-H31)) -> 0.04913046 | J31: =1-E31 -> 0.68400208 | K31: =D31*(1-J31)+I31*J31 -> 0.064470793
... A115: Total Market (without financials) | B115: 42750 | C115: 1.048002 | D115: =$D$9+C115*$D$10 -> 0.10564091 | E115: 0.77228238 | F115: 0.41664367 | G115: =$D$9+VLOOKUP(F115,$G$10:$I$16,3)+$D$11 -> 0.0657 | H115: 0.1223853 | I115: =IF($F$12="Yes",G115*(1-$F$13),G115*(1-H115)) -> 0.04913046 | J115: =1-E115 -> 0.22771762 | K115: =D115*(1-J115)+I115*J115 -> 0.092772488
C116: =AVERAGE(C65,C33) -> 1.0700504 | D116: =AVERAGE(D65,D33) -> 0.10689988 | E116: =AVERAGE(E65,E33) -> 0.79921286 | F116: =AVERAGE(F65,F33) -> 0.4002483 | G116: =AVERAGE(G65,G33) -> 0.0657 | H116: =AVERAGE(H65,H33) -> 0.16692436 | I116: =AVERAGE(I65,I33) -> 0.04913046 | J116: =AVERAGE(J65,J33) -> 0.20078714 | K116: =AVERAGE(K65,K33) -> 0.095133686

Sheet BENEFICIO FISCAL
B1: Valor de Marca | C1: =+MARCA!D31 -> 0 | H1: TABLA DE AMORTIZACION MARCA (B2E BLUE ENERGY AND ELECTRICITY)
H2: Cálculo de Beneficio Fiscal por Deducción de Activo Intangible
B5: TAX AMORTIZATION BENEFIT (TAB) | H5: Valor de Activo Intangible | M5: =+C1 -> 0
B6: VALOR DEL ACTIVO | C6: =+MARCA!D26 -> 0 | H6: Tasa Descuento (Marca) | M6: =+C7 -> #DIV/0!
B7: TASA DE CAPITAL | C7: =+WACC!G28 -> #DIV/0! | H7: Años de Deducción | M7: =1/15% -> 6.6666667
B8: TASA FISCAL | C8: 0.3 | H8: Tasa Fiscal | M8: 0.3
B9: PERIODO (AMORTIZACION) | C9: =1/15% -> 6.6666667
B10: FACTOR DE CAPITALIZACIÓN | C10: =+(((1+C7)^C9-1)/(C7*(1+C7)^C9)) -> #DIV/0! | H10: Año | I10: Saldo Inicial | J10: Monto a Deducir | K10: Saldo Final | L10: Tasa por Año | M10: Beneficio Fiscal | N10: Periodo Desc. | O10: Factor Desc | P10: VP Beneficio Fiscal
B11: TASA FISCAL / PERIODO | C11: =+C8/C9 -> 0.045 | I11: A | J11: B | K11: C = A - B | L11: D | M11: E = D * B | N11: F | O11: G = 1/(1+TASA DESC)^(F) | P11: H = G * E
B12: TAB | C12: =1/(1-(C10*C11)) -> #DIV/0! | H12: 1 | I12: =M5 -> 0 | J12: =-I12*(15%) -> 0 | K12: =+I12+J12 -> 0 | L12: =M8 -> 0.3 | M12: =J12*L12 -> 0 | N12: 0.5 | O12: =1/(1+$M$6)^N12 -> #DIV/0! | P12: =O12*M12 -> #DIV/0!
H13: 2 | I13: =K12 -> 0 | J13: =+J12 -> 0 | K13: =+I13+J13 -> 0 | L13: =+L12 -> 0.3 | M13: =J13*L13 -> 0 | N13: 1.5 | O13: =1/(1+$M$6)^N13 -> #DIV/0! | P13: =O13*M13 -> #DIV/0!
H14: 3 | I14: =K13 -> 0 | J14: =+J13 -> 0 | K14: =+I14+J14 -> 0 | L14: =+L13 -> 0.3 | M14: =J14*L14 -> 0 | N14: 2.5 | O14: =1/(1+$M$6)^N14 -> #DIV/0! | P14: =O14*M14 -> #DIV/0!
H15: 4 | I15: =K14 -> 0 | J15: =+J14 -> 0 | K15: =+I15+J15 -> 0 | L15: =+L14 -> 0.3 | M15: =J15*L15 -> 0 | N15: 3.5 | O15: =1/(1+$M$6)^N15 -> #DIV/0! | P15: =O15*M15 -> #DIV/0!
H16: 5 | I16: =K15 -> 0 | J16: =+J15 -> 0 | K16: =+I16+J16 -> 0 | L16: =+L15 -> 0.3 | M16: =J16*L16 -> 0 | N16: 4.5 | O16: =1/(1+$M$6)^N16 -> #DIV/0! | P16: =O16*M16 -> #DIV/0!
H17: 6 | I17: =K16 -> 0 | J17: =+J16 -> 0 | K17: =+I17+J17 -> 0 | L17: =+L16 -> 0.3 | M17: =J17*L17 -> 0 | N17: 5.5 | O17: =1/(1+$M$6)^N17 -> #DIV/0! | P17: =O17*M17 -> #DIV/0!
H18: 7 | I18: =K17 -> 0 | J18: =-I12*(10%) -> 0 | K18: =+I18+J18 -> 0 | L18: =+L17 -> 0.3 | M18: =J18*L18 -> 0 | N18: =N17+(C9-6) -> 6.1666667 | O18: =1/(1+$M$6)^N18 -> #DIV/0! | P18: =O18*M18 -> #DIV/0!
J24: =+SUM(J12:J22) -> 0 | M24: =+SUM(M12:M22) -> 0 | P24: =+SUM(P12:P22) -> #DIV/0!
H26: Valor de Activo Intangible | N26: A | O26: =M5 -> 0
H27: VP Beneficio Fiscal | N27: B | O27: =-P24 -> #DIV/0!
H28: Valor de Intangible incluyendo Beneficio Fiscal | N28: C | O28: =+O27+O26 -> #DIV/0!
H30: Efecto por Beneficio Fiscal | N30: D = C / A | O30: =O28/O26 -> #DIV/0!

Sheet EV SALES
A1: Date updated: | B1: 45662
A2: Created by: | B2: Aswath Damodaran, adamodar@stern.nyu.edu
A3: What is this data? | B3: Revenue multiples | F3: Global
A4: Home Page: | B4: http://www.damodaran.com
A5: Data website: | B5: https://www.stern.nyu.edu/~adamodar/pc/datasets/psdata.xls
A6: Companies in each industry: | B6: https://www.stern.nyu.edu/~adamodar/pc/datasets/indname.xls
A7: Variable definitions: | B7: https://www.stern.nyu.edu/~adamodar/New_Home_Page/datafile/variable.htm
A8: Indusry Name | B8: Number of firms | C8: Price/Sales | D8: Net Margin | E8: EV/Sales | F8: Pre-tax Operating Margin
A9: Advertising | B9: 54 | C9: 2.33 | D9: 0.03 | E9: 2.75 | F9: 0.1125
A10: Aerospace/Defense | B10: 67 | C10: 2.21 | D10: 0.0437 | E10: 2.6 | F10: 0.0766
A11: Air Transport | B11: 24 | C11: 0.55 | D11: 0.0221 | E11: 1.02 | F11: 0.0546
A12: Apparel | B12: 37 | C12: 1.09 | D12: 0.0298 | E12: 1.41 | F12: 0.0961
A13: Auto & Truck | B13: 34 | C13: 2.94 | D13: 0.0377 | E13: 3.47 | F13: 0.0321
A14: Auto Parts | B14: 33 | C14: 0.55 | D14: 0.0227 | E14: 0.75 | F14: 0.0521
A15: Bank (Money Center) | B15: 15 | C15: NA | D15: NA | E15: NA | F15: NA
A16: Banks (Regional) | B16: 591 | C16: NA | D16: NA | E16: NA | F16: NA
A17: Beverage (Alcoholic) | B17: 18 | C17: 2.58 | D17: 0.0929 | E17: 3.3 | F17: 0.2288
A18: Beverage (Soft) | B18: 29 | C18: 3.47 | D18: 0.1407 | E18: 4 | F18: 0.2013
A19: Broadcasting | B19: 22 | C19: 0.57 | D19: -0.0564 | E19: 1.29 | F19: 0.1251
A20: Brokerage & Investment Banking | B20: 30 | C20: NA | D20: NA | E20: NA | F20: NA
A21: Building Materials | B21: 39 | C21: 2.03 | D21: 0.1056 | E21: 2.33 | F21: 0.135
A22: Business & Consumer Services | B22: 152 | C22: 2.6 | D22: 0.0709 | E22: 2.93 | F22: 0.1224
A23: Cable TV | B23: 9 | C23: 1.03 | D23: 0.0758 | E23: 2.27 | F23: 0.1817
A24: Chemical (Basic) | B24: 31 | C24: 0.7 | D24: 0.0276 | E24: 1.03 | F24: 0.0625
A25: Chemical (Diversified) | B25: 4 | C25: 0.51 | D25: -0.005 | E25: 1 | F25: 0.0448
A26: Chemical (Specialty) | B26: 60 | C26: 2.26 | D26: 0.0646 | E26: 2.77 | F26: 0.1217
A27: Coal & Related Energy | B27: 16 | C27: 1.64 | D27: 0.1006 | E27: 1.57 | F27: 0.1111
A28: Computer Services | B28: 63 | C28: 1.16 | D28: 0.0415 | E28: 1.38 | F28: 0.0631
A29: Computers/Peripherals | B29: 35 | C29: 6.46 | D29: 0.1678 | E29: 6.68 | F29: 0.2267
A30: Construction Supplies | B30: 46 | C30: 2.1 | D30: 0.1123 | E30: 2.46 | F30: 0.1519
A31: Diversified | B31: 21 | C31: 2.61 | D31: 0.2515 | E31: 2.91 | F31: 0.3297
A32: Drugs (Biotechnology) | B32: 535 | C32: 6.11 | D32: -0.132 | E32: 6.79 | F32: 0.013
... A104: Total Market (without financials) | B104: 4935 | C104: 2.58 | D104: 0.0733 | E104: 2.99 | F104: 0.1187

Sheet operating margin
A1: Date updated: | B1: 45662
A2: Created by: | B2: Aswath Damodaran, adamodar@stern.nyu.edu
A3: What is this data? | B3: Profit margins (net, operating and EBITDA) | F3: Global
A4: Home Page: | B4: http://www.damodaran.com
A5: Data website: | B5: https://pages.stern.nyu.edu/~adamodar/pc/datasets/margin.xls
A6: Companies in each industry: | B6: https://pages.stern.nyu.edu/~adamodar/pc/datasets/indname.xls
A7: Variable definitions: | B7: https://pages.stern.nyu.edu/~adamodar/New_Home_Page/datafile/variable.htm
C8: Gross Income Based | D8: Net Income Based | E8: Operating Income Based | L8: EBITDA Based | O8: Expense Ratios
A9: Industry Name | B9: Number of firms | C9: Gross Margin | D9: Net Margin | E9: Pre-tax, Pre-stock compensation Operating Margin | F9: Pre-tax Unadjusted Operating Margin | G9: After-tax Unadjusted Operating Margin | H9: Pre-tax Lease adjusted Margin | I9: After-tax Lease Adjusted Margin | J9: Pre-tax Lease & R&D adj Margin | K9: After-tax Lease & R&D adj Margin | L9: EBITDA/Sales | M9: EBITDASG&A/Sales | N9: EBITDAR&D/Sales | O9: COGS/Sales | P9: R&D/Sales | Q9: SG&A/ Sales | R9: Stock-Based Compensation/Sales | S9: Lease Expense/Sales
A10: Advertising | B10: 54 | C10: 0.29912828 | D10: 0.029977379 | E10: 0.13611637 | F10: 0.10900602 | G10: 0.10064934 | H10: 0.11248214 | I10: 0.10385897 | J10: 0.11395905 | K10: 0.10533588 | L10: 0.1371755 | M10: 0.27287213 | N10: 0.1586667 | O10: 0.70087172 | P10: 0.021491199 | Q10: 0.13569662 | R10: 0.027110346 | S10: 0.02995519
A11: Aerospace/Defense | B11: 67 | C11: 0.17053224 | D11: 0.043674714 | E11: 0.086169796 | F11: 0.075864631 | G11: 0.067501204 | H11: 0.076580514 | I11: 0.068138167 | J11: 0.078696976 | K11: 0.070254629 | L11: 0.11224699 | M11: 0.18385029 | N11: 0.15304657 | O11: 0.82946776 | P11: 0.040799584 | Q11: 0.071603299 | R11: 0.010305165 | S11: 0.0078836517
A12: Air Transport | B12: 24 | C12: 0.24959457 | D12: 0.022119117 | E12: 0.058816687 | F12: 0.055360162 | G12: 0.049742335 | H12: 0.054641866 | I12: 0.04909693 | J12: 0.055046004 | K12: 0.049501068 | L12: 0.11030959 | M12: 0.1477321 | N12: 0.11411594 | O12: 0.75040543 | P12: 0.0038063442 | Q12: 0.037422505 | R12: 0.0034565249 | S12: 0.072751431
A13: Apparel | B13: 37 | C13: 0.5427752 | D13: 0.029802062 | E13: 0.096738212 | F13: 0.087262866 | G13: 0.080215412 | H13: 0.096109272 | I13: 0.088347372 | J13: 0.096195175 | K13: 0.088433275 | L13: 0.11789018 | M13: 0.57109936 | N13: 0.11902554 | O13: 0.4572248 | P13: 0.0011353547 | Q13: 0.45320918 | R13: 0.0094753453 | S13: 0.059981857
A14: Auto & Truck | B14: 34 | C14: 0.11107096 | D14: 0.037724459 | E14: 0.039367954 | F14: 0.031316364 | G14: 0.030656069 | H14: 0.032089853 | I14: 0.031413249 | J14: 0.033115493 | K14: 0.032438889 | L14: 0.07036828 | M14: 0.13417989 | N14: 0.12357126 | O14: 0.88892904 | P14: 0.053202977 | Q14: 0.063811613 | R14: 0.0080515901 | S14: 0.0050572943
A15: Auto Parts | B15: 33 | C15: 0.15210531 | D15: 0.022724943 | E15: 0.058651218 | F15: 0.050968432 | G15: 0.044460719 | H15: 0.052069559 | I15: 0.045421252 | J15: 0.054112155 | K15: 0.047463848 | L15: 0.087049263 | M15: 0.16864225 | N15: 0.13288585 | O15: 0.84789469 | P15: 0.045836588 | Q15: 0.081592982 | R15: 0.0076827855 | S15: 0.008309311
A16: Bank (Money Center) | B16: 15 | C16: NA | D16: NA | E16: NA | F16: NA | G16: NA | H16: NA | I16: NA | J16: NA | K16: NA | L16: NA | M16: NA | N16: NA | O16: NA | P16: NA | Q16: NA | R16: NA | S16: NA
A17: Banks (Regional) | B17: 591 | C17: NA | D17: NA | E17: NA | F17: NA | G17: NA | H17: NA | I17: NA | J17: NA | K17: NA | L17: NA | M17: NA | N17: NA | O17: NA | P17: NA | Q17: NA | R17: NA | S17: NA
A18: Beverage (Alcoholic) | B18: 18 | C18: 0.46528973 | D18: 0.092860276 | E18: 0.23452996 | F18: 0.22851541 | G18: 0.20959668 | H18: 0.22883891 | I18: 0.2098934 | J18: 0.22883891 | K18: 0.2098934 | L18: 0.26042019 | M18: 0.48943228 | N18: 0.26042019 | O18: 0.53471027 | P18: 0 | Q18: 0.2290121 | R18: 0.0060145501 | S18: 0.015309155
A19: Beverage (Soft) | B19: 29 | C19: 0.54895938 | D19: 0.14069442 | E19: 0.20527463 | F19: 0.20008555 | G19: 0.18619901 | H19: 0.20129309 | I19: 0.18732273 | J19: 0.20137096 | K19: 0.1874006 | L19: 0.22192677 | M19: 0.56483841 | N19: 0.22688616 | O19: 0.45104062 | P19: 0.0049593951 | Q19: 0.34291164 | R19: 0.0051890731 | S19: 0.012585188
A20: Broadcasting | B20: 22 | C20: 0.39843104 | D20: -0.056440062 | E20: 0.13437367 | F20: 0.12511923 | G20: 0.11168609 | H20: 0.12512483 | I20: 0.11169109 | J20: 0.12512541 | K20: 0.11169167 | L20: 0.14183995 | M20: 0.37186999 | N20: 0.14188314 | O20: 0.60156896 | P20: 4.3190201e-05 | Q20: 0.23003005 | R20: 0.0092544364 | S20: 0.0086266668
A21: Brokerage & Investment Banking | B21: 30 | C21: NA | D21: NA | E21: NA | F21: NA | G21: NA | H21: NA | I21: NA | J21: NA | K21: NA | L21: NA | M21: NA | N21: NA | O21: NA | P21: NA | Q21: NA | R21: NA | S21: NA
A22: Building Materials | B22: 39 | C22: 0.32045378 | D22: 0.10557675 | E22: 0.14000812 | F22: 0.13339808 | G22: 0.10791027 | H22: 0.13496817 | I22: 0.10918037 | J22: 0.13659536 | K22: 0.11080756 | L22: 0.16564997 | M22: 0.33581878 | N22: 0.17843263 | O22: 0.67954622 | P22: 0.012782666 | Q22: 0.17016881 | R22: 0.0066100424 | S22: 0.0096359388
A23: Business & Consumer Services | B23: 152 | C23: 0.33701853 | D23: 0.070921379 | E23: 0.13400918 | F23: 0.1210671 | G23: 0.10595594 | H23: 0.12236237 | I23: 0.10708953 | J23: 0.12434266 | K23: 0.10906982 | L23: 0.15411705 | M23: 0.33650228 | N23: 0.16565307 | O23: 0.66298147 | P23: 0.011536016 | Q23: 0.18238522 | R23: 0.012942071 | S23: 0.014295974
A24: Cable TV | B24: 9 | C24: 0.57889817 | D24: 0.075825655 | E24: 0.19446007 | F24: 0.18459798 | G24: 0.16527551 | H24: 0.18170066 | I24: 0.16268147 | J24: 0.18156022 | K24: 0.16254103 | L24: 0.31604378 | M24: 0.56718987 | N24: 0.31797369 | O24: 0.42110183 | P24: 0.0019299148 | Q24: 0.25114609 | R24: 0.0098620971 | S24: 0.012727672
A25: Chemical (Basic) | B25: 31 | C25: 0.12540819 | D25: 0.027590835 | E25: 0.064860105 | F25: 0.060486894 | G25: 0.055664993 | H25: 0.06248075 | I25: 0.057499903 | J25: 0.062465659 | K25: 0.057484812 | L25: 0.12672654 | M25: 0.17857664 | N25: 0.13647848 | O25: 0.87459181 | P25: 0.0097519393 | Q25: 0.051850106 | R25: 0.0043732109 | S25: 0.021434477
A26: Chemical (Diversified) | B26: 4 | C26: 0.16469105 | D26: -0.0050040817 | E26: 0.04798536 | F26: 0.043609561 | G26: 0.043609561 | H26: 0.044811685 | I26: 0.044811685 | J26: 0.043824309 | K26: 0.043824309 | L26: 0.12000254 | M26: 0.22287329 | N26: 0.13782918 | O26: 0.83530895 | P26: 0.017826633 | Q26: 0.10287074 | R26: 0.0043757987 | S26: 0.013532551
A27: Chemical (Specialty) | B27: 60 | C27: 0.33765784 | D27: 0.064570177 | E27: 0.12766752 | F27: 0.11934945 | G27: 0.10743167 | H27: 0.12171002 | I27: 0.10955652 | J27: 0.1212337 | K27: 0.1090802 | L27: 0.19094716 | M27: 0.36829404 | N27: 0.21825948 | O27: 0.66234216 | P27: 0.027312319 | Q27: 0.17734688 | R27: 0.0083180768 | S27: 0.016036039
A28: Coal & Related Energy | B28: 16 | C28: 0.25073405 | D28: 0.10055876 | E28: 0.11617236 | F28: 0.10974054 | G28: 0.10669946 | H28: 0.11107209 | I28: 0.10799411 | J28: 0.11036163 | K28: 0.10728365 | L28: 0.31732854 | M28: 0.36322519 | N28: 0.32076615 | O28: 0.74926595 | P28: 0.0034376088 | Q28: 0.045896653 | R28: 0.0064318214 | S28: 0.01215408
A29: Computer Services | B29: 63 | C29: 0.24140785 | D29: 0.041466105 | E29: 0.068149003 | F29: 0.060552453 | G29: 0.054024015 | H29: 0.063077281 | I29: 0.05627663 | J29: 0.06447428 | K29: 0.057673628 | L29: 0.096616066 | M29: 0.24928993 | N29: 0.12030673 | O29: 0.75859215 | P29: 0.023690669 | Q29: 0.15267386 | R29: 0.0075965508 | S29: 0.010423224
A30: Computers/Peripherals | B30: 35 | C30: 0.38724509 | D30: 0.16782527 | E30: 0.25047978 | F30: 0.22650657 | G30: 0.20613761 | H30: 0.22673236 | I30: 0.2063431 | J30: 0.22950815 | K30: 0.20911889 | L30: 0.25460126 | M30: 0.34526072 | N30: 0.32468073 | O30: 0.61275491 | P30: 0.070079472 | Q30: 0.090659462 | R30: 0.02397321 | S30: 0.027681656
A31: Construction Supplies | B31: 46 | C31: 0.25981997 | D31: 0.11234137 | E31: 0.15546383 | F31: 0.15132789 | G31: 0.13081902 | H31: 0.15188477 | I31: 0.13130043 | J31: 0.1520683 | K31: 0.13148396 | L31: 0.18402556 | M31: 0.26592054 | N31: 0.20888079 | O31: 0.74018003 | P31: 0.024855229 | Q31: 0.081894979 | R31: 0.0041359322 | S31: 0.0062669399
A32: Diversified | B32: 21 | C32: 0.36461085 | D32: 0.25150091 | E32: 0.32965547 | F32: 0.32847329 | G32: 0.31200307 | H32: 0.32967589 | I32: 0.31314538 | J32: 0.33000089 | K32: 0.31347037 | L32: 0.33427944 | M32: 0.36287337 | N32: 0.34138199 | O32: 0.63538915 | P32: 0.0071025515 | Q32: 0.028593932 | R32: 0.0011821812 | S32: 0.0058466429
A33: Drugs (Biotechnology) | B33: 535 | C33: 0.56022158 | D33: -0.13204348 | E33: 0.087705443 | F33: 0.014221273 | G33: 0.014071313 | H33: 0.013020143 | I33: 0.012882849 | J33: 0.074882658 | K33: 0.074745364 | L33: 0.10909679 | M33: 0.43484798 | N33: 0.59123455 | O33: 0.43977842 | P33: 0.48213775 | Q33: 0.32575119 | R33: 0.073484171 | S33: 0.015105666
... A105: Total Market (without financials) | B105: 4935 | C105: 0.32389139 | D105: 0.073327089 | E105: 0.13338643 | F105: 0.11934235 | G105: 0.11128641 | H105: 0.11874755 | I105: 0.11073176 | J105: 0.12132099 | K105: 0.11330521 | L105: 0.1612103 | M105: 0.29812773 | N105: 0.20037312 | O105: 0.67610861 | P105: 0.039162816 | Q105: 0.13691743 | R105: 0.014044079 | S105: 0.014673652
C106: =AVERAGE(C23,C55) -> 0.3376046 | D106: =AVERAGE(D23,D55) -> 0.066586735 | E106: =AVERAGE(E23,E55) -> 0.13237191 | F106: =AVERAGE(F23,F55) -> 0.11822514 | G106: =AVERAGE(G23,G55) -> 0.10180274 | H106: =AVERAGE(H23,H55) -> 0.12192241 | I106: =AVERAGE(I23,I55) -> 0.10495046 | J106: =AVERAGE(J23,J55) -> 0.12339213 | ... N106: =AVERAGE(N23,N55) -> 0.17741603 | O106: =AVERAGE(D23,D55) -> 0.066586735 | P106: =AVERAGE(P23,P55) -> 0.015458913 | Q106: =AVERAGE(Q23,Q55) -> 0.18202064 | R106: =AVERAGE(R23,R55) -> 0.014146772 | S106: =AVERAGE(S23,S55) -> 0.017009578

Sheet Reinvestment Rate 25
A1: Date updated: | B1: 45662
A2: Created by: | B2: Aswath Damodaran, adamodar@stern.nyu.edu
A3: What is this data? | B3: Fundamental (Sustainable) growth rate in operating income | F3: US companies
A4: Home Page: | B4: http://www.damodaran.com
A5: Data website: | B5: https://pages.stern.nyu.edu/~adamodar/New_Home_Page/datafile/fundgrEB.html
A6: Companies in each industry: | B6: https://www.stern.nyu.edu/~adamodar/pc/datasets/indname.xls
A7: Variable definitions: | B7: https://www.stern.nyu.edu/~adamodar/New_Home_Page/datafile/variable.htm
A8: Industry Name | B8: Number of Firms | C8: ROC | D8: Reinvestment Rate | E8: Expected Growth in EBIT
A9: Advertising | B9: 54 | C9: 0.3491 | D9: 0.1615 | E9: 0.0564
A10: Aerospace/Defense | B10: 67 | C10: 0.1403 | D10: 0.6501 | E10: 0.0912
A11: Air Transport | B11: 24 | C11: 0.0848 | D11: 0.9955 | E11: 0.0844
A12: Apparel | B12: 37 | C12: 0.1526 | D12: -0.3375 | E12: -0.0515
A13: Auto & Truck | B13: 34 | C13: 0.0315 | D13: 0.3134 | E13: 0.0099
A14: Auto Parts | B14: 33 | C14: 0.0866 | D14: 0.9872 | E14: 0.0855
A15: Bank (Money Center) | B15: 15 | C15: NA | D15: NA | E15: NA
A16: Banks (Regional) | B16: 591 | C16: NA | D16: NA | E16: NA
A17: Beverage (Alcoholic) | B17: 18 | C17: 0.1786 | D17: 0.3571 | E17: 0.0638
A18: Beverage (Soft) | B18: 29 | C18: 0.3061 | D18: 0.2699 | E18: 0.0826
A19: Broadcasting | B19: 22 | C19: 0.1268 | D19: 2.0277 | E19: 0.2571
A20: Brokerage & Investment Banking | B20: 30 | C20: NA | D20: NA | E20: NA
A21: Building Materials | B21: 39 | C21: 0.2684 | D21: 1.3576 | E21: 0.3643
A22: Business & Consumer Services | B22: 152 | C22: 0.2683 | D22: 0.0467 | E22: 0.0125
A23: Cable TV | B23: 9 | C23: 0.1375 | D23: 0.0482 | E23: 0.0066
A24: Chemical (Basic) | B24: 31 | C24: 0.0871 | D24: 0.694 | E24: 0.0605
A25: Chemical (Diversified) | B25: 4 | C25: 0.0535 | D25: 0.2143 | E25: 0.0115
A26: Chemical (Specialty) | B26: 60 | C26: 0.1131 | D26: 0.543 | E26: 0.0614
A27: Coal & Related Energy | B27: 16 | C27: 0.1314 | D27: 0.7842 | E27: 0.103
A28: Computer Services | B28: 63 | C28: 0.2051 | D28: -0.1352 | E28: -0.0277
A29: Computers/Peripherals | B29: 35 | C29: 0.4141 | D29: 0.0218 | E29: 0.009
A30: Construction Supplies | B30: 46 | C30: 0.1841 | D30: 0.4233 | E30: 0.0779
A31: Diversified | B31: 21 | C31: 0.2465 | D31: 0.1087 | E31: 0.0268
A32: Drugs (Biotechnology) | B32: 535 | C32: 0.0308 | D32: NA | E32: NA
A33: Drugs (Pharmaceutical) | B33: 231 | C33: 0.1408 | D33: 1.1762 | E33: 0.1656
A34: Education | B34: 29 | C34: 0.1186 | D34: 0.3045 | E34: 0.0361
A35: Electrical Equipment | B35: 101 | C35: 0.1223 | D35: 2.0271 | E35: 0.2478
A36: Electronics (Consumer & Office) | B36: 11 | C36: -0.0581 | D36: NA | E36: NA
A37: Electronics (General) | B37: 122 | C37: 0.1311 | D37: 0.5423 | E37: 0.0711
A38: Engineering/Construction | B38: 42 | C38: 0.1916 | D38: 0.842 | E38: 0.1613
A39: Entertainment | B39: 96 | C39: 0.0994 | D39: -0.7119 | E39: -0.0708
A40: Environmental & Waste Services | B40: 50 | C40: 0.3172 | D40: 0.5898 | E40: 0.1871
A41: Farming/Agriculture | B41: 35 | C41: 0.0997 | D41: 0.448 | E41: 0.0446
A42: Financial Svcs. (Non-bank & Insurance) | B42: 166 | C42: NA | D42: 0.1498 | E42: NA
A43: Food Processing | B43: 77 | C43: 0.179 | D43: 0.4159 | E43: 0.0744
A44: Food Wholesalers | B44: 14 | C44: 0.173 | D44: 0.723 | E44: 0.1251
A45: Furn/Home Furnishings | B45: 28 | C45: 0.1065 | D45: 0.115 | E45: 0.0123
A46: Green & Renewable Energy | B46: 18 | C46: 0.0367 | D46: 1.5994 | E46: 0.0587
A47: Healthcare Products | B47: 218 | C47: 0.1471 | D47: 0.5546 | E47: 0.0816
A48: Healthcare Support Services | B48: 113 | C48: 0.446 | D48: 0.4595 | E48: 0.205
A49: Heathcare Information and Technology | B49: 116 | C49: 0.1274 | D49: 0.3803 | E49: 0.0485
A50: Homebuilding | B50: 30 | C50: 0.2105 | D50: 0.5138 | E50: 0.1081
A51: Hospitals/Healthcare Facilities | B51: 33 | C51: 0.2119 | D51: 0.3396 | E51: 0.072
A52: Hotel/Gaming | B52: 65 | C52: 0.1217 | D52: 0.2542 | E52: 0.0309
A53: Household Products | B53: 101 | C53: 0.3356 | D53: 0.013 | E53: 0.0043
A54: Information Services | B54: 16 | C54: 0.2455 | D54: 0.4471 | E54: 0.1098
... A104: Total Market (without financials) | B104: 4935 | C104: 0.1501 | D104: 0.5079 | E104: 0.0762

Sheet Historical Impl Premiums
A1: Date updated: | B1: 45661
A2: Created by: | B2: Aswath Damodaran, adamodar@stern.nyu.edu
A3: What is this data? | B3: Implied Equity Risk Premiums (by year) | F3: S&P 500
A4: Home Page: | B4: http://www.damodaran.com
A5: Data website: | B5: https://pages.stern.nyu.edu/~adamodar/New_Home_Page/data.html
A7: Year | B7: Earnings Yield | C7: Dividend Yield | D7: S&P 500 | E7: Earnings* | F7: Dividends* | G7: Dividends + Buybacks | H7: Change in Earnings | I7: Change in Dividends | J7: T.Bill Rate | K7: T.Bond Rate | L7: Bond-Bill | M7: Smoothed Growth | N7: Implied Premium (DDM) | O7: Analyst Growth Estimate | P7: Implied Premium (FCFE) | Q7: Implied Premium (FCFE with sustainable Payout) | R7: ERP/Riskfree Rate
A8: 1960 | B8: 0.0534 | C8: 0.0341 | D8: 58.11 | E8: 3.1 | F8: 1.98 | J8: 0.0266 | K8: 0.0276 | L8: 0.001 | M8: 0.0245
A9: 1961 | B9: 0.0471 | C9: 0.0285 | D9: 71.55 | E9: 3.37 | F9: 2.04 | H9: 0.086 | I9: 0.0291 | J9: 0.0213 | K9: 0.0235 | L9: 0.0022 | M9: 0.0241 | N9: 0.0292 | P9: 0.0292 | R9: 1.24
A10: 1962 | B10: 0.0581 | C10: 0.034 | D10: 63.1 | E10: 3.67 | F10: 2.15 | H10: 0.0879 | I10: 0.0521 | J10: 0.0273 | K10: 0.0385 | L10: 0.0112 | M10: 0.0405 | N10: 0.0356 | P10: 0.0356 | R10: 0.92
A11: 1963 | B11: 0.0551 | C11: 0.0313 | D11: 75.02 | E11: 4.13 | F11: 2.35 | H11: 0.1275 | I11: 0.0945 | J11: 0.0312 | K11: 0.0414 | L11: 0.0102 | M11: 0.0496 | N11: 0.0338 | P11: 0.0338 | R11: 0.82
A12: 1964 | B12: 0.0562 | C12: 0.0305 | D12: 84.75 | E12: 4.76 | F12: 2.58 | H12: 0.1523 | I12: 0.1008 | J12: 0.0354 | K12: 0.0421 | L12: 0.0067 | M12: 0.0513 | N12: 0.0331 | P12: 0.0331 | R12: 0.79
A13: 1965 | B13: 0.0573 | C13: 0.0306 | D13: 92.43 | E13: 5.3 | F13: 2.83 | H13: 0.112 | I13: 0.0942 | J13: 0.0393 | K13: 0.0465 | L13: 0.0072 | M13: 0.0546 | N13: 0.0332 | P13: 0.0332 | R13: 0.71
A14: 1966 | B14: 0.0674 | C14: 0.0359 | D14: 80.33 | E14: 5.41 | F14: 2.88 | H14: 0.0223 | I14: 0.0196 | J14: 0.0476 | K14: 0.0464 | L14: -0.0012 | M14: 0.0419 | N14: 0.0368 | P14: 0.0368 | R14: 0.79
A15: 1967 | B15: 0.0566 | C15: 0.0309 | D15: 96.47 | E15: 5.46 | F15: 2.98 | H15: 0.0085 | I15: 0.0337 | J15: 0.0421 | K15: 0.057 | L15: 0.0149 | M15: 0.0525 | N15: 0.032 | P15: 0.032 | R15: 0.56
A16: 1968 | B16: 0.0551 | C16: 0.0293 | D16: 103.86 | E16: 5.72 | F16: 3.04 | H16: 0.0481 | I16: 0.0209 | J16: 0.0521 | K16: 0.0616 | L16: 0.0095 | M16: 0.0532 | N16: 0.03 | P16: 0.03 | R16: 0.49
A17: 1969 | B17: 0.0663 | C17: 0.0352 | D17: 92.06 | E17: 6.1 | F17: 3.24 | H17: 0.0666 | I17: 0.0649 | J17: 0.0658 | K17: 0.0788 | L17: 0.013 | M17: 0.0755 | N17: 0.0374 | P17: 0.0374 | R17: 0.47
A18: 1970 | B18: 0.0598 | C18: 0.0346 | D18: 92.15 | E18: 5.51 | F18: 3.19 | H18: -0.0972 | I18: -0.0161 | J18: 0.0653 | K18: 0.065 | L18: -0.0003 | M18: 0.0478 | N18: 0.0341 | P18: 0.0341 | R18: 0.52
A19: 1971 | B19: 0.0546 | C19: 0.031 | D19: 102.09 | E19: 5.57 | F19: 3.16 | H19: 0.0115 | I19: -0.0074 | J19: 0.0439 | K19: 0.0589 | L19: 0.015 | M19: 0.0457 | N19: 0.0309 | P19: 0.0309 | R19: 0.52
A20: 1972 | B20: 0.0523 | C20: 0.027 | D20: 118.05 | E20: 6.17 | F20: 3.19 | H20: 0.1076 | I20: 0.0071 | J20: 0.0384 | K20: 0.0641 | L20: 0.0257 | M20: 0.0521 | N20: 0.0272 | P20: 0.0272 | R20: 0.42
... A32: 1984 | B32: 0.1007 | C32: 0.0468 | D32: 167.24 | E32: 16.84 | F32: 7.83 | H32: 0.2669 | I32: 0.0985 | J32: 0.0985 | K32: 0.1151 | L32: 0.0166 | M32: 0.1102 | N32: 0.0511 | P32: 0.0511 | R32: 0.44
A33: 1985 | B33: 0.0742 | C33: 0.0388 | D33: 211.28 | E33: 15.68 | F33: 8.2 | H33: -0.0691 | I33: 0.0474 | J33: 0.0772 | K33: 0.0899 | L33: 0.0127 | M33: 0.0789 | N33: 0.0403 | O33: 0.0675 | P33: 0.0384 | R33: 0.43
A34: 1986 | B34: 0.0596 | C34: 0.0338 | D34: 242.17 | E34: 14.43 | F34: 8.19 | H34: -0.0793 | I34: -0.0015 | J34: 0.0616 | K34: 0.0722 | L34: 0.0106 | M34: 0.0554 | N34: 0.0336 | O34: 0.0696 | P34: 0.0358 | R34: 0.5
A35: 1987 | B35: 0.0649 | C35: 0.0371 | D35: 247.08 | E35: 16.04 | F35: 9.17 | H35: 0.111 | I35: 0.1199 | J35: 0.0547 | K35: 0.0886 | L35: 0.0339 | M35: 0.0966 | N35: 0.0418 | O35: 0.0858 | P35: 0.0399 | R35: 0.45
A36: 1988 | B36: 0.082 | C36: 0.0368 | D36: 277.72 | E36: 24.12 | F36: 10.22 | H36: 0.5042 | I36: 0.1149 | J36: 0.0635 | K36: 0.0914 | L36: 0.0279 | M36: 0.0976 | N36: 0.0412 | O36: 0.0767 | P36: 0.0377 | R36: 0.41
A37: 1989 | B37: 0.068 | C37: 0.0332 | D37: 353.4 | E37: 24.32 | F37: 11.73 | H37: 0.0083 | I37: 0.148 | J37: 0.0837 | K37: 0.0793 | L37: -0.0044 | M37: 0.0958 | N37: 0.0385 | O37: 0.0746 | P37: 0.0351 | R37: 0.44
A38: 1990 | B38: 0.0658 | C38: 0.0374 | D38: 330.22 | E38: 22.65 | F38: 12.35 | H38: -0.0687 | I38: 0.0526 | J38: 0.0781 | K38: 0.0807 | L38: 0.0026 | M38: 0.0739 | N38: 0.0392 | O38: 0.0719 | P38: 0.0389 | R38: 0.48
A39: 1991 | B39: 0.0458 | C39: 0.0311 | D39: 417.09 | E39: 19.3 | F39: 12.97 | H39: -0.1479 | I39: 0.0503 | J39: 0.07 | K39: 0.067 | L39: -0.003 | M39: 0.0634 | N39: 0.0327 | O39: 0.0781 | P39: 0.0348 | R39: 0.52
A40: 1992 | B40: 0.0416 | C40: 0.029 | D40: 435.71 | E40: 20.87 | F40: 12.64 | H40: 0.0813 | I40: -0.0259 | J40: 0.053 | K40: 0.0668 | L40: 0.0138 | M40: 0.0467 | N40: 0.0283 | O40: 0.0983 | P40: 0.0355 | R40: 0.53
A41: 1993 | B41: 0.0425 | C41: 0.0272 | D41: 466.45 | E41: 26.9 | F41: 12.69 | H41: 0.2889 | I41: 0.0041 | J41: 0.035 | K41: 0.0579 | L41: 0.0229 | M41: 0.0473 | N41: 0.0274 | O41: 0.08 | P41: 0.0317 | R41: 0.55
A42: 1994 | B42: 0.0589 | C42: 0.0291 | D42: 459.27 | E42: 31.75 | F42: 13.36 | H42: 0.1803 | I42: 0.0534 | J42: 0.05 | K42: 0.0782 | L42: 0.0282 | M42: 0.0723 | N42: 0.0306 | O42: 0.0717 | P42: 0.0355 | R42: 0.45
A43: 1995 | B43: 0.0574 | C43: 0.023 | D43: 615.93 | E43: 37.7 | F43: 14.17 | H43: 0.1874 | I43: 0.06 | J43: 0.035 | K43: 0.0557 | L43: 0.0207 | M43: 0.0565 | N43: 0.0244 | O43: 0.065 | P43: 0.0329 | R43: 0.59
A44: 1996 | B44: 0.0483 | C44: 0.0201 | D44: 740.74 | E44: 40.63 | F44: 14.89 | H44: 0.0777 | I44: 0.051 | J44: 0.05 | K44: 0.0641 | L44: 0.0141 | M44: 0.0613 | N44: 0.0211 | O44: 0.0792 | P44: 0.032 | R44: 0.5
... A48: 2000 | B48: 0.0394 | C48: 0.0123 | D48: 1320.28 | E48: 56.13 | F48: 16.27 | H48: 0.0861 | I48: -0.0265 | J48: 0.0573 | K48: 0.0511 | L48: -0.0062 | M48: 0.0371 | N48: 0.0165 | O48: 0.12 | P48: 0.0287 | R48: 0.56
A49: 2001 | B49: 0.0385 | C49: 0.0137 | D49: 1148.09 | E49: 38.85 | F49: 15.74 | G49: 30.08 | H49: -0.3079 | I49: -0.0324 | J49: 0.018 | K49: 0.0505 | L49: 0.0325 | M49: 0.0356 | N49: 0.0173 | O49: 0.103 | P49: 0.0362 | Q49: 0.0291 | R49: 0.72
A50: 2002 | B50: 0.0523 | C50: 0.0183 | D50: 879.82 | E50: 46.04 | F50: 16.08 | G50: 29.83 | H50: 0.1851 | I50: 0.0215 | J50: 0.012 | K50: 0.0381 | L50: 0.0261 | M50: 0.0357 | N50: 0.0229 | O50: 0.08 | P50: 0.041 | Q50: 0.0473 | R50: 1.08
A51: 2003 | B51: 0.0487 | C51: 0.0161 | D51: 1111.91 | E51: 54.69 | F51: 17.88 | G51: 31.58 | H51: 0.1879 | I51: 0.1119 | J51: 0.01 | K51: 0.0425 | L51: 0.0325 | M51: 0.0535 | N51: 0.0212 | O51: 0.11 | P51: 0.0369 | Q51: 0.0474 | R51: 0.87
A52: 2004 | B52: 0.0558 | C52: 0.016 | D52: 1211.92 | E52: 67.68 | F52: 19.407 | G52: 40.6 | H52: 0.2375 | I52: 0.0854 | J52: 0.0218 | K52: 0.0422 | L52: 0.0204 | M52: 0.049 | N52: 0.0202 | O52: 0.085 | P52: 0.0365 | Q52: 0.0486 | R52: 0.86
A53: 2005 | B53: 0.0547 | C53: 0.0179 | D53: 1248.29 | E53: 76.45 | F53: 22.38 | G53: 61.17 | H53: 0.1296 | I53: 0.1532 | J53: 0.0431 | K53: 0.0439 | L53: 0.0008 | M53: 0.0616 | N53: 0.022 | O53: 0.08 | P53: 0.0408 | Q53: 0.0522 | R53: 0.93
A54: 2006 | B54: 0.0618 | C54: 0.0177 | D54: 1418.3 | E54: 87.72 | F54: 25.05 | G54: 73.16 | H54: 0.1474 | I54: 0.1193 | J54: 0.0488 | K54: 0.047 | L54: -0.0018 | M54: 0.0593 | N54: 0.0197 | O54: 0.125 | P54: 0.0416 | Q54: 0.0612 | R54: 0.89
A55: 2007 | B55: 0.0562 | C55: 0.0189 | D55: 1468.36 | E55: 82.54 | F55: 27.73 | G55: 95.36 | H55: -0.0591 | I55: 0.107 | J55: 0.0331 | K55: 0.0402 | L55: 0.0071 | M55: 0.0503 | N55: 0.0206 | O55: 0.05 | P55: 0.0437 | Q55: 0.0459 | R55: 1.09
A56: 2008 | B56: 0.0724 | C56: 0.0311 | D56: 903.25 | E56: 65.39 | F56: 28.05 | G56: 67.52 | H56: -0.2078 | I56: 0.0115 | J56: 0.0159 | K56: 0.0221 | L56: 0.0062 | M56: 0.0211 | N56: 0.0405 | O56: 0.04 | P56: 0.0643 | Q56: 0.0692 | R56: 2.91
A57: 2009 | B57: 0.0535 | C57: 0.02 | D57: 1115.1 | E57: 59.65 | F57: 22.31 | G57: 37.43 | H57: -0.0878 | I57: -0.2046 | J57: 0.0014 | K57: 0.0384 | L57: 0.037 | M57: 0.0028 | N57: 0.026 | O57: 0.072 | P57: 0.0436 | Q57: 0.0464 | R57: 1.14
A58: 2010 | B58: 0.0665 | C58: 0.0184 | D58: 1257.64 | E58: 83.66 | F58: 23.12 | G58: 55.53 | H58: 0.4025 | I58: 0.0363 | J58: 0.0013 | K58: 0.0329 | L58: 0.0316 | M58: 0.0333 | N58: 0.0224 | O58: 0.0695 | P58: 0.052 | Q58: 0.0609 | R58: 1.58
A59: 2011 | B59: 0.0772 | C59: 0.0207 | D59: 1257.6 | E59: 97.05 | F59: 26.02 | G59: 71.28 | H59: 0.1601 | I59: 0.1254 | J59: 0.0003 | K59: 0.0188 | L59: 0.0185 | M59: 0.0275 | N59: 0.0271 | O59: 0.0718 | P59: 0.0601 | Q59: 0.0834 | R59: 3.2
A60: 2012 | B60: 0.0718 | C60: 0.0213 | D60: 1426.19 | E60: 102.47 | F60: 30.44 | G60: 75.9 | H60: 0.0558 | I60: 0.1699 | J60: 0.0005 | K60: 0.0176 | L60: 0.0171 | M60: 0.0293 | N60: 0.0247 | O60: 0.0527 | P60: 0.0578 | Q60: 0.073 | R60: 3.28
... A71: 2023 | B71: 0.0461 | C71: 0.0147 | D71: 4769.83 | E71: 219.7 | F71: 70.3 | G71: 164.25 | H71: 0.001 | I71: 0.0287 | J71: 0.052 | K71: 0.0388 | L71: -0.0132 | M71: 0.0373 | N71: 0.0197 | O71: 0.0874 | P71: 0.046 | Q71: 0.0457 | R71: 1.19
K72: =+AVERAGE(K51:K70) -> 0.02891
A75: * Earnings and dividends numbers each year reflect the estimated numbers as of the end of the year. These numbers get updated later in the year but I do not update the numbers in this spreadsheet, since I would not have had access to them at the end of the year.
B77: Period | C77: ERP | D77: ERP + Riskfree Rate
B78: 1960-2021 | C78: =AVERAGE(P9:P69) -> 0.042131148 | D78: =C78+AVERAGE(K9:K68) -> 0.10064948
B79: 2002-2021 | C79: =AVERAGE(P50:P69) -> 0.04979 | D79: =C79+AVERAGE(K49:K68) -> 0.080435
B80: 2012-2021 | C80: =AVERAGE(P60:P69) -> 0.05353 | D80: =C80+AVERAGE(K59:K68) -> 0.07504
B81: End of 2023 | C81: 0.0594 | D81: =C81+K70 -> 0.0982

Sheet MEDICION DE INGRESOS 
F2: Growth(%) | G2: Crecimiento (%)
B3: EMPRESA | E3: Fuente | F3: Revenue Growth Rate (5Y) | G3: Revenue Growth Rate (3Y)*
B4: M2CROWD, S.A. DE C.V.
B9: MONIFI, S.A. DE C.V. | E9: Promedio | F9: =AVERAGE(F4:F5) -> #DIV/0! | G9: =AVERAGE(G4:G5) -> #DIV/0!
A12: En miles | B12: =+B4 -> M2CROWD, S.A. DE C.V. | C12: 44195 | D12: 44560 | E12: 44651 | F12: Crecimiento por Año | J12: Promedio | K12: CAGR
B13: Ingresos Totales | C13: 12648 | D13: 17059 | E13: 4586 | H13: =+D13/C13-1 -> 0.34875079 | I13: =+E13/D13-1 -> -0.7311683 | J13: =AVERAGE(F13:I13) -> -0.19120875 | K13: =+(E11/C13)^(1/2)-1 -> -1
B14: Utilidad Operativa | C14: 12963 | D14: 17198 | E14: -279 | H14: =+D14/C14-1 -> 0.32669907 | I14: =+E14/D14-1 -> -1.0162228 | J14: =AVERAGE(F14:G14,I14) -> -1.0162228 | K14: =+(E14/#REF!)^(1/3)-1 -> #REF!
B16: =+B5 -> 0 | C16: 43464 | D16: 43829 | E16: 44195 | F16: Crecimiento por Año | J16: Promedio | K16: CAGR
B17: Ingresos Totales | C17: 9352 | D17: 9041.4 | E17: 9149.7 | H17: =+D17/C17-1 -> -0.033212147 | I17: =+E17/D17-1 -> 0.011978233 | J17: =AVERAGE(F17:H17) -> -0.033212147 | K17: =+(E17/#REF!)^(1/3)-1 -> #REF!
B18: Utilidad Operativa | C18: 489 | D18: 348.1 | E18: 599.7 | H18: =+D18/C18-1 -> -0.28813906 | I18: =+E18/D18-1 -> 0.72278081 | J18: =AVERAGE(F18:H18) -> -0.28813906 | K18: =+(E18/#REF!)^(1/3)-1 -> #REF!
B20: =+B6 -> 0 | C20: 29/092019 | D20: 29/092020 | E20: 29/092021 | F20: Crecimiento por Año | J20: Promedio | K20: CAGR
B21: Ingresos Totales | C21: 122.25 | D21: 92.51 | E21: 108.56 | H21: =+D21/C21-1 -> -0.24327198 | I21: =+E21/D21-1 -> 0.17349476 | J21: =AVERAGE(G21,I21) -> 0.17349476 | K21: =+(E21/#REF!)^(1/3)-1 -> #REF!
B22: Utilidad Operativa | C22: 45.06 | D22: 6.83 | E22: 14.44 | H22: =+D22/C22-1 -> -0.84842432 | I22: =+E22/D22-1 -> 1.114202 | J22: =AVERAGE(G22,I22) -> 1.114202 | K22: =+(E22/#REF!)^(1/3)-1 -> #REF!
B24: =+B7 -> 0 | C24: 43464 | D24: 43829 | E24: 44195 | F24: Crecimiento por Año | J24: Promedio | K24: CAGR
B25: Ingresos Totales | C25: 45.74 | D25: 41.14 | E25: 41.4 | H25: =+D25/C25-1 -> -0.10056843 | I25: =+E25/D25-1 -> 0.0063198833 | J25: =AVERAGE(G25,I25,F25) -> 0.0063198833 | K25: =+(E25/#REF!)^(1/3)-1 -> #REF!
B26: Utilidad Operativa | C26: 843 | D26: -1027 | E26: 1427 | H26: =+D26/C26-1 -> -2.2182681 | I26: =+E26/D26-1 -> -2.3894839 | J26: =AVERAGE(G26) -> #DIV/0! | K26: =+(E26/#REF!)^(1/3)-1 -> #REF!
B28: =+B8 -> 0 | C28: 43464 | D28: 43829 | E28: 44195 | F28: Crecimiento por Año | J28: Promedio | K28: CAGR
B29: Ingresos Totales | C29: 6289 | D29: 6209 | E29: 5987 | H29: =+D29/C29-1 -> -0.012720623 | I29: =+E29/D29-1 -> -0.03575455 | J29: =AVERAGE(G29,F29) -> #DIV/0! | K29: =+(E29/#REF!)^(1/3)-1 -> #REF!
B30: Utilidad Operativa | C30: 703 | D30: 664 | E30: 577 | H30: =+D30/C30-1 -> -0.055476529 | I30: =+E30/D30-1 -> -0.1310241 | J30: =AVERAGE(G30) -> #DIV/0! | K30: =+(E30/#REF!)^(1/3)-1 -> #REF!
B32: **Últimos 3 años. | G32: Crecimiento Promedio | J32: =AVERAGE(J13,J17) -> -0.11221045 | K32: =AVERAGE(K13,K17) -> #REF!
G33: Crecimiento Promedio | J33: =AVERAGE(J14,J18) -> -0.65218094 | K33: =AVERAGE(K14,K18) -> #REF!
A38: En miles | B38: =+B12 -> M2CROWD, S.A. DE C.V. | C38: 43464 | D38: 43829 | E38: 44195 | F38: Crecimiento por Año | J38: Promedio | K38: CAGR
B39: Total Revenue | F39: =+#REF!/#REF!-1 -> #REF! | G39: =+C39/#REF!-1 -> #REF! | H39: =+D39/C39-1 -> #DIV/0! | J39: =AVERAGE(F39:I39) -> #REF! | K39: =+(D39/#REF!)^(1/3)-1 -> #REF!
B40: Operating Income | F40: =+#REF!/#REF!-1 -> #REF! | G40: =+C40/#REF!-1 -> #REF! | H40: =+D40/C40-1 -> #DIV/0! | J40: =AVERAGE(F40:H40) -> #REF! | K40: =+(D40/#REF!)^(1/3)-1 -> #REF!
C43: 43464 | D43: 43829 | E43: 44195 | F43: Crecimiento por Año | J43: Promedio | K43: CAGR
B44: Total Revenue | F44: =+#REF!/#REF!-1 -> #REF! | G44: =+C44/#REF!-1 -> #REF! | H44: =+D44/C44-1 -> #DIV/0! | J44: =AVERAGE(F44:I44) -> #REF! | K44: =+(D44/#REF!)^(1/3)-1 -> #REF!
B45: Operating Income | F45: =+#REF!/#REF!-1 -> #REF! | G45: =+C45/#REF!-1 -> #REF! | H45: =+D45/C45-1 -> #DIV/0! | J45: =AVERAGE(F45:H45) -> #REF! | K45: =+(D45/#REF!)^(1/3)-1 -> #REF!
B47: **Últimos 3 años. | G47: Crecimiento Promedio | J47: =AVERAGE(J39,J44) -> #REF! | K47: =AVERAGE(K39,K44) -> #REF!
G48: Crecimiento Promedio | J48: =AVERAGE(J40,J44) -> #REF! | K48: =AVERAGE(K40,K44) -> #REF!
B51: Análisis Vertical
A54: En miles | B54: =+B12 -> M2CROWD, S.A. DE C.V. | C54: 43465 | D54: 43830 | E54: 44196 | F54: Media
B55: Total Revenue | C55: =+C13/C13 -> 1 | D55: =+D13/D13 -> 1 | E55: =+E13/E13 -> 1 | F55: =AVERAGE(C55:E55) -> 1
B56: Operating Income | C56: =+C14/C13 -> 1.0249051 | D56: =+D14/D13 -> 1.0081482 | E56: =+E14/E13 -> -0.060837331 | F56: =AVERAGE(C56:D56) -> 1.0165267
A59: En miles | B59: =+B16 -> 0 | C59: 43465 | D59: 43830 | E59: 44196 | F59: Promedio*
B60: Total Revenue | C60: =+C17/C17 -> 1 | D60: =+D17/D17 -> 1 | E60: =+E17/E17 -> 1 | F60: 1
B61: Operating Income | C61: =+C18/C17 -> 0.052288281 | D61: =+D18/D17 -> 0.038500675 | E61: =+E18/E17 -> 0.065543133 | F61: =AVERAGE(C61:D61) -> 0.045394478
D63: Promedio Sector | F63: =+AVERAGE(F56,F61) -> 0.53096057

Sheet EXPECTED GROWTH
A1: Date updated: | B1: 44566
A2: Created by: | B2: Aswath Damodaran, adamodar@stern.nyu.edu
A3: What is this data? | B3: Historical (compounded annual) growth rate in net income and revenues - last 5 years | F3: US companies
A4: Home Page: | B4: http://www.damodaran.com
A5: Data website: | B5: https://www.stern.nyu.edu/~adamodar/New_Home_Page/data.html
A6: Companies in each industry: | B6: https://www.stern.nyu.edu/~adamodar/pc/datasets/indname.xls
A7: Variable definitions: | B7: https://www.stern.nyu.edu/~adamodar/New_Home_Page/datafile/variable.htm
A8: Industry Name | B8: Number of Firms | C8: CAGR in Net Income- Last 5 years | D8: CAGR in Revenues- Last 5 years | E8: Expected Growth in Revenues - Next 2 years | F8: Expected Growth in EPS - Next 5 years
A9: Advertising | B9: 49 | C9: 0.10708 | D9: 0.071315789 | E9: 0.23349333 | F9: 0.1782
A10: Aerospace/Defense | B10: 73 | C10: 0.054805 | D10: 0.049397561 | E10: 0.26846243 | F10: 0.10253182
A11: Air Transport | B11: 21 | C11: -0.32732 | D11: -0.069958333 | E11: 0.52592857 | F11: 0.456
A12: Apparel | B12: 39 | C12: 0.038212 | D12: 0.061162 | E12: 0.1609412 | F12: 0.26835714
A13: Auto & Truck | B13: 26 | C13: 0.08502 | D13: 0.11937143 | E13: 1.6060091 | F13: 0.046714286
A14: Auto Parts | B14: 38 | C14: 0.0553 | D14: 0.061078077 | E14: 0.184628 | F14: 0.45484615
A15: Bank (Money Center) | B15: 7 | C15: 0.1172 | D15: 0.046133333 | E15: 0.014662 | F15: 0.1392
A16: Banks (Regional) | B16: 563 | C16: 0.20695044 | D16: 0.11739005 | E16: 0.072557184 | F16: 0.13103333
A17: Beverage (Alcoholic) | B17: 21 | C17: 0.0067833333 | D17: 0.1456875 | E17: 0.13018571 | F17: 0.08112
A18: Beverage (Soft) | B18: 32 | C18: 0.17906 | D18: 0.20472333 | E18: 0.22314 | F18: 0.11396
A19: Broadcasting | B19: 28 | C19: 0.20314615 | D19: 0.096442632 | E19: 0.14556471 | F19: 1.64516
A20: Brokerage & Investment Banking | B20: 31 | C20: 0.41505882 | D20: 0.17959545 | E20: 0.10717778 | F20: 0.24031667
... A26: Chemical (Specialty) | B26: 81 | C26: 0.09224303 | D26: 0.079344706 | E26: 0.18326667 | F26: 0.13242222
A27: Coal & Related Energy | B27: 18 | C27: 0.0814 | D27: -0.21844286 | E27: 2.1920875 | F27: #DIV/0!
A28: Computer Services | B28: 83 | C28: 0.17630435 | D28: 0.088714524 | E28: 0.11320741 | F28: 0.16145
A29: Computers/Peripherals | B29: 46 | C29: 0.10832727 | D29: 0.16677923 | E29: 0.13780208 | F29: 0.13685
A30: Construction Supplies | B30: 48 | C30: 0.12912692 | D30: 0.062764118 | E30: 1.4628625 | F30: 0.2965
A31: Diversified | B31: 22 | C31: 0.12114 | D31: 0.00279 | E31: 0.41067111 | F31: 0.08394
A32: Drugs (Biotechnology) | B32: 581 | C32: 0.056963636 | D32: 0.30857305 | E32: 1.1472552 | F32: 0.11173625
A33: Drugs (Pharmaceutical) | B33: 298 | C33: 0.20709 | D33: 0.42848129 | E33: 1.4980149 | F33: 0.102465
A34: Education | B34: 35 | C34: 0.089255556 | D34: 0.0081042105 | E34: 0.11535625 | F34: 0.13358333
A35: Electrical Equipment | B35: 104 | C35: 0.11717143 | D35: 0.0583578 | E35: 1.0337043 | F35: 0.14940909
A36: Electronics (Consumer & Office) | B36: 16 | C36: 0.0875 | D36: 0.014991 | E36: 0.17207167 | F36: -0.046333333
A37: Electronics (General) | B37: 137 | C37: 0.2004775 | D37: 0.084135341 | E37: 0.50183603 | F37: 0.19629394
A38: Engineering/Construction | B38: 48 | C38: 0.28063125 | D38: 0.08828037 | E38: 0.23355 | F38: 0.18661111
A39: Entertainment | B39: 108 | C39: 0.21746364 | D39: 0.22613333 | E39: 0.4644303 | F39: 0.22378571
... A72: Real Estate (Development) | B72: 19 | C72: -0.655 | D72: -0.08428 | E72: 11.403667 | F72: 0.49
A73: Real Estate (General/Diversified) | B73: 10 | C73: 0.11799 | D73: 0.091 | E73: 0.038 | F73: #DIV/0!
A74: Real Estate (Operations & Services) | B74: 51 | C74: 0.21146364 | D74: 0.054861905 | E74: 0.39866667 | F74: 0.086485
A75: Recreation | B75: 60 | C75: 0.2065065 | D75: 0.075996897 | E75: 0.29148387 | F75: 0.39638462
A76: Reinsurance | B76: 2 | C76: 0.0099 | D76: 0.10415 | E76: 0.0514 | F76: #DIV/0!
A77: Restaurant/Dining | B77: 70 | C77: 0.091803333 | D77: 0.047096279 | E77: 0.29501842 | F77: 0.26540909
A78: Retail (Automotive) | B78: 32 | C78: 0.30653125 | D78: 0.14697059 | E78: 0.39252174 | F78: 0.15500308
A79: Retail (Building Supply) | B79: 16 | C79: 0.34346667 | D79: 0.17428083 | E79: 0.16928462 | F79: 0.15030909
A80: Retail (Distributors) | B80: 68 | C80: 0.18828258 | D80: 0.040963404 | E80: 0.16369946 | F80: 0.214316
A81: Retail (General) | B81: 16 | C81: 0.062633333 | D81: 0.038878462 | E81: 0.11353071 | F81: 0.091825
A82: Retail (Grocery and Food) | B82: 15 | C82: 0.097052857 | D82: 0.0324125 | E82: 0.063123333 | F82: 0.0472
A83: Retail (Online) | B83: 60 | C83: 0.37440125 | D83: 0.102 | E83: 0.19027655 | F83: 0.44518824
A84: Retail (Special Lines) | B84: 76 | C84: 0.17452368 | D84: 0.11783 | E84: 0.14979811 | F84: 0.25721154
A85: Rubber& Tires | B85: 2 | C85: -0.0324 | D85: 0.042015 | E85: 0.282 | F85: #DIV/0!
A86: Semiconductor | B86: 67 | C86: 0.33606667 | D86: 0.066251667 | E86: 0.22250239 | F86: 0.30140256
A87: Semiconductor Equip | B87: 34 | C87: 0.43112941 | D87: 0.13994241 | E87: 0.32622308 | F87: 0.17772222
A88: Shipbuilding & Marine | B88: 8 | C88: 0.674 | D88: 0.16393333 | E88: 0.2688 | F88: 0.12
A89: Shoe | B89: 12 | C89: 0.1143 | D89: 0.0638 | E89: 0.27505 | F89: 0.27433333
A90: Software (Entertainment) | B90: 88 | C90: 0.16216667 | D90: 0.22905963 | E90: 0.34664194 | F90: 0.2516
A91: Software (Internet) | B91: 36 | C91: 0.10545 | D91: 0.2206 | E91: 0.25845 | F91: 0.26677778
A92: Software (System & Application) | B92: 375 | C92: 0.23036047 | D92: 0.1772226 | E92: 0.41693244 | F92: 0.2214713
A93: Steel | B93: 28 | C93: 0.59322222 | D93: 0.19973333 | E93: 0.26601444 | F93: 0.14135
A94: Telecom (Wireless) | B94: 17 | C94: 0.529 | D94: -0.015962857 | E94: 0.0807 | F94: 0.195
A95: Telecom. Equipment | B95: 82 | C95: 0.089025 | D95: 0.066588448 | E95: 0.23452564 | F95: 0.15948636
A96: Telecom. Services | B96: 42 | C96: 0.081314286 | D96: 0.1012185 | E96: 0.19053125 | F96: 0.1577
A97: Tobacco | B97: 16 | C97: 0.0948 | D97: 0.069115 | E97: 0.179022 | F97: 0.11956667
... A104: Total Market (without financials) | B104: 5619 | C104: 0.15739631 | D104: 0.11904171 | E104: 0.49943957 | F104: 0.2066041

Sheet Industry Averages_REINVESTMENT
A1: Date updated: | B1: 45662
A2: Created by: | B2: Aswath Damodaran, adamodar@stern.nyu.edu
A3: What is this data? | B3: Capital Expenditures, Acquisitions and R&D and Sales/Invested Capital Ratios ($ values in millions) | F3: US companies
A4: Home Page: | B4: http://www.damodaran.com
A5: Data website: | B5: https://pages.stern.nyu.edu/~adamodar/pc/datasets/capex.xls
A6: Companies in each industry: | B6: https://www.stern.nyu.edu/~adamodar/pc/datasets/indname.xls
A7: Variable definitions: | B7: https://www.stern.nyu.edu/~adamodar/New_Home_Page/datafile/variable.htm
A8: Industry Name | B8: Number of Firms | C8: Capital Expenditures (US $ millions) | D8: Depreciation & Amort ((US $ millions) | E8: Cap Ex/Deprecn | F8: Acquisitions (US $ millions) | G8: Net R&D (US $ millions) | H8: Net Cap Ex/Sales | I8: Net Cap Ex/ EBIT (1-t) | J8: Sales/ Invested Capital (LTM)
A9: Advertising | B9: 54 | C9: 772.539 | D9: 1550.407 | E9: 0.49828142 | F9: 1015.557 | G9: 63.1658 | H9: 0.0070344212 | I9: 0.085615255 | J9: 4.1947709
A10: Aerospace/Defense | B10: 67 | C10: 13791.951 | D10: 15847.194 | E10: 0.87030871 | F10: 4797.737 | G10: 1045.6442 | H10: 0.0076674729 | I10: 0.12535884 | J10: 2.6209632
A11: Air Transport | B11: 24 | C11: 20711.123 | D11: 11241.54 | E11: 1.8423742 | F11: 716.23 | G11: 95.1868 | H11: 0.043650452 | I11: 1.0798135 | J11: 1.7451652
A12: Apparel | B12: 37 | C12: 1357.223 | D12: 1375.306 | E12: 0.98685165 | F12: 101.46 | G12: 5.8262 | H12: 0.001315238 | I12: 0.01579305 | J12: 1.7344818
A13: Auto & Truck | B13: 34 | C13: 33094.771 | D13: 19037.585 | E13: 1.7383912 | F13: 12.736 | G13: 498.73 | H13: 0.029960463 | I13: 1.0392553 | J13: 1.1507771
A14: Auto Parts | B14: 33 | C14: 3094.592 | D14: 1927.112 | E14: 1.6058184 | F14: 1380.83 | G14: 187.546 | H14: 0.029796679 | I14: 0.77885973 | J14: 2.4258769
A15: Bank (Money Center) | B15: 15 | C15: 8763 | D15: 0 | E15: NA | F15: 2795 | G15: 0 | H15: NA | I15: NA | J15: NA
A16: Banks (Regional) | B16: 591 | C16: 4418.36 | D16: 3.192 | E16: NA | F16: -3238.208 | G16: 0 | H16: NA | I16: NA | J16: NA
A17: Beverage (Alcoholic) | B17: 18 | C17: 2494.615 | D17: 862.778 | E17: 2.8913753 | F17: 158.048 | G17: 0 | H17: 0.062082137 | I17: 0.33305509 | J17: 0.85107422
A18: Beverage (Soft) | B18: 29 | C18: 9387.689 | D18: 4781.047 | E18: 1.9635216 | F18: 354.641 | G18: 13.6908 | H18: 0.028297226 | I18: 0.17527804 | J18: 1.6739558
A19: Broadcasting | B19: 22 | C19: 1313.426 | D19: 3036.051 | E19: 0.43260999 | F19: 68.61 | G19: 0.04 | H19: -0.023811838 | I19: -0.22993199 | J19: 1.1351345
A20: Brokerage & Investment Banking | B20: 30 | C20: 7224.451 | D20: 5515.269 | E20: 1.3099 | F20: 130.325 | G20: 1.7868 | H20: NA | I20: NA | J20: NA
A21: Building Materials | B21: 39 | C21: 4233.206 | D21: 3908.09 | E21: 1.0831905 | F21: 17532.317 | G21: 203.71 | H21: 0.14426832 | I21: 1.4052551 | J21: 2.6563018
A22: Business & Consumer Services | B22: 152 | C22: 7372.071 | D22: 10641.827 | E22: 0.69274486 | F22: 2448.718 | G22: 514.6204 | H22: -0.0011791142 | I22: -0.01279088 | J22: 2.6612038
A23: Cable TV | B23: 9 | C23: 27407.7 | D23: 28042.8 | E23: 0.97735248 | F23: 195.08 | G23: -30.2 | H23: -0.0021867097 | I23: -0.015523762 | J23: 0.8503768
A24: Chemical (Basic) | B24: 31 | C24: 7331.534 | D24: 3183.074 | E24: 2.3032873 | F24: 425.6 | G24: -1.8416 | H24: 0.037466858 | I24: 0.72998533 | J24: 1.5856092
A25: Chemical (Diversified) | B25: 4 | C25: 692.6 | D25: 642.53 | E25: 1.0779263 | F25: 0 | G25: -12.1072 | H25: 0.0030959738 | I25: 0.069088538 | J25: 1.3096091
A26: Chemical (Specialty) | B26: 60 | C26: 18312.045 | D26: 11082.411 | E26: 1.6523521 | F26: 3674.072 | G26: -98.9202 | H26: 0.052027276 | I26: 0.53222546 | J26: 1.134432
A27: Coal & Related Energy | B27: 16 | C27: 780.232 | D27: 648.58 | E27: 1.202985 | F27: 198.3 | G27: -5.512 | H27: 0.04181844 | I27: 0.48888409 | J27: 1.2410015
A28: Computer Services | B28: 63 | C28: 3264.619 | D28: 8930.247 | E28: 0.36556872 | F28: 5659.789 | G28: 459.9186 | H28: 0.0013792624 | I28: 0.02615383 | J28: 4.7139988
A29: Computers/Peripherals | B29: 35 | C29: 16066.354 | D29: 16083.953 | E29: 0.9989058 | F29: 373.1 | G29: 1727.4876 | H29: 0.0033470275 | I29: 0.019107649 | J29: 3.3449301
A30: Construction Supplies | B30: 46 | C30: 10236.395 | D30: 6621.914 | E30: 1.5458363 | F30: 4525.919 | G30: 38.9836 | H30: 0.038508067 | I30: 0.32793451 | J30: 1.5644348
A31: Diversified | B31: 21 | C31: 22431.227 | D31: 16629.95 | E31: 1.3488451 | F31: 7895.25 | G31: 149.922 | H31: 0.030015662 | I31: 0.1127355 | J31: 0.79974779
A32: Drugs (Biotechnology) | B32: 535 | C32: 6752.635 | D32: 22231.12 | E32: 0.30374695 | F32: 53156.216 | G32: 12429.677 | H32: 0.24938462 | I32: NA | J32: 0.93339464
A33: Drugs (Pharmaceutical) | B33: 231 | C33: 19335.475 | D33: 31381.07 | E33: 0.61615092 | F33: 88331.285 | G33: 10070.161 | H33: 0.23936247 | I33: 1.1926276 | J33: 1.014858
A34: Education | B34: 29 | C34: 716.014 | D34: 592.018 | E34: 1.2094463 | F34: 50.771 | G34: 30.5332 | H34: 0.0089103062 | I34: 0.14958559 | J34: 1.8590089
A35: Electrical Equipment | B35: 101 | C35: 6352.889 | D35: 6062.74 | E35: 1.0478577 | F35: 12858.089 | G35: 324.4884 | H35: 0.10742964 | I35: 2.0029863 | J35: 2.0875372
A36: Electronics (Consumer & Office) | B36: 11 | C36: 67.93 | D36: 83.978 | E36: 0.80890233 | F36: 12.283 | G36: 10.935 | H36: 0.0021872119 | I36: NA | J36: 2.7373985
A37: Electronics (General) | B37: 122 | C37: 5079.179 | D37: 3681.837 | E37: 1.379523 | F37: 5713.151 | G37: 147.373 | H37: 0.047231928 | I37: 0.71249169 | J37: 2.1729518
A38: Engineering/Construction | B38: 42 | C38: 3481.224 | D38: 2394.298 | E38: 1.4539644 | F38: 4595.547 | G38: 3.5996 | H38: 0.038518529 | I38: 0.89494189 | J38: 3.8629621
A39: Entertainment | B39: 96 | C39: 9296.03 | D39: 20334.935 | E39: 0.45714579 | F39: 887.468 | G39: 305.4754 | H39: -0.039181988 | I39: -0.64089325 | J39: 1.4069695
A40: Environmental & Waste Services | B40: 50 | C40: 6405.776 | D40: 5131.793 | E40: 1.248253 | F40: 3432.752 | G40: 26.2354 | H40: 0.064171995 | I40: 0.55300582 | J40: 2.3193891
A41: Farming/Agriculture | B41: 35 | C41: 9068.492 | D41: 4583.507 | E41: 1.9785051 | F41: 3146.925 | G41: 98.1522 | H41: 0.033604203 | I41: 0.59396197 | J41: 1.5671727
A42: Financial Svcs. (Non-bank & Insurance) | B42: 166 | C42: 14831.9 | D42: 20839.396 | E42: 0.71172408 | F42: 15815.554 | G42: 160.2048 | H42: 0.01791866 | I42: 0.135409 | J42: 0.068100315
A43: Food Processing | B43: 77 | C43: 11356.068 | D43: 7071.588 | E43: 1.6058724 | F43: 8016.108 | G43: 103.118 | H43: 0.04355998 | I43: 0.47314614 | J43: 1.6975231
A44: Food Wholesalers | B44: 14 | C44: 2295.383 | D44: 931.465 | E44: 2.4642719 | F44: 1952.27 | G44: 0 | H44: 0.014365743 | I44: 0.71264329 | J44: 7.7773251
A45: Furn/Home Furnishings | B45: 28 | C45: 1646.009 | D45: 1247.163 | E45: 1.3198026 | F45: 179.616 | G45: 38.3302 | H45: 0.011233595 | I45: 0.19937722 | J45: 1.9591798
A46: Green & Renewable Energy | B46: 18 | C46: 4105.661 | D46: 2471.118 | E46: 1.6614589 | F46: 1533.5 | G46: -3.0624 | H46: 0.38159403 | I46: 1.9440927 | J46: 0.18825826
A47: Healthcare Products | B47: 218 | C47: 11793.031 | D47: 13416.057 | E47: 0.87902362 | F47: 12476.258 | G47: 394.0412 | H47: 0.045760403 | I47: 0.36555755 | J47: 1.3345093
A48: Healthcare Support Services | B48: 113 | C48: 15514.422 | D48: 19226.241 | E48: 0.80693995 | F48: 21975.908 | G48: -58.718 | H48: 0.0074326016 | I48: 0.28207645 | J48: 14.649504
... A57: Insurance (Prop/Cas.) | B57: 53 | C57: 2862.994 | D57: 2069.26 | E57: 1.3835835 | F57: 1512.878 | G57: 0 | H57: 0.0061452887 | I57: 0.05640691 | J57: 1.911339
A58: Investments & Asset Management | B58: 231 | C58: 4225.052 | D58: -3154.897 | E58: NA | F58: 1954.753 | G58: 73.6418 | H58: 0.054996962 | I58: 0.4851594 | J58: 0.516545
A59: Machinery | B59: 109 | C59: 4557.609 | D59: 6724.897 | E59: 0.67772176 | F59: 11765.928 | G59: 14.317 | H59: 0.050323075 | I59: 0.40169675 | J59: 1.9682598
A60: Metals & Mining | B60: 64 | C60: 7550.792 | D60: 4262.591 | E60: 1.771409 | F60: 0.415 | G60: 14.7926 | H60: 0.058526634 | I60: 0.40970096 | J60: 1.2286157
A61: Office Equipment & Services | B61: 14 | C61: 393.492 | D61: 443.815 | E61: 0.88661267 | F61: 7.215 | G61: 2.7342 | H61: -0.0022258744 | I61: -0.031661503 | J61: 2.3287715
A62: Oil/Gas (Integrated) | B62: 4 | C62: 47186 | D62: 44901.7 | E62: 1.0508734 | F62: 8539 | G62: 42.8 | H62: 0.019303911 | I62: 0.20177234 | J62: 1.2679675
A63: Oil/Gas (Production and Exploration) | B63: 147 | C63: 80372.35 | D63: 51152.229 | E63: 1.5712385 | F63: 10021.284 | G63: 11.5914 | H63: 0.17944803 | I63: 0.77620131 | J63: 0.66742412
A64: Oil/Gas Distribution | B64: 24 | C64: 21546.394 | D64: 10321.894 | E64: 2.0874458 | F64: 3295.438 | G64: 5.158 | H64: 0.15403105 | I64: 0.67211109 | J64: 0.48899531
A65: Oilfield Svcs/Equip. | B65: 97 | C65: 17223.395 | D65: 19807.636 | E65: 0.86953309 | F65: 3935.246 | G65: 109.1406 | H65: 0.002021968 | I65: 0.04904839 | J65: 3.1319386
A66: Packaging & Container | B66: 22 | C66: 6944.648 | D66: 6128.702 | E66: 1.1331352 | F66: 1192.5 | G66: -8.764 | H66: 0.016203867 | I66: 0.20012049 | J66: 1.7435135
A67: Paper/Forest Products | B67: 6 | C67: 589.8 | D67: 429.1 | E67: 1.3745048 | F67: 708.2 | G67: 2.4 | H67: 0.078687607 | I67: 1.0572281 | J67: 2.4742493
A68: Power | B68: 48 | C68: 137875.02 | D68: 53393.494 | E68: 2.5822438 | F68: 4583.8 | G68: 0.1684 | H68: 0.23573285 | I68: 1.3594791 | J68: 0.38012046
A69: Precious Metals | B69: 60 | C69: 5370.504 | D69: 3916.202 | E69: 1.3713552 | F69: -658.228 | G69: 9.036 | H69: 0.030208703 | I69: 0.18954375 | J69: 0.709283
A70: Publishing & Newspapers | B70: 19 | C70: 908.438 | D70: 1460.525 | E70: 0.62199415 | F70: 372.69 | G70: 13.2546 | H70: -0.0063874491 | I70: -0.10653206 | J70: 2.2554076
... A104: Total Market (without financials) | B104: 4935 | C104: 1234984.6 | D104: 941457.81 | E104: 1.311779 | F104: 537504.95 | G104: 52288.334 | H104: 0.043473903 | I104: 0.4582834 | J104: 1.5606598

Sheet Dupont
B1: Dupont = (Margen de Utilidad X Rotación de Activo Total X Palanca Financiera)
B3: •(1) El primer componente de la ecuación nos dice que % de ganancias obtenemos sobre las ventas netas.
B4: •(2) El segundo indica, los recursos mínimos requeridos ($)para soportar las ventas netas.
B5: •( 3) El tercer componente indica, el importe de capital accionario invertido($) para financiar los recursos mínimos requeridos.
B7: • Si en la ecuación Dupont, simplificamos las Ventas Netas, los dos primeros términos nos dan el ROA, y si posteriormente simplificamos el Activo Total, obtenemos el ROE.
B9: Pesos Corrientes
B10: Concepto | C10: 2015 | D10: 2016 | E10: 2017 | F10: 2018 | G10: 2019 | H10: 2020 | I10: 2021
B11: Ventas Netas | D11: =+'1. Datos'!D6 -> 0 | E11: =+'1. Datos'!#REF! -> #REF! | F11: =+'1. Datos'!#REF! -> #REF! | G11: =+'1. Datos'!E8 -> 0 | H11: =+'1. Datos'!F8 -> 0 | I11: =+'1. Datos'!G8 -> 0
B12: Utilidad Neta | D12: =+'1. Datos'!D30 -> 0 | E12: =+'1. Datos'!#REF! -> #REF! | F12: =+'1. Datos'!#REF! -> #REF! | G12: =+'1. Datos'!E30 -> 0 | H12: =+'1. Datos'!F30 -> 0 | I12: =+'1. Datos'!G30 -> 0
B13: Activo Total | D13: =+'1. Datos'!D95 -> 0 | E13: =+'1. Datos'!#REF! -> #REF! | F13: =+'1. Datos'!#REF! -> #REF! | G13: =+'1. Datos'!E95 -> 0 | H13: =+'1. Datos'!F95 -> 0 | I13: =+'1. Datos'!G95 -> 0
B14: Pasivo Total | D14: =+'1. Datos'!D123 -> 0 | E14: =+'1. Datos'!#REF! -> #REF! | F14: =+'1. Datos'!#REF! -> #REF! | G14: =+'1. Datos'!E123 -> 0 | H14: =+'1. Datos'!F123 -> 0 | I14: =+'1. Datos'!G123 -> 0
B15: Capital Contable | D15: =+'1. Datos'!D135 -> 0 | E15: =+'1. Datos'!#REF! -> #REF! | F15: =+'1. Datos'!#REF! -> #REF! | G15: =+'1. Datos'!E135 -> 0 | H15: =+'1. Datos'!F135 -> 0 | I15: =+'1. Datos'!G135 -> 0
B16: ROE | D16: =+D12/D15 -> #DIV/0! | E16: =+E12/E15 -> #REF! | F16: =+F12/F15 -> #REF! | G16: =+G12/G15 -> #DIV/0! | H16: =+H12/H15 -> #DIV/0! | I16: =+I12/I15 -> #DIV/0! | J16: Rentabilidad Patrimonial
A17: ROA | B17: ROA (Rentabilidad de Activos) | D17: =+D12/D13 -> #DIV/0! | E17: =+E12/E13 -> #REF! | F17: =+F12/F13 -> #REF! | G17: =+G12/G13 -> #DIV/0! | H17: =+H12/H13 -> #DIV/0! | I17: =+I12/I13 -> #DIV/0! | J17: Palanqueo Operativo
A18: AF | B18: Apalancamiento Financiero | D18: =+D13/D15 -> #DIV/0! | E18: =+E13/E15 -> #REF! | F18: =+F13/F15 -> #REF! | G18: =+G13/G15 -> #DIV/0! | H18: =+H13/H15 -> #DIV/0! | I18: =+I13/I15 -> #DIV/0! | J18: Palanqueo Financiero
A21: ROA | B21: Margen Neto | D21: =+D12/D11 -> #DIV/0! | E21: =+E12/E11 -> #REF! | F21: =+F12/F11 -> #REF! | G21: =+G12/G11 -> #DIV/0! | H21: =+H12/H11 -> #DIV/0! | I21: =+I12/I11 -> #DIV/0!
B22: Rotación de Activo Total | D22: =+D11/D13 -> #DIV/0! | E22: =+E11/E13 -> #REF! | F22: =+F11/F13 -> #REF! | G22: =+G11/G13 -> #DIV/0! | H22: =+H11/H13 -> #DIV/0! | I22: =+I11/I13 -> #DIV/0!
A23: AF | B23: Apalancamiento Financiero | D23: =+D13/D15 -> #DIV/0! | E23: =+E13/E15 -> #REF! | F23: =+F13/F15 -> #REF! | G23: =+G13/G15 -> #DIV/0! | H23: =+H13/H15 -> #DIV/0! | I23: =+I13/I15 -> #DIV/0!
B24: ROE [ROA*Apalanca. Fin] | D24: =+D21*D22*D23 -> #DIV/0! | E24: =+E21*E22*E23 -> #REF! | F24: =+F21*F22*F23 -> #REF! | G24: =+G21*G22*G23 -> #DIV/0! | H24: =+H21*H22*H23 -> #DIV/0! | I24: =+I21*I22*I23 -> #DIV/0!
B25: Prueba | D25: =+D16-D24 -> #DIV/0! | E25: =+E16-E24 -> #REF! | F25: =+F16-F24 -> #REF! | G25: =+G16-G24 -> #DIV/0! | H25: =+H16-H24 -> #DIV/0! | I25: =+I16-I24 -> #DIV/0!
B28: ANALISIS
B30: =B21 -> Margen Neto | C30: =C21 -> 0 | D30: =D21 -> #DIV/0! | E30: =E21 -> #REF! | G30: =G21 -> #DIV/0! | H30: =H21 -> #DIV/0! | I30: =I21 -> #DIV/0! | J30: =+AVERAGE(G30:I30) -> #DIV/0!
B31: El margen Neto en el ejercicio 2016 muestra un descenso considerable en comparativa con los demás ejercicios; el margen oscila en 19.64% en promedio considerando los últimos 5 años. La empresa actualmente genera beneficios económicos, sobre la actividad que desempeña.
J33: ok
B35: =B22 -> Rotación de Activo Total | C35: =C22 -> 0 | D35: =D22 -> #DIV/0! | E35: =E22 -> #REF! | F35: =F22 -> #REF! | G35: =G22 -> #DIV/0! | H35: =H22 -> #DIV/0! | I35: =I22 -> #DIV/0! | J35: =+AVERAGE(D35:I35) -> #DIV/0!
B36: La empresa ha mostrado un rendimiento negativo respeto con el activo. La rotación de activo total promedio es de -10.45%. Esta relación se ha mantenido negativo durante los en los últimos 5 años, obteniendo el mayor rendiemiento de 46.17% en el año 2017.
J37: ok
B39: Apalancamiento Financiero | C39: =C23 -> 0 | D39: =D23 -> #DIV/0! | E39: =E23 -> #REF! | F39: =F23 -> #REF! | G39: =G23 -> #DIV/0! | H39: =H23 -> #DIV/0! | I39: =I23 -> #DIV/0! | J39: =+AVERAGE(D39:I39) -> #DIV/0!
B40: Se puede observar que el rendimiento más importante viene del apalancamiento financiero. Durante los últimos 6 años la empresa ha manifestado resultados negativos.
J42: ok
A44: =A17 -> ROA | B44: =B17 -> ROA (Rentabilidad de Activos) | C44: =C17 -> 0 | D44: =D17 -> #DIV/0! | E44: =E17 -> #REF! | F44: =F17 -> #REF! | G44: =G17 -> #DIV/0! | H44: =H17 -> #DIV/0! | I44: =I17 -> #DIV/0! | J44: =+AVERAGE(D44:I44) -> #DIV/0!
B45: Esta razón indica la rentabilidad de la empresa en relación con sus activos. Demuestra la efectividad con la que los activos son utilizados para poder generar los ingresos de la compañía. Durante los ultimos 6 años, la empresa no cuentan con rentabilidad suficiente para ser frende su actividad.
J46: ok
B48: =B16 -> ROE | C48: =C16 -> 0 | D48: =D16 -> #DIV/0! | E48: =E16 -> #REF! | F48: =F16 -> #REF! | G48: =G16 -> #DIV/0! | H48: =H16 -> #DIV/0! | I48: =I16 -> #DIV/0! | J48: =+AVERAGE(D48:I48) -> #DIV/0!
B49: Indica la efectividad con la que la administración está utilizando las aportaciones realizadas por los accionistas para la generación de ingresos en la compañía. Indica a los accionistas la eficiencia del dinero invertido. Se muestra que para el año 2016 se tuvieron rendimientos por arriba del 100% del capital. Para el año 2018, 2019 y 2020 se manifiesta un rendimiento sobre el capital, excediendo el 50%. En promedio se ha tenido un rendimiento de 103.69%.
J51: ok
B56: http://web.uqroo.mx/archivos/jlesparza/acpef140/Razones%20fins.pdf

Sheet ERPs 2021
A1: Country and Equity Risk Premiums
A2: Date of update: | B2: 42735
A3: Enter the current risk premium for a mature equity market | E3: 0.0472 | F3: Updated January 1, 2021
A4: Do you want to adjust the country default spread for the additional volatility of the equity market to get to a country premium? | E4: Yes
A5: If yes, enter the multiplier to use on the default spread (See worksheet for volatility numbers for selected emerging markets) | E5: 1.0959233 | F5: Updated January 1, 2021
A7: Country | B7: Africa | C7: Moody's rating | D7: Rating-based Default Spread | E7: Total Equity Risk Premium | F7: Country Risk Premium | G7: Sovereign CDS, net of US | H7: Total Equity Risk Premium2 | I7: Country Risk Premium3 | J7: Has to be sorted in ascending order
A8: Abu Dhabi | B8: Middle East | C8: Aa2 | D8: =VLOOKUP(C8,$J$9:$K$31,2,FALSE)/10000 -> 0.0043848898 | E8: =$E$3+F8 -> 0.052005503 | F8: =IF($E$4="Yes",D8*$E$5,D8) -> 0.0048055029 | G8: 0.0046 | H8: =IF(I8="NA","NA",$E$3+I8) -> 0.052241247 | I8: =IF(G8="NA","NA",G8*$E$5) -> 0.0050412471 | J8: Rating | K8: Default spread in basis points
A9: Albania | B9: Eastern Europe & Russia | C9: B1 | D9: =VLOOKUP(C9,$J$9:$K$31,2,FALSE)/10000 -> 0.039782909 | E9: =$E$3+F9 -> 0.090799017 | F9: =IF($E$4="Yes",D9*$E$5,D9) -> 0.043599017 | G9: NA | H9: =IF(I9="NA","NA",$E$3+I9) -> NA | I9: =IF(G9="NA","NA",G9*$E$5) -> NA | J9: A1 | K9: =C189 -> 62.18571
A10: Andorra (Principality of) | B10: Western Europe | C10: Caa1 | D10: =VLOOKUP(C10,$J$9:$K$31,2,FALSE)/10000 -> 0.066251699 | E10: =$E$3+F10 -> 0.11980678 | F10: =IF($E$4="Yes",D10*$E$5,D10) -> 0.07260678 | G10: NA | H10: =IF(I10="NA","NA",$E$3+I10) -> NA | I10: =IF(G10="NA","NA",G10*$E$5) -> NA | J10: A2 | K10: =C190 -> 74.941753
A11: Angola | B11: Africa | C11: Caa1 | D11: =VLOOKUP(C11,$J$9:$K$31,2,FALSE)/10000 -> 0.066251699 | E11: =$E$3+F11 -> 0.11980678 | F11: =IF($E$4="Yes",D11*$E$5,D11) -> 0.07260678 | G11: 0.0727 | H11: =IF(I11="NA","NA",$E$3+I11) -> 0.12687362 | I11: =IF(G11="NA","NA",G11*$E$5) -> 0.079673623 | J11: A3 | K11: =C191 -> 106.03461
A12: Argentina | B12: Central and South America | C12: Ca | D12: =VLOOKUP(C12,$J$9:$K$31,2,FALSE)/10000 -> 0.10603461 | E12: =$E$3+F12 -> 0.1634058 | F12: =IF($E$4="Yes",D12*$E$5,D12) -> 0.1162058 | G12: NA | H12: =IF(I12="NA","NA",$E$3+I12) -> NA | I12: =IF(G12="NA","NA",G12*$E$5) -> NA | J12: Aa1 | K12: =C192 -> 35.079119
A13: Armenia | B13: Eastern Europe & Russia | C13: Ba3 | D13: =VLOOKUP(C13,$J$9:$K$31,2,FALSE)/10000 -> 0.031810382 | E13: =$E$3+F13 -> 0.082061739 | F13: =IF($E$4="Yes",D13*$E$5,D13) -> 0.034861739 | G13: NA | H13: =IF(I13="NA","NA",$E$3+I13) -> NA | I13: =IF(G13="NA","NA",G13*$E$5) -> NA | J13: Aa2 | K13: =C193 -> 43.848898
A14: Aruba | B14: Caribbean | C14: Baa1 | D14: =VLOOKUP(C14,$J$9:$K$31,2,FALSE)/10000 -> 0.014111373 | E14: =$E$3+F14 -> 0.062664982 | F14: =IF($E$4="Yes",D14*$E$5,D14) -> 0.015464982 | G14: NA | H14: =IF(I14="NA","NA",$E$3+I14) -> NA | I14: =IF(G14="NA","NA",G14*$E$5) -> NA | J14: Aa3 | K14: =C194 -> 53.41593
A15: Australia | B15: Australia & New Zealand | C15: Aaa | D15: =VLOOKUP(C15,$J$9:$K$31,2,FALSE)/10000 -> 0 | E15: =$E$3+F15 -> 0.0472 | F15: =IF($E$4="Yes",D15*$E$5,D15) -> 0 | G15: 0 | H15: =IF(I15="NA","NA",$E$3+I15) -> 0.0472 | I15: =IF(G15="NA","NA",G15*$E$5) -> 0 | J15: Aaa | K15: =C195 -> 0
A16: Austria | B16: Western Europe | C16: Aa1 | D16: =VLOOKUP(C16,$J$9:$K$31,2,FALSE)/10000 -> 0.0035079119 | E16: =$E$3+F16 -> 0.051044402 | F16: =IF($E$4="Yes",D16*$E$5,D16) -> 0.0038444023 | G16: 0 | H16: =IF(I16="NA","NA",$E$3+I16) -> 0.0472 | I16: =IF(G16="NA","NA",G16*$E$5) -> 0 | J16: B1 | K16: =C196 -> 397.82909
A17: Azerbaijan | B17: Eastern Europe & Russia | C17: Ba2 | D17: =VLOOKUP(C17,$J$9:$K$31,2,FALSE)/10000 -> 0.026548515 | E17: =$E$3+F17 -> 0.076295136 | F17: =IF($E$4="Yes",D17*$E$5,D17) -> 0.029095136 | G17: NA | H17: =IF(I17="NA","NA",$E$3+I17) -> NA | I17: =IF(G17="NA","NA",G17*$E$5) -> NA | J17: B2 | K17: =C197 -> 486.32414
A18: Bahamas | B18: Caribbean | C18: Ba2 | D18: =VLOOKUP(C18,$J$9:$K$31,2,FALSE)/10000 -> 0.026548515 | E18: =$E$3+F18 -> 0.076295136 | F18: =IF($E$4="Yes",D18*$E$5,D18) -> 0.029095136 | G18: NA | H18: =IF(I18="NA","NA",$E$3+I18) -> NA | I18: =IF(G18="NA","NA",G18*$E$5) -> NA | J18: B3 | K18: =C198 -> 574.81919
A19: Bahrain | B19: Middle East | C19: B2 | D19: =VLOOKUP(C19,$J$9:$K$31,2,FALSE)/10000 -> 0.048632414 | E19: =$E$3+F19 -> 0.1004974 | F19: =IF($E$4="Yes",D19*$E$5,D19) -> 0.053297395 | G19: 0.0295 | H19: =IF(I19="NA","NA",$E$3+I19) -> 0.079529737 | I19: =IF(G19="NA","NA",G19*$E$5) -> 0.032329737 | J19: Ba1 | K19: =C199 -> 220.839
A20: Bangladesh | B20: Asia | C20: Ba3 | D20: =VLOOKUP(C20,$J$9:$K$31,2,FALSE)/10000 -> 0.031810382 | E20: =$E$3+F20 -> 0.082061739 | F20: =IF($E$4="Yes",D20*$E$5,D20) -> 0.034861739 | G20: NA | H20: =IF(I20="NA","NA",$E$3+I20) -> NA | I20: =IF(G20="NA","NA",G20*$E$5) -> NA | J20: Ba2 | K20: =C200 -> 265.48515
A21: Barbados | B21: Caribbean | C21: Caa1 | D21: =VLOOKUP(C21,$J$9:$K$31,2,FALSE)/10000 -> 0.066251699 | E21: =$E$3+F21 -> 0.11980678 | F21: =IF($E$4="Yes",D21*$E$5,D21) -> 0.07260678 | G21: NA | H21: =IF(I21="NA","NA",$E$3+I21) -> NA | I21: =IF(G21="NA","NA",G21*$E$5) -> NA | J21: Ba3 | K21: =C201 -> 318.10382
A22: Belarus | B22: Eastern Europe & Russia | C22: B3 | D22: =VLOOKUP(C22,$J$9:$K$31,2,FALSE)/10000 -> 0.057481919 | E22: =$E$3+F22 -> 0.11019577 | F22: =IF($E$4="Yes",D22*$E$5,D22) -> 0.062995774 | G22: NA | H22: =IF(I22="NA","NA",$E$3+I22) -> NA | I22: =IF(G22="NA","NA",G22*$E$5) -> NA | J22: Baa1 | K22: =C202 -> 141.11373
A23: Belgium | B23: Western Europe | C23: Aa3 | D23: =VLOOKUP(C23,$J$9:$K$31,2,FALSE)/10000 -> 0.005341593 | E23: =$E$3+F23 -> 0.053053976 | F23: =IF($E$4="Yes",D23*$E$5,D23) -> 0.0058539762 | G23: 0.0004 | H23: =IF(I23="NA","NA",$E$3+I23) -> 0.047638369 | I23: =IF(G23="NA","NA",G23*$E$5) -> 0.00043836932 | J23: Baa2 | K23: =C203 -> 168.22032
A24: Belize | B24: Central and South America | C24: Caa3 | D24: =VLOOKUP(C24,$J$9:$K$31,2,FALSE)/10000 -> 0.088335598 | E24: =$E$3+F24 -> 0.14400904 | F24: =IF($E$4="Yes",D24*$E$5,D24) -> 0.09680904 | G24: NA | H24: =IF(I24="NA","NA",$E$3+I24) -> NA | I24: =IF(G24="NA","NA",G24*$E$5) -> NA | J24: Baa3 | K24: =C204 -> 194.52966
A25: Benin | B25: Africa | C25: B2 | D25: =VLOOKUP(C25,$J$9:$K$31,2,FALSE)/10000 -> 0.048632414 | E25: =$E$3+F25 -> 0.1004974 | F25: =IF($E$4="Yes",D25*$E$5,D25) -> 0.053297395 | G25: NA | H25: =IF(I25="NA","NA",$E$3+I25) -> NA | I25: =IF(G25="NA","NA",G25*$E$5) -> NA | J25: C | K25: =C205 -> 1750
A26: Bermuda | B26: Caribbean | C26: A2 | D26: =VLOOKUP(C26,$J$9:$K$31,2,FALSE)/10000 -> 0.0074941753 | E26: =$E$3+F26 -> 0.055413041 | F26: =IF($E$4="Yes",D26*$E$5,D26) -> 0.0082130413 | G26: NA | H26: =IF(I26="NA","NA",$E$3+I26) -> NA | I26: =IF(G26="NA","NA",G26*$E$5) -> NA | J26: Ca | K26: =C206 -> 1060.3461
A27: Bolivia | B27: Central and South America | C27: B2 | D27: =VLOOKUP(C27,$J$9:$K$31,2,FALSE)/10000 -> 0.048632414 | E27: =$E$3+F27 -> 0.1004974 | F27: =IF($E$4="Yes",D27*$E$5,D27) -> 0.053297395 | G27: NA | H27: =IF(I27="NA","NA",$E$3+I27) -> NA | I27: =IF(G27="NA","NA",G27*$E$5) -> NA | J27: =B207 -> Caa1 | K27: =C207 -> 662.51699
A28: Bosnia and Herzegovina | B28: Eastern Europe & Russia | C28: B3 | D28: =VLOOKUP(C28,$J$9:$K$31,2,FALSE)/10000 -> 0.057481919 | E28: =$E$3+F28 -> 0.11019577 | F28: =IF($E$4="Yes",D28*$E$5,D28) -> 0.062995774 | G28: NA | H28: =IF(I28="NA","NA",$E$3+I28) -> NA | I28: =IF(G28="NA","NA",G28*$E$5) -> NA | J28: =B208 -> Caa2 | K28: =C208 -> 795.65819
A29: Botswana | B29: Africa | C29: A2 | D29: =VLOOKUP(C29,$J$9:$K$31,2,FALSE)/10000 -> 0.0074941753 | E29: =$E$3+F29 -> 0.055413041 | F29: =IF($E$4="Yes",D29*$E$5,D29) -> 0.0082130413 | G29: NA | H29: =IF(I29="NA","NA",$E$3+I29) -> NA | I29: =IF(G29="NA","NA",G29*$E$5) -> NA | J29: =B209 -> Caa3 | K29: =C209 -> 883.35598
A30: Brazil | B30: Central and South America | C30: Ba2 | D30: =VLOOKUP(C30,$J$9:$K$31,2,FALSE)/10000 -> 0.026548515 | E30: =$E$3+F30 -> 0.076295136 | F30: =IF($E$4="Yes",D30*$E$5,D30) -> 0.029095136 | G30: 0.0192 | H30: =IF(I30="NA","NA",$E$3+I30) -> 0.068241727 | I30: =IF(G30="NA","NA",G30*$E$5) -> 0.021041727 | J30: NR | K30: =C210 -> NA
A31: Bulgaria | B31: Eastern Europe & Russia | C31: Baa1 | D31: =VLOOKUP(C31,$J$9:$K$31,2,FALSE)/10000 -> 0.014111373 | E31: =$E$3+F31 -> 0.062664982 | F31: =IF($E$4="Yes",D31*$E$5,D31) -> 0.015464982 | G31: 0.0047 | H31: =IF(I31="NA","NA",$E$3+I31) -> 0.052350839 | I31: =IF(G31="NA","NA",G31*$E$5) -> 0.0051508395
A32: Burkina Faso | B32: Africa | C32: B2 | D32: =VLOOKUP(C32,$J$9:$K$31,2,FALSE)/10000 -> 0.048632414 | E32: =$E$3+F32 -> 0.1004974 | F32: =IF($E$4="Yes",D32*$E$5,D32) -> 0.053297395 | G32: NA | H32: =IF(I32="NA","NA",$E$3+I32) -> NA | I32: =IF(G32="NA","NA",G32*$E$5) -> NA
A33: Cambodia | B33: Asia | C33: B2 | D33: =VLOOKUP(C33,$J$9:$K$31,2,FALSE)/10000 -> 0.048632414 | E33: =$E$3+F33 -> 0.1004974 | F33: =IF($E$4="Yes",D33*$E$5,D33) -> 0.053297395 | G33: NA | H33: =IF(I33="NA","NA",$E$3+I33) -> NA | I33: =IF(G33="NA","NA",G33*$E$5) -> NA
A34: Cameroon | B34: Africa | C34: B2 | D34: =VLOOKUP(C34,$J$9:$K$31,2,FALSE)/10000 -> 0.048632414 | E34: =$E$3+F34 -> 0.1004974 | F34: =IF($E$4="Yes",D34*$E$5,D34) -> 0.053297395 | G34: 0.0564 | H34: =IF(I34="NA","NA",$E$3+I34) -> 0.10901007 | I34: =IF(G34="NA","NA",G34*$E$5) -> 0.061810073
A35: Canada | B35: North America | C35: Aaa | D35: =VLOOKUP(C35,$J$9:$K$31,2,FALSE)/10000 -> 0 | E35: =$E$3+F35 -> 0.0472 | F35: =IF($E$4="Yes",D35*$E$5,D35) -> 0 | G35: 0.0019 | H35: =IF(I35="NA","NA",$E$3+I35) -> 0.049282254 | I35: =IF(G35="NA","NA",G35*$E$5) -> 0.0020822542
A36: Cape Verde | B36: Africa | C36: B2 | D36: =VLOOKUP(C36,$J$9:$K$31,2,FALSE)/10000 -> 0.048632414 | E36: =$E$3+F36 -> 0.1004974 | F36: =IF($E$4="Yes",D36*$E$5,D36) -> 0.053297395 | G36: NA | H36: =IF(I36="NA","NA",$E$3+I36) -> NA | I36: =IF(G36="NA","NA",G36*$E$5) -> NA
A37: Cayman Islands | B37: Caribbean | C37: Aa3 | D37: =VLOOKUP(C37,$J$9:$K$31,2,FALSE)/10000 -> 0.005341593 | E37: =$E$3+F37 -> 0.053053976 | F37: =IF($E$4="Yes",D37*$E$5,D37) -> 0.0058539762 | G37: NA | H37: =IF(I37="NA","NA",$E$3+I37) -> NA | I37: =IF(G37="NA","NA",G37*$E$5) -> NA
A38: Chile | B38: Central and South America | C38: A1 | D38: =VLOOKUP(C38,$J$9:$K$31,2,FALSE)/10000 -> 0.006218571 | E38: =$E$3+F38 -> 0.054015077 | F38: =IF($E$4="Yes",D38*$E$5,D38) -> 0.0068150768 | G38: 0.0067 | H38: =IF(I38="NA","NA",$E$3+I38) -> 0.054542686 | I38: =IF(G38="NA","NA",G38*$E$5) -> 0.007342686
A39: China | B39: Asia | C39: A1 | D39: =VLOOKUP(C39,$J$9:$K$31,2,FALSE)/10000 -> 0.006218571 | E39: =$E$3+F39 -> 0.054015077 | F39: =IF($E$4="Yes",D39*$E$5,D39) -> 0.0068150768 | G39: 0.0033 | H39: =IF(I39="NA","NA",$E$3+I39) -> 0.050816547 | I39: =IF(G39="NA","NA",G39*$E$5) -> 0.0036165469
A40: Colombia | B40: Central and South America | C40: Baa2 | D40: =VLOOKUP(C40,$J$9:$K$31,2,FALSE)/10000 -> 0.016822032 | E40: =$E$3+F40 -> 0.065635656 | F40: =IF($E$4="Yes",D40*$E$5,D40) -> 0.018435656 | G40: 0.0129 | H40: =IF(I40="NA","NA",$E$3+I40) -> 0.06133741 | I40: =IF(G40="NA","NA",G40*$E$5) -> 0.01413741
A41: Congo (Democratic Republic of) | B41: Africa | C41: Caa1 | D41: =VLOOKUP(C41,$J$9:$K$31,2,FALSE)/10000 -> 0.066251699 | E41: =$E$3+F41 -> 0.11980678 | F41: =IF($E$4="Yes",D41*$E$5,D41) -> 0.07260678 | G41: NA | H41: =IF(I41="NA","NA",$E$3+I41) -> NA | I41: =IF(G41="NA","NA",G41*$E$5) -> NA
A42: Congo (Republic of) | B42: Africa | C42: Caa2 | D42: =VLOOKUP(C42,$J$9:$K$31,2,FALSE)/10000 -> 0.079565819 | E42: =$E$3+F42 -> 0.13439803 | F42: =IF($E$4="Yes",D42*$E$5,D42) -> 0.087198034 | G42: NA | H42: =IF(I42="NA","NA",$E$3+I42) -> NA | I42: =IF(G42="NA","NA",G42*$E$5) -> NA
A43: Cook Islands | B43: Australia & New Zealand | C43: B1 | D43: =VLOOKUP(C43,$J$9:$K$31,2,FALSE)/10000 -> 0.039782909 | E43: =$E$3+F43 -> 0.090799017 | F43: =IF($E$4="Yes",D43*$E$5,D43) -> 0.043599017 | G43: NA | H43: =IF(I43="NA","NA",$E$3+I43) -> NA | I43: =IF(G43="NA","NA",G43*$E$5) -> NA
A44: Costa Rica | B44: Central and South America | C44: B2 | D44: =VLOOKUP(C44,$J$9:$K$31,2,FALSE)/10000 -> 0.048632414 | E44: =$E$3+F44 -> 0.1004974 | F44: =IF($E$4="Yes",D44*$E$5,D44) -> 0.053297395 | G44: 0.059 | H44: =IF(I44="NA","NA",$E$3+I44) -> 0.11185947 | I44: =IF(G44="NA","NA",G44*$E$5) -> 0.064659474
A45: Côte d'Ivoire | B45: Africa | C45: Ba3 | D45: =VLOOKUP(C45,$J$9:$K$31,2,FALSE)/10000 -> 0.031810382 | E45: =$E$3+F45 -> 0.082061739 | F45: =IF($E$4="Yes",D45*$E$5,D45) -> 0.034861739 | G45: NA | H45: =IF(I45="NA","NA",$E$3+I45) -> NA | I45: =IF(G45="NA","NA",G45*$E$5) -> NA
A46: Croatia | B46: Eastern Europe & Russia | C46: Ba1 | D46: =VLOOKUP(C46,$J$9:$K$31,2,FALSE)/10000 -> 0.0220839 | E46: =$E$3+F46 -> 0.07140226 | F46: =IF($E$4="Yes",D46*$E$5,D46) -> 0.02420226 | G46: 0.0105 | H46: =IF(I46="NA","NA",$E$3+I46) -> 0.058707195 | I46: =IF(G46="NA","NA",G46*$E$5) -> 0.011507195
A47: Cuba | B47: Caribbean | C47: Caa2 | D47: =VLOOKUP(C47,$J$9:$K$31,2,FALSE)/10000 -> 0.079565819 | E47: =$E$3+F47 -> 0.13439803 | F47: =IF($E$4="Yes",D47*$E$5,D47) -> 0.087198034 | G47: NA | H47: =IF(I47="NA","NA",$E$3+I47) -> NA | I47: =IF(G47="NA","NA",G47*$E$5) -> NA
A48: Curacao | B48: Caribbean | C48: A3 | D48: =VLOOKUP(C48,$J$9:$K$31,2,FALSE)/10000 -> 0.010603461 | E48: =$E$3+F48 -> 0.05882058 | F48: =IF($E$4="Yes",D48*$E$5,D48) -> 0.01162058 | G48: NA | H48: =IF(I48="NA","NA",$E$3+I48) -> NA | I48: =IF(G48="NA","NA",G48*$E$5) -> NA
A49: Cyprus | B49: Western Europe | C49: Ba2 | D49: =VLOOKUP(C49,$J$9:$K$31,2,FALSE)/10000 -> 0.026548515 | E49: =$E$3+F49 -> 0.076295136 | F49: =IF($E$4="Yes",D49*$E$5,D49) -> 0.029095136 | G49: 0.0096 | H49: =IF(I49="NA","NA",$E$3+I49) -> 0.057720864 | I49: =IF(G49="NA","NA",G49*$E$5) -> 0.010520864
A50: Czech Republic | B50: Eastern Europe & Russia | C50: Aa3 | D50: =VLOOKUP(C50,$J$9:$K$31,2,FALSE)/10000 -> 0.005341593 | E50: =$E$3+F50 -> 0.053053976 | F50: =IF($E$4="Yes",D50*$E$5,D50) -> 0.0058539762 | G50: 0.0028 | H50: =IF(I50="NA","NA",$E$3+I50) -> 0.050268585 | I50: =IF(G50="NA","NA",G50*$E$5) -> 0.0030685852
A51: Denmark | B51: Western Europe | C51: Aaa | D51: =VLOOKUP(C51,$J$9:$K$31,2,FALSE)/10000 -> 0 | E51: =$E$3+F51 -> 0.0472 | F51: =IF($E$4="Yes",D51*$E$5,D51) -> 0 | G51: 0 | H51: =IF(I51="NA","NA",$E$3+I51) -> 0.0472 | I51: =IF(G51="NA","NA",G51*$E$5) -> 0
A52: Dominican Republic | B52: Caribbean | C52: Ba3 | D52: =VLOOKUP(C52,$J$9:$K$31,2,FALSE)/10000 -> 0.031810382 | E52: =$E$3+F52 -> 0.082061739 | F52: =IF($E$4="Yes",D52*$E$5,D52) -> 0.034861739 | G52: NA | H52: =IF(I52="NA","NA",$E$3+I52) -> NA | I52: =IF(G52="NA","NA",G52*$E$5) -> NA
A53: Ecuador | B53: Central and South America | C53: Caa3 | D53: =VLOOKUP(C53,$J$9:$K$31,2,FALSE)/10000 -> 0.088335598 | E53: =$E$3+F53 -> 0.14400904 | F53: =IF($E$4="Yes",D53*$E$5,D53) -> 0.09680904 | G53: NA | H53: =IF(I53="NA","NA",$E$3+I53) -> NA | I53: =IF(G53="NA","NA",G53*$E$5) -> NA
A54: Egypt | B54: Africa | C54: B2 | D54: =VLOOKUP(C54,$J$9:$K$31,2,FALSE)/10000 -> 0.048632414 | E54: =$E$3+F54 -> 0.1004974 | F54: =IF($E$4="Yes",D54*$E$5,D54) -> 0.053297395 | G54: 0.0385 | H54: =IF(I54="NA","NA",$E$3+I54) -> 0.089393047 | I54: =IF(G54="NA","NA",G54*$E$5) -> 0.042193047
A55: El Salvador | B55: Central and South America | C55: B3 | D55: =VLOOKUP(C55,$J$9:$K$31,2,FALSE)/10000 -> 0.057481919 | E55: =$E$3+F55 -> 0.11019577 | F55: =IF($E$4="Yes",D55*$E$5,D55) -> 0.062995774 | G55: 0.0755 | H55: =IF(I55="NA","NA",$E$3+I55) -> 0.12994221 | I55: =IF(G55="NA","NA",G55*$E$5) -> 0.082742208
A56: Estonia | B56: Eastern Europe & Russia | C56: A1 | D56: =VLOOKUP(C56,$J$9:$K$31,2,FALSE)/10000 -> 0.006218571 | E56: =$E$3+F56 -> 0.054015077 | F56: =IF($E$4="Yes",D56*$E$5,D56) -> 0.0068150768 | G56: 0.0047 | H56: =IF(I56="NA","NA",$E$3+I56) -> 0.052350839 | I56: =IF(G56="NA","NA",G56*$E$5) -> 0.0051508395
A57: Ethiopia | B57: Africa | C57: B2 | D57: =VLOOKUP(C57,$J$9:$K$31,2,FALSE)/10000 -> 0.048632414 | E57: =$E$3+F57 -> 0.1004974 | F57: =IF($E$4="Yes",D57*$E$5,D57) -> 0.053297395 | G57: NA | H57: =IF(I57="NA","NA",$E$3+I57) -> NA | I57: =IF(G57="NA","NA",G57*$E$5) -> NA
A58: Fiji | B58: Asia | C58: Ba3 | D58: =VLOOKUP(C58,$J$9:$K$31,2,FALSE)/10000 -> 0.031810382 | E58: =$E$3+F58 -> 0.082061739 | F58: =IF($E$4="Yes",D58*$E$5,D58) -> 0.034861739 | G58: NA | H58: =IF(I58="NA","NA",$E$3+I58) -> NA | I58: =IF(G58="NA","NA",G58*$E$5) -> NA
A59: Finland | B59: Western Europe | C59: Aa1 | D59: =VLOOKUP(C59,$J$9:$K$31,2,FALSE)/10000 -> 0.0035079119 | E59: =$E$3+F59 -> 0.051044402 | F59: =IF($E$4="Yes",D59*$E$5,D59) -> 0.0038444023 | G59: 0.0002 | H59: =IF(I59="NA","NA",$E$3+I59) -> 0.047419185 | I59: =IF(G59="NA","NA",G59*$E$5) -> 0.00021918466
A60: France | B60: Western Europe | C60: Aa2 | D60: =VLOOKUP(C60,$J$9:$K$31,2,FALSE)/10000 -> 0.0043848898 | E60: =$E$3+F60 -> 0.052005503 | F60: =IF($E$4="Yes",D60*$E$5,D60) -> 0.0048055029 | G60: 0.0009 | H60: =IF(I60="NA","NA",$E$3+I60) -> 0.048186331 | I60: =IF(G60="NA","NA",G60*$E$5) -> 0.00098633096
A61: Gabon | B61: Africa | C61: Caa1 | D61: =VLOOKUP(C61,$J$9:$K$31,2,FALSE)/10000 -> 0.066251699 | E61: =$E$3+F61 -> 0.11980678 | F61: =IF($E$4="Yes",D61*$E$5,D61) -> 0.07260678 | G61: NA | H61: =IF(I61="NA","NA",$E$3+I61) -> NA | I61: =IF(G61="NA","NA",G61*$E$5) -> NA
A62: Georgia | B62: Eastern Europe & Russia | C62: Ba2 | D62: =VLOOKUP(C62,$J$9:$K$31,2,FALSE)/10000 -> 0.026548515 | E62: =$E$3+F62 -> 0.076295136 | F62: =IF($E$4="Yes",D62*$E$5,D62) -> 0.029095136 | G62: NA | H62: =IF(I62="NA","NA",$E$3+I62) -> NA | I62: =IF(G62="NA","NA",G62*$E$5) -> NA
A63: Germany | B63: Western Europe | C63: Aaa | D63: =VLOOKUP(C63,$J$9:$K$31,2,FALSE)/10000 -> 0 | E63: =$E$3+F63 -> 0.0472 | F63: =IF($E$4="Yes",D63*$E$5,D63) -> 0 | G63: 0 | H63: =IF(I63="NA","NA",$E$3+I63) -> 0.0472 | I63: =IF(G63="NA","NA",G63*$E$5) -> 0
A64: Ghana | B64: Africa | C64: B3 | D64: =VLOOKUP(C64,$J$9:$K$31,2,FALSE)/10000 -> 0.057481919 | E64: =$E$3+F64 -> 0.11019577 | F64: =IF($E$4="Yes",D64*$E$5,D64) -> 0.062995774 | G64: NA | H64: =IF(I64="NA","NA",$E$3+I64) -> NA | I64: =IF(G64="NA","NA",G64*$E$5) -> NA
A65: Greece | B65: Western Europe | C65: Ba3 | D65: =VLOOKUP(C65,$J$9:$K$31,2,FALSE)/10000 -> 0.031810382 | E65: =$E$3+F65 -> 0.082061739 | F65: =IF($E$4="Yes",D65*$E$5,D65) -> 0.034861739 | G65: 0.0138 | H65: =IF(I65="NA","NA",$E$3+I65) -> 0.062323741 | I65: =IF(G65="NA","NA",G65*$E$5) -> 0.015123741
A66: Guatemala | B66: Central and South America | C66: Ba1 | D66: =VLOOKUP(C66,$J$9:$K$31,2,FALSE)/10000 -> 0.0220839 | E66: =$E$3+F66 -> 0.07140226 | F66: =IF($E$4="Yes",D66*$E$5,D66) -> 0.02420226 | G66: NA | H66: =IF(I66="NA","NA",$E$3+I66) -> NA | I66: =IF(G66="NA","NA",G66*$E$5) -> NA
A67: Guernsey (States of) | B67: Western Europe | C67: Aaa | D67: =VLOOKUP(C67,$J$9:$K$31,2,FALSE)/10000 -> 0 | E67: =$E$3+F67 -> 0.0472 | F67: =IF($E$4="Yes",D67*$E$5,D67) -> 0 | G67: NA | H67: =IF(I67="NA","NA",$E$3+I67) -> NA | I67: =IF(G67="NA","NA",G67*$E$5) -> NA
A68: Honduras | B68: Central and South America | C68: B1 | D68: =VLOOKUP(C68,$J$9:$K$31,2,FALSE)/10000 -> 0.039782909 | E68: =$E$3+F68 -> 0.090799017 | F68: =IF($E$4="Yes",D68*$E$5,D68) -> 0.043599017 | G68: NA | H68: =IF(I68="NA","NA",$E$3+I68) -> NA | I68: =IF(G68="NA","NA",G68*$E$5) -> NA
A69: Hong Kong | B69: Asia | C69: Aa3 | D69: =VLOOKUP(C69,$J$9:$K$31,2,FALSE)/10000 -> 0.005341593 | E69: =$E$3+F69 -> 0.053053976 | F69: =IF($E$4="Yes",D69*$E$5,D69) -> 0.0058539762 | G69: 0.005 | H69: =IF(I69="NA","NA",$E$3+I69) -> 0.052679616 | I69: =IF(G69="NA","NA",G69*$E$5) -> 0.0054796164
A70: Hungary | B70: Eastern Europe & Russia | C70: Baa3 | D70: =VLOOKUP(C70,$J$9:$K$31,2,FALSE)/10000 -> 0.019452966 | E70: =$E$3+F70 -> 0.068518958 | F70: =IF($E$4="Yes",D70*$E$5,D70) -> 0.021318958 | G70: 0.0071 | H70: =IF(I70="NA","NA",$E$3+I70) -> 0.054981055 | I70: =IF(G70="NA","NA",G70*$E$5) -> 0.0077810553
A71: Iceland | B71: Western Europe | C71: A2 | D71: =VLOOKUP(C71,$J$9:$K$31,2,FALSE)/10000 -> 0.0074941753 | E71: =$E$3+F71 -> 0.055413041 | F71: =IF($E$4="Yes",D71*$E$5,D71) -> 0.0082130413 | G71: 0.0062 | H71: =IF(I71="NA","NA",$E$3+I71) -> 0.053994724 | I71: =IF(G71="NA","NA",G71*$E$5) -> 0.0067947244
A72: India | B72: Asia | C72: Baa3 | D72: =VLOOKUP(C72,$J$9:$K$31,2,FALSE)/10000 -> 0.019452966 | E72: =$E$3+F72 -> 0.068518958 | F72: =IF($E$4="Yes",D72*$E$5,D72) -> 0.021318958 | G72: 0.0101 | H72: =IF(I72="NA","NA",$E$3+I72) -> 0.058268825 | I72: =IF(G72="NA","NA",G72*$E$5) -> 0.011068825
A73: Indonesia | B73: Asia | C73: Baa2 | D73: =VLOOKUP(C73,$J$9:$K$31,2,FALSE)/10000 -> 0.016822032 | E73: =$E$3+F73 -> 0.065635656 | F73: =IF($E$4="Yes",D73*$E$5,D73) -> 0.018435656 | G73: 0.0105 | H73: =IF(I73="NA","NA",$E$3+I73) -> 0.058707195 | I73: =IF(G73="NA","NA",G73*$E$5) -> 0.011507195
A74: Iraq | B74: Middle East | C74: Caa1 | D74: =VLOOKUP(C74,$J$9:$K$31,2,FALSE)/10000 -> 0.066251699 | E74: =$E$3+F74 -> 0.11980678 | F74: =IF($E$4="Yes",D74*$E$5,D74) -> 0.07260678 | G74: 0.0675 | H74: =IF(I74="NA","NA",$E$3+I74) -> 0.12117482 | I74: =IF(G74="NA","NA",G74*$E$5) -> 0.073974822
A75: Ireland | B75: Western Europe | C75: A2 | D75: =VLOOKUP(C75,$J$9:$K$31,2,FALSE)/10000 -> 0.0074941753 | E75: =$E$3+F75 -> 0.055413041 | F75: =IF($E$4="Yes",D75*$E$5,D75) -> 0.0082130413 | G75: 0.0009 | H75: =IF(I75="NA","NA",$E$3+I75) -> 0.048186331 | I75: =IF(G75="NA","NA",G75*$E$5) -> 0.00098633096
A76: Isle of Man | B76: Western Europe | C76: Aa3 | D76: =VLOOKUP(C76,$J$9:$K$31,2,FALSE)/10000 -> 0.005341593 | E76: =$E$3+F76 -> 0.053053976 | F76: =IF($E$4="Yes",D76*$E$5,D76) -> 0.0058539762 | G76: NA | H76: =IF(I76="NA","NA",$E$3+I76) -> NA | I76: =IF(G76="NA","NA",G76*$E$5) -> NA
A77: Israel | B77: Middle East | C77: A1 | D77: =VLOOKUP(C77,$J$9:$K$31,2,FALSE)/10000 -> 0.006218571 | E77: =$E$3+F77 -> 0.054015077 | F77: =IF($E$4="Yes",D77*$E$5,D77) -> 0.0068150768 | G77: 0.0054 | H77: =IF(I77="NA","NA",$E$3+I77) -> 0.053117986 | I77: =IF(G77="NA","NA",G77*$E$5) -> 0.0059179858
A78: Italy | B78: Western Europe | C78: Baa3 | D78: =VLOOKUP(C78,$J$9:$K$31,2,FALSE)/10000 -> 0.019452966 | E78: =$E$3+F78 -> 0.068518958 | F78: =IF($E$4="Yes",D78*$E$5,D78) -> 0.021318958 | G78: 0.012 | H78: =IF(I78="NA","NA",$E$3+I78) -> 0.060351079 | I78: =IF(G78="NA","NA",G78*$E$5) -> 0.013151079
A79: Jamaica | B79: Caribbean | C79: B2 | D79: =VLOOKUP(C79,$J$9:$K$31,2,FALSE)/10000 -> 0.048632414 | E79: =$E$3+F79 -> 0.1004974 | F79: =IF($E$4="Yes",D79*$E$5,D79) -> 0.053297395 | G79: NA | H79: =IF(I79="NA","NA",$E$3+I79) -> NA | I79: =IF(G79="NA","NA",G79*$E$5) -> NA
A80: Japan | B80: Asia | C80: A1 | D80: =VLOOKUP(C80,$J$9:$K$31,2,FALSE)/10000 -> 0.006218571 | E80: =$E$3+F80 -> 0.054015077 | F80: =IF($E$4="Yes",D80*$E$5,D80) -> 0.0068150768 | G80: 0.0005 | H80: =IF(I80="NA","NA",$E$3+I80) -> 0.047747962 | I80: =IF(G80="NA","NA",G80*$E$5) -> 0.00054796164
A81: Jersey (States of) | B81: Western Europe | C81: Aaa | D81: =VLOOKUP(C81,$J$9:$K$31,2,FALSE)/10000 -> 0 | E81: =$E$3+F81 -> 0.0472 | F81: =IF($E$4="Yes",D81*$E$5,D81) -> 0 | G81: NA | H81: =IF(I81="NA","NA",$E$3+I81) -> NA | I81: =IF(G81="NA","NA",G81*$E$5) -> NA
A82: Jordan | B82: Middle East | C82: B1 | D82: =VLOOKUP(C82,$J$9:$K$31,2,FALSE)/10000 -> 0.039782909 | E82: =$E$3+F82 -> 0.090799017 | F82: =IF($E$4="Yes",D82*$E$5,D82) -> 0.043599017 | G82: NA | H82: =IF(I82="NA","NA",$E$3+I82) -> NA | I82: =IF(G82="NA","NA",G82*$E$5) -> NA
